Workbook
Name BIAIDs: '07. BIA'!$B$6:$B$285
Name BusinessUnit: '99. Engine'!$O$4:$O$37
Name BusinessUnits: '10. Risk Assessment'!$C$5
Name BusinessUnits1: ScopeProductsServices[Business Unit]
Name CAPA_BIARefs: '07. BIA'!$B$6:$B$285
Name CAPA_DepRefs: DependencyRegister[Dep ID]
Name CAPA_DocRefs: '18. ISO Docs & Records'!$A$5:$A$24
Name CAPA_DRRefs: ITDRRegister[DR ID]
Name CAPA_RiskRefs: INDEX(RiskAssessment[],0,2)
Name CAPA_RRRefs: RecoveryResponsePlans[R&R ID]
Name DC_1: '09. Risk Assumption Map'!$C$4:$I$4
Name DependencyBIAIDs: '08. Dependency Register'!$C$5:$C$204
Name DivisionSite: '99. Engine'!$P$4:$P$37
Name DivisionSites: ScopeProductsServices[Division / Site]
Name E_1: '06. Application & Equipment'!$I$9
Name E_E: ApplicationEquipmentMaster[Equipment / Building / Utilities]
Name I_A: ApplicationEquipmentMaster[Application]
Name I_S: ApplicationEquipmentMaster[Service]
Name ICT_0: '06. Application & Equipment'!$A$10
Name ICT_1: '06. Application & Equipment'!$G$9
Name ICT_List: '06. Application & Equipment'!$G$9:$H$9
Name lstChainCrit: '99. Engine'!$F$4:$F$7
Name lstCorpCrit: '99. Engine'!$E$4:$E$6
Name lstDepCat: '99. Engine'!$D$4:$D$10
Name lstDRStrategy: '99. Engine'!$J$4:$J$9
Name lstISOStatus: '99. Engine'!$Q$4:$Q$7
Name lstReqCat: '99. Engine'!$M$4:$M$9
Name lstScore: '99. Engine'!$C$4:$C$9
Name lstSPOF: '99. Engine'!$L$4:$L$5
Name lstStatus: '99. Engine'!$G$4:$G$7
Name lstStrategy: '99. Engine'!$H$4:$H$10
Name lstTestResult: '99. Engine'!$I$4:$I$6
Name lstYN: '99. Engine'!$A$4:$A$5
Name lstYPN: '99. Engine'!$B$4:$B$6
Name MTPDMap: '99. Engine'!$S$4:$T$12
Name ProcessProductCodes: ProcessesActivities[Product Code]
Name RequirementStrategyIDs: RequirementsRegister[S&S ID]
Name RiskIDs: INDEX(RiskAssessment[],0,2)
Name S_1: '06. Application & Equipment'!$C$11
Name ScopeNames: ScopeProductsServices[Product / Service]
Name SSIDs: '11. Strategies & Solutions'!$C$5:$C$64
Name StrategyRiskIDs: StrategiesSolutions[Risk ID]

Sheet 00. Document Control
A1: BCM Implementation Toolkit
A2: CONFIDENTIAL | ISO 22301: 7.5 Documented information
A4: Document Control
A5: Version Number | B5: 1
A6: Release Date | B6: 46031
A7: Review Date | B7: =IF(B6="","",EDATE(B6,12)) -> 46396
A8: Status | B8: Draft- under review
A9: Custodian | B9: BCM Function
A11: Prepared by:
A12: Position / Title | B12: Name | C12: Date | D12: Signature
A15: Reviewed by:
A16: Position / Title | B16: Name | C16: Date | D16: Signature
A19: Approved by:
A20: Position / Title | B20: Name | C20: Date | D20: Signature
A23: Version Control History
A24: Version | B24: Effective Date | C24: Change Description | D24: Approved By
A25: =IF($B$5="","",$B$5) -> 1 | B25: =IF($B$6="","",$B$6) -> 46031 | C25: Current controlled version | D25: =IF($B$21="","",$B$21)

Sheet 01. Instructions
A1: How the Toolkit Works - Governance, Colours & Flow (v6)
A2: CONFIDENTIAL: reveals critical organisational infrastructure - distribution restricted to the approved BCM list | ISO 22301: 7.5 Documented information (control & use)
A4: Colour code
A5: WHITE cells | B5: You fill these. Everything the toolkit needs from a human is white.
A6: LIGHT BLUE cells | B6: Automatic - formulas. Do not type here; they read the toolkit and update themselves.
A8: Governance | B8: DATA STEWARD: only the Head of BCM (or a named delegate) issues P&S IDs and unlocks '99. Engine'. REVIEW CYCLE: each BIA block carries Assessment Date / Valid Until - expiry flips the PDCA BIA step to Partial. IDs derive from the static No. column, so sorting or filtering never breaks identity.
A9: Grouping (+/-) | B9: Sheets use Excel grouping: BIA blocks and Risk Assessment associations collapse with the +/- buttons on the left margin; the ISO map groups by clause. Collapse what you are not working on.
A10: Chain & Logic | B10: 1 P&S <-> 1 BIA. Risk = assumption per dependency (1 BIA -> many Risks; 1 Risk -> many BIAs). 1 Risk <-> 1 S&S. 1 S&S -> 1 BCP; 1 BCP -> many S&S. Requirements live one-row-each in 5b. Flow: 0a Profile -> 2 Scope -> 3 BIA -> 3b Dependencies -> 4 RA -> 5 S&S -> 5b Requirements -> 6 RR (BCP) -> 7 Register -> 8 Dashboard -> 11 PDCA -> 14 ISO Map. Docs Register (12) and IT DR (13) plug into the same chain.
A11: Impact Over Time | B11: Nine horizons (6h -> >1 month) with edges on the ERM Operational bands. Score each phase with the ERM rating carried if still down at the END of that phase, using the anchors in '9. Reference Data'. MTPD / RTO / criticality calculate automatically; the value chain overrides upstream with the worst downstream MTPD.
A12: Common Mistakes | B12: x RTO equal to MTPD (toolkit keeps a buffer). x Dependencies typed as long text in one cell - use 3b, one row each. x Requirement flag = Yes in Sheet 5 with no matching row in 5b (the flag turns red). x Deleting rows - clear contents instead. x Scoring without the Sheet 9 anchors.
A13: Growth Headroom | B13: Spare capacity: 45 scope rows, 40 BIA blocks, 28 risks, 60 S&S, 100 BCP rows, 300 requirement rows, 200 dependencies, 30 DR systems. Formulas already cover the spare rows.

Sheet 02. Dashboard
A1: BCM Programme Dashboard - [Company]
A2: Live counters - review weekly - red items need action, not explanation | ISO 22301: 9.1 Monitoring, measurement, analysis, evaluation
A4: Coverage | D4: Risk & Readiness | G4: Governance & Compliance
A5: P&S in scope | B5: =COUNTIF('04. Products & Services'!$I$6:$I$50,"Yes") -> 1 | D5: Risks assessed | E5: =COUNTIF(INDEX(RiskAssessment[],0,2),"RA-*") -> 1 | G5: BCP rows (RR plan) | H5: =COUNTIF('14. Recovery & Response'!$C$6:$C$105,"SS-*") -> 1
A6: BIAs completed | B6: {=SUMPRODUCT(--('07. BIA'!$B$6:$B$285<>""),--ISNUMBER('07. BIA'!$AF$6:$AF$285))} -> 1 | D6: Critical / Significant risks | E6: =COUNTIF('10. Risk Assessment'!$P$5:$P$34,"Critical")+COUNTIF('10. Risk Assessment'!$P$5:$P$34,"Significant") -> 1 | G6: Exercises done / overdue | H6: =COUNT(RecoveryResponsePlans[Actual Exercise Date])&" / "&COUNTIF(RecoveryResponsePlans[Exercise Status],"Overdue") -> 0 / 0
A7: Critical P&S (final) | B7: =COUNTIF('07. BIA'!$W$6:$W$285,"Yes") -> 1 | D7: Priority 1-2 risks (BCP) | E7: =COUNTIF('10. Risk Assessment'!$Q$5:$Q$34,1)+COUNTIF('10. Risk Assessment'!$Q$5:$Q$34,2) -> 1 | G7: DR systems / tested-current | H7: =COUNTIF(ITDRRegister[DR ID],"DR-*")&" / "&COUNTIF(ITDRRegister[Status (auto)],"Tested & Current") -> 0 / 0
A8: P&S-risk associations | B8: {=_xlfn.LET(_xlpm.x,INDEX(RiskAssessment[],0,6),SUMPRODUCT(--(_xlpm.x<>""),LEN(_xlpm.x)-LEN(SUBSTITUTE(_xlpm.x,",",""))+1))} -> 1 | D8: Solutions defined / overdue | E8: =COUNTIF('11. Strategies & Solutions'!$C$5:$C$64,"SS-*")&" / "&COUNTIF('11. Strategies & Solutions'!$T$5:$T$64,"Overdue") -> 1 / 0 | G8: External evidence not evidenced | H8: {=SUMPRODUCT(--(LEFT('18. ISO Docs & Records'!$A$5:$A$24,4)="EXT-"),--(((('18. ISO Docs & Records'!$F$5:$F$24<>"Evidence Filed")*('18. ISO Docs & Records'!$F$5:$F$24<>"Not Applicable"))+('18. ISO Docs & Records'!$S$5:$S$24="Overdue"))>0))} -> 20
A9: Dependencies registered | B9: =COUNTIF('08. Dependency Register'!$B$5:$B$204,"DEP-*") -> 0 | D9: Requirement rows (5b) | E9: =COUNTIF('12. Requirements Register'!$B$5:$B$304,"REQ-*") -> 0 | G9: ISO clauses missing | H9: =COUNTIF('19. ISO 22301 Map'!$D$5:$D$43,"Missing") -> 0
A10: BIA reviews overdue | B10: =SUMPRODUCT(--('07. BIA'!$AG$6:$AG$285<>"")*('07. BIA'!$AG$6:$AG$285<TODAY())) -> 0 | G10: Duplicate S&S mappings | H10: =COUNTIF('11. Strategies & Solutions'!$U$5:$U$64,"DUPLICATE") -> 0
A12: PDCA snapshot
A13: ='17. BCMS Progress (PDCA)'!$C$5 -> Scope & Context (0a Profile + P&S) | B13: ='17. BCMS Progress (PDCA)'!$F$5 -> Partial
A14: ='17. BCMS Progress (PDCA)'!$C$6 -> Leadership & Policy (BCM Policy approved) | B14: ='17. BCMS Progress (PDCA)'!$F$6 -> Not Assessed
A15: ='17. BCMS Progress (PDCA)'!$C$7 -> Corporate BIA (CEO-level criticality) | B15: ='17. BCMS Progress (PDCA)'!$F$7 -> Yes
A16: ='17. BCMS Progress (PDCA)'!$C$8 -> Business Impact Analysis (+ review currency) | B16: ='17. BCMS Progress (PDCA)'!$F$8 -> Yes
A17: ='17. BCMS Progress (PDCA)'!$C$9 -> Dependency Register | B17: ='17. BCMS Progress (PDCA)'!$F$9 -> Yes
A18: ='17. BCMS Progress (PDCA)'!$C$10 -> Risk Assessment (all assumptions rated) | B18: ='17. BCMS Progress (PDCA)'!$F$10 -> Partial
A19: ='17. BCMS Progress (PDCA)'!$C$11 -> Strategies & Solutions (every risk covered) | B19: ='17. BCMS Progress (PDCA)'!$F$11 -> Partial
A20: ='17. BCMS Progress (PDCA)'!$C$12 -> Requirements captured (5b) | B20: ='17. BCMS Progress (PDCA)'!$F$12 -> Partial
A21: ='17. BCMS Progress (PDCA)'!$C$13 -> BCP Development (every S&S in a BCP) | B21: ='17. BCMS Progress (PDCA)'!$F$13 -> Partial
A22: ='17. BCMS Progress (PDCA)'!$C$14 -> IT DR & Cyber Resilience (ISO 22301 8.3 ICT) | B22: ='17. BCMS Progress (PDCA)'!$F$14 -> Not Assessed
A23: ='17. BCMS Progress (PDCA)'!$C$15 -> Exercising & Testing | B23: ='17. BCMS Progress (PDCA)'!$F$15 -> Partial
A24: ='17. BCMS Progress (PDCA)'!$C$16 -> Performance Evaluation (KPIs to Board) | B24: ='17. BCMS Progress (PDCA)'!$F$16 -> Not Assessed
A25: ='17. BCMS Progress (PDCA)'!$C$17 -> Internal Audit of BCMS | B25: ='17. BCMS Progress (PDCA)'!$F$17 -> Not Assessed
A26: ='17. BCMS Progress (PDCA)'!$C$18 -> Management Review | B26: ='17. BCMS Progress (PDCA)'!$F$18 -> Not Assessed
A27: ='17. BCMS Progress (PDCA)'!$C$19 -> Continual Improvement | B27: ='17. BCMS Progress (PDCA)'!$F$19 -> Not Assessed
A29: Corrective Action & Improvement
A30: Open CAPAs | B30: =COUNTIFS(CAPARegister[CAPA ID],"CAPA-*",CAPARegister[Status],"<>Closed",CAPARegister[Status],"<>Cancelled") -> 0 | D30: Overdue CAPAs | E30: =COUNTIF(CAPARegister[Overdue],"Overdue") -> 0 | G30: Effectiveness pending | H30: =COUNTIFS(CAPARegister[Status],"Pending Verification")+COUNTIFS(CAPARegister[Status],"Closed",CAPARegister[Effectiveness],"Pending") -> 0
A31: Critical / High open | B31: =COUNTIFS(CAPARegister[Status],"<>Closed",CAPARegister[Status],"<>Cancelled",CAPARegister[Severity],"Critical")+COUNTIFS(CAPARegister[Status],"<>Closed",CAPARegister[Status],"<>Cancelled",CAPARegister[Severity],"High") -> 0

Sheet 03. Business Unit Profile
A1: Business Unit Profile - BCM Implementation Scope (ISO 22301 Clause 4)
A2: CONFIDENTIAL - Understanding the organization's context, interested parties, and BCMS scope
A4: Section 1 - Organization Identity (ISO 22301 Clause 4.1)
A5: Organization Legal Name
A6: Business Unit Name
A7: Business Unit Code / ID
A8: Parent Division
A9: Headquarters Location
A10: Operating Locations (list)
A11: Date Established
A12: Number of Employees (BU)
A13: Industry Sector
... A16: Section 2 - Leadership & Governance (ISO 22301 Clause 5)
A17: Field | B17: Name | C17: Title | D17: Contact
A27: Section 3 - Internal Context (ISO 22301 Clause 4.1)
A28: Mission Statement
A29: Vision Statement
A30: Strategic Objectives (BU)
A31: Key Products / Services
A32: Annual Revenue (local currency)
A33: Operating Hours
A34: Peak Seasons / Periods
A35: Organizational Structure
A37: Section 4 - External Context (ISO 22301 Clause 4.1)
A38: Primary Regulators
A39: Market Position
... A48: Section 5 - Interested Parties & Requirements (ISO 22301 Clause 4.2)
A49: Interested Party | B49: Requirements / Expectations | C49: How Addressed | D49: Priority
A50: Shareholders / Board
A51: Customers (B2B)
A52: Consumers (End Users)
A53: Employees
A54: Suppliers / Vendors
A55: Regulatory Authorities
A56: Government Agencies
A57: Local Communities
A58: Insurance Providers
A59: Media / Public
A60: Banks / Financial Institutions
A62: Section 6 - BCMS Scope Definition (ISO 22301 Clause 4.3)
... A70: Section 7 - Legal & Regulatory Requirements (ISO 22301 Clause 4.2.2)
A71: Requirement Type | B71: Specific Requirement | C71: Compliance Status | D71: Owner
A83: Section 8 - Critical Assets & Resources Overview
A84: Critical Facilities / Sites
A85: Critical Equipment / Machinery
A86: Critical IT Systems
A87: Critical Data / Records
A88: Key Suppliers (Top 5)
A89: Key Customers (Top 5)
A90: Outsourced Functions
A91: Utility Dependencies
A92: Transportation / Logistics
A93: Specialized Skills / Roles
A95: Section 9 - Risk Appetite & Tolerance (aligned with ERM)
A96: Risk Category | B96: Appetite Level | C96: Tolerance Threshold | D96: Rationale
A97: Financial
A98: Operational
A99: Product / Service Safety
A100: Health, Safety & Environment
A101: Regulatory & Compliance
A102: Reputation
A103: Information Technology
A104: Customer Impact
A106: Section 10 - Profile Approval
A107: Profile Completed By:
A108: Position / Title | B108: Name | C108: Date | D108: Signature
A111: Profile Reviewed By:
A112: Position / Title | B112: Name | C112: Date | D112: Signature
A114: ERM - Business Continuity
A115: Profile Approved By:
A116: Position / Title | B116: Name | C116: Date | D116: Signature
A119: Completed Date: | C119: Next Review Date: | D119: =IF(B119="","",EDATE(B119,12))
A121: Section 11 - Climate Relevance for BCMS Context and Interested Parties
A122: Climate prompt | B122: Assessment / response
A123: Is climate change a relevant external or internal issue for the BCMS? Record the rationale.
A124: Which interested parties have climate-related requirements or expectations relevant to continuity?
A125: Which products, sites, utilities, logistics routes, suppliers or ICT services have climate-sensitive dependencies?
A126: Which acute or chronic climate-related disruption scenarios should be assessed?
A127: Which continuity strategies or actions address material climate-related risks and dependencies?

Sheet 04. Products & Services
A1: Step 1 - Scope: Products & Services + Corporate BIA + Value Chain
A2: Steward issues P&S IDs | ISO 22301: 4.3 Scope; 8.2.2 Prioritised activities
J4: Corporate BIA (CEO-level first check) | N4: Calculated (auto)
A5: No. | B5: P&S ID | C5: Business Unit | D5: Division / Site | E5: Product / Service | F5: Sub-Category | G5: Owner | H5: EVP | I5: In Scope (Y/N) | J5: Corporate BIA Critical | K5: Corporate MBCO (if provided) | L5: Corporate MTPD (if provided) | M5: Corporate MTPD (hours) | N5: BIA Order | O5: BU BIA MTPD
A6: 1 | B6: =IF($E6="","","PS-"&TEXT($A6,"000")) -> PS-001 | C6: ss | D6: hr | E6: cb | I6: Yes | J6: Yes | K6: fill this with the MBCO | M6: {=IF(ISBLANK(L6),"",_xlfn.LET( _xlpm.Num,--_xlfn.TEXTBEFORE(L6," "), _xlpm.Unit,LOWER(_xlfn.TEXTAFTER(L6," ")), _xlfn.SWITCH(_xlpm.Unit, "hour",_xlpm.Num, "hours",_xlpm.Num, "day",_xlpm.Num*24, "days",_xlpm.Num*24, "week",_xlpm.Num*24*7, "weeks",_xlpm.Num*24*7, "month",_xlpm.Num*24*(365.25/12), "months",_xlpm.Num*24*(365.25/12), "") ))} | N6: =IF($I6<>"Yes","",IF($A6="","",COUNTIFS($A$6:$A$50,"<"&$A6,$I$6:$I$50,"Yes")+1)) -> 1 | O6: =IF(ScopeProductsServices[[#This Row],[Product / Service]]="","",IFERROR(_xlfn.LET(_xlpm.r,MATCH(ScopeProductsServices[[#This Row],[Product / Service]],'07. BIA'!$E$6:$E$285,0),_xlpm.b,OFFSET('07. BIA'!$J$6,_xlpm.r-1,0,7,9),IF(COUNT(_xlpm.b)=0,"",IF(MAX(INDEX(_xlpm.b,0,1))>=4,6,IF(MAX(INDEX(_xlpm.b,0,2))>=4,18,IF(MAX(INDEX(_xlpm.b,0,3))>=4,36,IF(MAX(INDEX(_xlpm.b,0,4))>=4,72,IF(MAX(INDEX(_xlpm.b,0,5))>=4,168,IF(MAX(INDEX(_xlpm.b,0,6))>=4,336,IF(MAX(INDEX(_xlpm.b,0,7))>=4,504,IF(MAX(INDEX(_xlpm.b,0,8))>=4,672,"")))))))))),"")) -> 6
A7: 2 | B7: =IF($E7="","","PS-"&TEXT($A7,"000")) | M7: {=IF(ISBLANK(L7),"",_xlfn.LET( _xlpm.Num,--_xlfn.TEXTBEFORE(L7," "), _xlpm.Unit,LOWER(_xlfn.TEXTAFTER(L7," ")), _xlfn.SWITCH(_xlpm.Unit, "hour",_xlpm.Num, "hours",_xlpm.Num, "day",_xlpm.Num*24, "days",_xlpm.Num*24, "week",_xlpm.Num*24*7, "weeks",_xlpm.Num*24*7, "month",_xlpm.Num*24*(365.25/12), "months",_xlpm.Num*24*(365.25/12), "") ))} | N7: =IF($I7<>"Yes","",IF($A7="","",COUNTIFS($A$6:$A$50,"<"&$A7,$I$6:$I$50,"Yes")+1)) | O7: =IF(ScopeProductsServices[[#This Row],[Product / Service]]="","",IFERROR(_xlfn.LET(_xlpm.r,MATCH(ScopeProductsServices[[#This Row],[Product / Service]],'07. BIA'!$E$6:$E$285,0),_xlpm.b,OFFSET('07. BIA'!$J$6,_xlpm.r-1,0,7,9),IF(COUNT(_xlpm.b)=0,"",IF(MAX(INDEX(_xlpm.b,0,1))>=4,6,IF(MAX(INDEX(_xlpm.b,0,2))>=4,18,IF(MAX(INDEX(_xlpm.b,0,3))>=4,36,IF(MAX(INDEX(_xlpm.b,0,4))>=4,72,IF(MAX(INDEX(_xlpm.b,0,5))>=4,168,IF(MAX(INDEX(_xlpm.b,0,6))>=4,336,IF(MAX(INDEX(_xlpm.b,0,7))>=4,504,IF(MAX(INDEX(_xlpm.b,0,8))>=4,672,"")))))))))),""))
A8: 3 | B8: =IF($E8="","","PS-"&TEXT($A8,"000")) | M8: {=IF(ISBLANK(L8),"",_xlfn.LET( _xlpm.Num,--_xlfn.TEXTBEFORE(L8," "), _xlpm.Unit,LOWER(_xlfn.TEXTAFTER(L8," ")), _xlfn.SWITCH(_xlpm.Unit, "hour",_xlpm.Num, "hours",_xlpm.Num, "day",_xlpm.Num*24, "days",_xlpm.Num*24, "week",_xlpm.Num*24*7, "weeks",_xlpm.Num*24*7, "month",_xlpm.Num*24*(365.25/12), "months",_xlpm.Num*24*(365.25/12), "") ))} | N8: =IF($I8<>"Yes","",IF($A8="","",COUNTIFS($A$6:$A$50,"<"&$A8,$I$6:$I$50,"Yes")+1)) | O8: =IF(ScopeProductsServices[[#This Row],[Product / Service]]="","",IFERROR(_xlfn.LET(_xlpm.r,MATCH(ScopeProductsServices[[#This Row],[Product / Service]],'07. BIA'!$E$6:$E$285,0),_xlpm.b,OFFSET('07. BIA'!$J$6,_xlpm.r-1,0,7,9),IF(COUNT(_xlpm.b)=0,"",IF(MAX(INDEX(_xlpm.b,0,1))>=4,6,IF(MAX(INDEX(_xlpm.b,0,2))>=4,18,IF(MAX(INDEX(_xlpm.b,0,3))>=4,36,IF(MAX(INDEX(_xlpm.b,0,4))>=4,72,IF(MAX(INDEX(_xlpm.b,0,5))>=4,168,IF(MAX(INDEX(_xlpm.b,0,6))>=4,336,IF(MAX(INDEX(_xlpm.b,0,7))>=4,504,IF(MAX(INDEX(_xlpm.b,0,8))>=4,672,"")))))))))),""))
A9: 4 | B9: =IF($E9="","","PS-"&TEXT($A9,"000")) | M9: {=IF(ISBLANK(L9),"",_xlfn.LET( _xlpm.Num,--_xlfn.TEXTBEFORE(L9," "), _xlpm.Unit,LOWER(_xlfn.TEXTAFTER(L9," ")), _xlfn.SWITCH(_xlpm.Unit, "hour",_xlpm.Num, "hours",_xlpm.Num, "day",_xlpm.Num*24, "days",_xlpm.Num*24, "week",_xlpm.Num*24*7, "weeks",_xlpm.Num*24*7, "month",_xlpm.Num*24*(365.25/12), "months",_xlpm.Num*24*(365.25/12), "") ))} | N9: =IF($I9<>"Yes","",IF($A9="","",COUNTIFS($A$6:$A$50,"<"&$A9,$I$6:$I$50,"Yes")+1)) | O9: =IF(ScopeProductsServices[[#This Row],[Product / Service]]="","",IFERROR(_xlfn.LET(_xlpm.r,MATCH(ScopeProductsServices[[#This Row],[Product / Service]],'07. BIA'!$E$6:$E$285,0),_xlpm.b,OFFSET('07. BIA'!$J$6,_xlpm.r-1,0,7,9),IF(COUNT(_xlpm.b)=0,"",IF(MAX(INDEX(_xlpm.b,0,1))>=4,6,IF(MAX(INDEX(_xlpm.b,0,2))>=4,18,IF(MAX(INDEX(_xlpm.b,0,3))>=4,36,IF(MAX(INDEX(_xlpm.b,0,4))>=4,72,IF(MAX(INDEX(_xlpm.b,0,5))>=4,168,IF(MAX(INDEX(_xlpm.b,0,6))>=4,336,IF(MAX(INDEX(_xlpm.b,0,7))>=4,504,IF(MAX(INDEX(_xlpm.b,0,8))>=4,672,"")))))))))),""))
A10: 5 | B10: =IF($E10="","","PS-"&TEXT($A10,"000")) | M10: {=IF(ISBLANK(L10),"",_xlfn.LET( _xlpm.Num,--_xlfn.TEXTBEFORE(L10," "), _xlpm.Unit,LOWER(_xlfn.TEXTAFTER(L10," ")), _xlfn.SWITCH(_xlpm.Unit, "hour",_xlpm.Num, "hours",_xlpm.Num, "day",_xlpm.Num*24, "days",_xlpm.Num*24, "week",_xlpm.Num*24*7, "weeks",_xlpm.Num*24*7, "month",_xlpm.Num*24*(365.25/12), "months",_xlpm.Num*24*(365.25/12), "") ))} | N10: =IF($I10<>"Yes","",IF($A10="","",COUNTIFS($A$6:$A$50,"<"&$A10,$I$6:$I$50,"Yes")+1)) | O10: =IF(ScopeProductsServices[[#This Row],[Product / Service]]="","",IFERROR(_xlfn.LET(_xlpm.r,MATCH(ScopeProductsServices[[#This Row],[Product / Service]],'07. BIA'!$E$6:$E$285,0),_xlpm.b,OFFSET('07. BIA'!$J$6,_xlpm.r-1,0,7,9),IF(COUNT(_xlpm.b)=0,"",IF(MAX(INDEX(_xlpm.b,0,1))>=4,6,IF(MAX(INDEX(_xlpm.b,0,2))>=4,18,IF(MAX(INDEX(_xlpm.b,0,3))>=4,36,IF(MAX(INDEX(_xlpm.b,0,4))>=4,72,IF(MAX(INDEX(_xlpm.b,0,5))>=4,168,IF(MAX(INDEX(_xlpm.b,0,6))>=4,336,IF(MAX(INDEX(_xlpm.b,0,7))>=4,504,IF(MAX(INDEX(_xlpm.b,0,8))>=4,672,"")))))))))),""))
A11: 6 | B11: =IF($E11="","","PS-"&TEXT($A11,"000")) | M11: {=IF(ISBLANK(L11),"",_xlfn.LET( _xlpm.Num,--_xlfn.TEXTBEFORE(L11," "), _xlpm.Unit,LOWER(_xlfn.TEXTAFTER(L11," ")), _xlfn.SWITCH(_xlpm.Unit, "hour",_xlpm.Num, "hours",_xlpm.Num, "day",_xlpm.Num*24, "days",_xlpm.Num*24, "week",_xlpm.Num*24*7, "weeks",_xlpm.Num*24*7, "month",_xlpm.Num*24*(365.25/12), "months",_xlpm.Num*24*(365.25/12), "") ))} | N11: =IF($I11<>"Yes","",IF($A11="","",COUNTIFS($A$6:$A$50,"<"&$A11,$I$6:$I$50,"Yes")+1)) | O11: =IF(ScopeProductsServices[[#This Row],[Product / Service]]="","",IFERROR(_xlfn.LET(_xlpm.r,MATCH(ScopeProductsServices[[#This Row],[Product / Service]],'07. BIA'!$E$6:$E$285,0),_xlpm.b,OFFSET('07. BIA'!$J$6,_xlpm.r-1,0,7,9),IF(COUNT(_xlpm.b)=0,"",IF(MAX(INDEX(_xlpm.b,0,1))>=4,6,IF(MAX(INDEX(_xlpm.b,0,2))>=4,18,IF(MAX(INDEX(_xlpm.b,0,3))>=4,36,IF(MAX(INDEX(_xlpm.b,0,4))>=4,72,IF(MAX(INDEX(_xlpm.b,0,5))>=4,168,IF(MAX(INDEX(_xlpm.b,0,6))>=4,336,IF(MAX(INDEX(_xlpm.b,0,7))>=4,504,IF(MAX(INDEX(_xlpm.b,0,8))>=4,672,"")))))))))),""))
A12: 7 | B12: =IF($E12="","","PS-"&TEXT($A12,"000")) | M12: {=IF(ISBLANK(L12),"",_xlfn.LET( _xlpm.Num,--_xlfn.TEXTBEFORE(L12," "), _xlpm.Unit,LOWER(_xlfn.TEXTAFTER(L12," ")), _xlfn.SWITCH(_xlpm.Unit, "hour",_xlpm.Num, "hours",_xlpm.Num, "day",_xlpm.Num*24, "days",_xlpm.Num*24, "week",_xlpm.Num*24*7, "weeks",_xlpm.Num*24*7, "month",_xlpm.Num*24*(365.25/12), "months",_xlpm.Num*24*(365.25/12), "") ))} | N12: =IF($I12<>"Yes","",IF($A12="","",COUNTIFS($A$6:$A$50,"<"&$A12,$I$6:$I$50,"Yes")+1)) | O12: =IF(ScopeProductsServices[[#This Row],[Product / Service]]="","",IFERROR(_xlfn.LET(_xlpm.r,MATCH(ScopeProductsServices[[#This Row],[Product / Service]],'07. BIA'!$E$6:$E$285,0),_xlpm.b,OFFSET('07. BIA'!$J$6,_xlpm.r-1,0,7,9),IF(COUNT(_xlpm.b)=0,"",IF(MAX(INDEX(_xlpm.b,0,1))>=4,6,IF(MAX(INDEX(_xlpm.b,0,2))>=4,18,IF(MAX(INDEX(_xlpm.b,0,3))>=4,36,IF(MAX(INDEX(_xlpm.b,0,4))>=4,72,IF(MAX(INDEX(_xlpm.b,0,5))>=4,168,IF(MAX(INDEX(_xlpm.b,0,6))>=4,336,IF(MAX(INDEX(_xlpm.b,0,7))>=4,504,IF(MAX(INDEX(_xlpm.b,0,8))>=4,672,"")))))))))),""))
A13: 8 | B13: =IF($E13="","","PS-"&TEXT($A13,"000")) | M13: {=IF(ISBLANK(L13),"",_xlfn.LET( _xlpm.Num,--_xlfn.TEXTBEFORE(L13," "), _xlpm.Unit,LOWER(_xlfn.TEXTAFTER(L13," ")), _xlfn.SWITCH(_xlpm.Unit, "hour",_xlpm.Num, "hours",_xlpm.Num, "day",_xlpm.Num*24, "days",_xlpm.Num*24, "week",_xlpm.Num*24*7, "weeks",_xlpm.Num*24*7, "month",_xlpm.Num*24*(365.25/12), "months",_xlpm.Num*24*(365.25/12), "") ))} | N13: =IF($I13<>"Yes","",IF($A13="","",COUNTIFS($A$6:$A$50,"<"&$A13,$I$6:$I$50,"Yes")+1)) | O13: =IF(ScopeProductsServices[[#This Row],[Product / Service]]="","",IFERROR(_xlfn.LET(_xlpm.r,MATCH(ScopeProductsServices[[#This Row],[Product / Service]],'07. BIA'!$E$6:$E$285,0),_xlpm.b,OFFSET('07. BIA'!$J$6,_xlpm.r-1,0,7,9),IF(COUNT(_xlpm.b)=0,"",IF(MAX(INDEX(_xlpm.b,0,1))>=4,6,IF(MAX(INDEX(_xlpm.b,0,2))>=4,18,IF(MAX(INDEX(_xlpm.b,0,3))>=4,36,IF(MAX(INDEX(_xlpm.b,0,4))>=4,72,IF(MAX(INDEX(_xlpm.b,0,5))>=4,168,IF(MAX(INDEX(_xlpm.b,0,6))>=4,336,IF(MAX(INDEX(_xlpm.b,0,7))>=4,504,IF(MAX(INDEX(_xlpm.b,0,8))>=4,672,"")))))))))),""))
A14: 9 | B14: =IF($E14="","","PS-"&TEXT($A14,"000")) | M14: {=IF(ISBLANK(L14),"",_xlfn.LET( _xlpm.Num,--_xlfn.TEXTBEFORE(L14," "), _xlpm.Unit,LOWER(_xlfn.TEXTAFTER(L14," ")), _xlfn.SWITCH(_xlpm.Unit, "hour",_xlpm.Num, "hours",_xlpm.Num, "day",_xlpm.Num*24, "days",_xlpm.Num*24, "week",_xlpm.Num*24*7, "weeks",_xlpm.Num*24*7, "month",_xlpm.Num*24*(365.25/12), "months",_xlpm.Num*24*(365.25/12), "") ))} | N14: =IF($I14<>"Yes","",IF($A14="","",COUNTIFS($A$6:$A$50,"<"&$A14,$I$6:$I$50,"Yes")+1)) | O14: =IF(ScopeProductsServices[[#This Row],[Product / Service]]="","",IFERROR(_xlfn.LET(_xlpm.r,MATCH(ScopeProductsServices[[#This Row],[Product / Service]],'07. BIA'!$E$6:$E$285,0),_xlpm.b,OFFSET('07. BIA'!$J$6,_xlpm.r-1,0,7,9),IF(COUNT(_xlpm.b)=0,"",IF(MAX(INDEX(_xlpm.b,0,1))>=4,6,IF(MAX(INDEX(_xlpm.b,0,2))>=4,18,IF(MAX(INDEX(_xlpm.b,0,3))>=4,36,IF(MAX(INDEX(_xlpm.b,0,4))>=4,72,IF(MAX(INDEX(_xlpm.b,0,5))>=4,168,IF(MAX(INDEX(_xlpm.b,0,6))>=4,336,IF(MAX(INDEX(_xlpm.b,0,7))>=4,504,IF(MAX(INDEX(_xlpm.b,0,8))>=4,672,"")))))))))),""))
A15: 10 | B15: =IF($E15="","","PS-"&TEXT($A15,"000")) | M15: {=IF(ISBLANK(L15),"",_xlfn.LET( _xlpm.Num,--_xlfn.TEXTBEFORE(L15," "), _xlpm.Unit,LOWER(_xlfn.TEXTAFTER(L15," ")), _xlfn.SWITCH(_xlpm.Unit, "hour",_xlpm.Num, "hours",_xlpm.Num, "day",_xlpm.Num*24, "days",_xlpm.Num*24, "week",_xlpm.Num*24*7, "weeks",_xlpm.Num*24*7, "month",_xlpm.Num*24*(365.25/12), "months",_xlpm.Num*24*(365.25/12), "") ))} | N15: =IF($I15<>"Yes","",IF($A15="","",COUNTIFS($A$6:$A$50,"<"&$A15,$I$6:$I$50,"Yes")+1)) | O15: =IF(ScopeProductsServices[[#This Row],[Product / Service]]="","",IFERROR(_xlfn.LET(_xlpm.r,MATCH(ScopeProductsServices[[#This Row],[Product / Service]],'07. BIA'!$E$6:$E$285,0),_xlpm.b,OFFSET('07. BIA'!$J$6,_xlpm.r-1,0,7,9),IF(COUNT(_xlpm.b)=0,"",IF(MAX(INDEX(_xlpm.b,0,1))>=4,6,IF(MAX(INDEX(_xlpm.b,0,2))>=4,18,IF(MAX(INDEX(_xlpm.b,0,3))>=4,36,IF(MAX(INDEX(_xlpm.b,0,4))>=4,72,IF(MAX(INDEX(_xlpm.b,0,5))>=4,168,IF(MAX(INDEX(_xlpm.b,0,6))>=4,336,IF(MAX(INDEX(_xlpm.b,0,7))>=4,504,IF(MAX(INDEX(_xlpm.b,0,8))>=4,672,"")))))))))),""))
A16: 11 | B16: =IF($E16="","","PS-"&TEXT($A16,"000")) | M16: {=IF(ISBLANK(L16),"",_xlfn.LET( _xlpm.Num,--_xlfn.TEXTBEFORE(L16," "), _xlpm.Unit,LOWER(_xlfn.TEXTAFTER(L16," ")), _xlfn.SWITCH(_xlpm.Unit, "hour",_xlpm.Num, "hours",_xlpm.Num, "day",_xlpm.Num*24, "days",_xlpm.Num*24, "week",_xlpm.Num*24*7, "weeks",_xlpm.Num*24*7, "month",_xlpm.Num*24*(365.25/12), "months",_xlpm.Num*24*(365.25/12), "") ))} | N16: =IF($I16<>"Yes","",IF($A16="","",COUNTIFS($A$6:$A$50,"<"&$A16,$I$6:$I$50,"Yes")+1)) | O16: =IF(ScopeProductsServices[[#This Row],[Product / Service]]="","",IFERROR(_xlfn.LET(_xlpm.r,MATCH(ScopeProductsServices[[#This Row],[Product / Service]],'07. BIA'!$E$6:$E$285,0),_xlpm.b,OFFSET('07. BIA'!$J$6,_xlpm.r-1,0,7,9),IF(COUNT(_xlpm.b)=0,"",IF(MAX(INDEX(_xlpm.b,0,1))>=4,6,IF(MAX(INDEX(_xlpm.b,0,2))>=4,18,IF(MAX(INDEX(_xlpm.b,0,3))>=4,36,IF(MAX(INDEX(_xlpm.b,0,4))>=4,72,IF(MAX(INDEX(_xlpm.b,0,5))>=4,168,IF(MAX(INDEX(_xlpm.b,0,6))>=4,336,IF(MAX(INDEX(_xlpm.b,0,7))>=4,504,IF(MAX(INDEX(_xlpm.b,0,8))>=4,672,"")))))))))),""))
A17: 12 | B17: =IF($E17="","","PS-"&TEXT($A17,"000")) | M17: {=IF(ISBLANK(L17),"",_xlfn.LET( _xlpm.Num,--_xlfn.TEXTBEFORE(L17," "), _xlpm.Unit,LOWER(_xlfn.TEXTAFTER(L17," ")), _xlfn.SWITCH(_xlpm.Unit, "hour",_xlpm.Num, "hours",_xlpm.Num, "day",_xlpm.Num*24, "days",_xlpm.Num*24, "week",_xlpm.Num*24*7, "weeks",_xlpm.Num*24*7, "month",_xlpm.Num*24*(365.25/12), "months",_xlpm.Num*24*(365.25/12), "") ))} | N17: =IF($I17<>"Yes","",IF($A17="","",COUNTIFS($A$6:$A$50,"<"&$A17,$I$6:$I$50,"Yes")+1)) | O17: =IF(ScopeProductsServices[[#This Row],[Product / Service]]="","",IFERROR(_xlfn.LET(_xlpm.r,MATCH(ScopeProductsServices[[#This Row],[Product / Service]],'07. BIA'!$E$6:$E$285,0),_xlpm.b,OFFSET('07. BIA'!$J$6,_xlpm.r-1,0,7,9),IF(COUNT(_xlpm.b)=0,"",IF(MAX(INDEX(_xlpm.b,0,1))>=4,6,IF(MAX(INDEX(_xlpm.b,0,2))>=4,18,IF(MAX(INDEX(_xlpm.b,0,3))>=4,36,IF(MAX(INDEX(_xlpm.b,0,4))>=4,72,IF(MAX(INDEX(_xlpm.b,0,5))>=4,168,IF(MAX(INDEX(_xlpm.b,0,6))>=4,336,IF(MAX(INDEX(_xlpm.b,0,7))>=4,504,IF(MAX(INDEX(_xlpm.b,0,8))>=4,672,"")))))))))),""))
A18: 13 | B18: =IF($E18="","","PS-"&TEXT($A18,"000")) | M18: {=IF(ISBLANK(L18),"",_xlfn.LET( _xlpm.Num,--_xlfn.TEXTBEFORE(L18," "), _xlpm.Unit,LOWER(_xlfn.TEXTAFTER(L18," ")), _xlfn.SWITCH(_xlpm.Unit, "hour",_xlpm.Num, "hours",_xlpm.Num, "day",_xlpm.Num*24, "days",_xlpm.Num*24, "week",_xlpm.Num*24*7, "weeks",_xlpm.Num*24*7, "month",_xlpm.Num*24*(365.25/12), "months",_xlpm.Num*24*(365.25/12), "") ))} | N18: =IF($I18<>"Yes","",IF($A18="","",COUNTIFS($A$6:$A$50,"<"&$A18,$I$6:$I$50,"Yes")+1)) | O18: =IF(ScopeProductsServices[[#This Row],[Product / Service]]="","",IFERROR(_xlfn.LET(_xlpm.r,MATCH(ScopeProductsServices[[#This Row],[Product / Service]],'07. BIA'!$E$6:$E$285,0),_xlpm.b,OFFSET('07. BIA'!$J$6,_xlpm.r-1,0,7,9),IF(COUNT(_xlpm.b)=0,"",IF(MAX(INDEX(_xlpm.b,0,1))>=4,6,IF(MAX(INDEX(_xlpm.b,0,2))>=4,18,IF(MAX(INDEX(_xlpm.b,0,3))>=4,36,IF(MAX(INDEX(_xlpm.b,0,4))>=4,72,IF(MAX(INDEX(_xlpm.b,0,5))>=4,168,IF(MAX(INDEX(_xlpm.b,0,6))>=4,336,IF(MAX(INDEX(_xlpm.b,0,7))>=4,504,IF(MAX(INDEX(_xlpm.b,0,8))>=4,672,"")))))))))),""))
... A50: 45 | B50: =IF($E50="","","PS-"&TEXT($A50,"000")) | M50: {=IF(ISBLANK(L50),"",_xlfn.LET( _xlpm.Num,--_xlfn.TEXTBEFORE(L50," "), _xlpm.Unit,LOWER(_xlfn.TEXTAFTER(L50," ")), _xlfn.SWITCH(_xlpm.Unit, "hour",_xlpm.Num, "hours",_xlpm.Num, "day",_xlpm.Num*24, "days",_xlpm.Num*24, "week",_xlpm.Num*24*7, "weeks",_xlpm.Num*24*7, "month",_xlpm.Num*24*(365.25/12), "months",_xlpm.Num*24*(365.25/12), "") ))} | N50: =IF($I50<>"Yes","",IF($A50="","",COUNTIFS($A$6:$A$50,"<"&$A50,$I$6:$I$50,"Yes")+1)) | O50: =IF(ScopeProductsServices[[#This Row],[Product / Service]]="","",IFERROR(_xlfn.LET(_xlpm.r,MATCH(ScopeProductsServices[[#This Row],[Product / Service]],'07. BIA'!$E$6:$E$285,0),_xlpm.b,OFFSET('07. BIA'!$J$6,_xlpm.r-1,0,7,9),IF(COUNT(_xlpm.b)=0,"",IF(MAX(INDEX(_xlpm.b,0,1))>=4,6,IF(MAX(INDEX(_xlpm.b,0,2))>=4,18,IF(MAX(INDEX(_xlpm.b,0,3))>=4,36,IF(MAX(INDEX(_xlpm.b,0,4))>=4,72,IF(MAX(INDEX(_xlpm.b,0,5))>=4,168,IF(MAX(INDEX(_xlpm.b,0,6))>=4,336,IF(MAX(INDEX(_xlpm.b,0,7))>=4,504,IF(MAX(INDEX(_xlpm.b,0,8))>=4,672,"")))))))))),""))

Sheet 05. Processes & Activities
A1: Step 1 - Scope: Products & Services + Corporate BIA + Value Chain
A2: Steward issues P&S IDs | ISO 22301: 4.3 Scope; 8.2.2 Prioritised activities
A4: Sl # | B4: Product Code | C4: Product & Services | D4: Activities performed within the process | E4: Frequency of Activity | F4: Peak Period | G4: Rationale for Peak Period | H4: Current Staff to Perform Activity | I4: Activity Can be Performed Remotely? | J4: BlA level MTPD in hours | K4: BIA Level RTO in hours | L4: Remark
A5: 1 | B5: PS-001 | C5: =IFERROR(VLOOKUP(B5,'04. Products & Services'!$B$6:$E$50,4,FALSE),"") -> cb | J5: =IF($B5="","",_xlfn.LET(_xlpm.x,_xlfn.XLOOKUP($B5,'07. BIA'!$F$6:$F$285,'07. BIA'!$AA$6:$AA$285,""),IF(_xlpm.x=0,"",_xlpm.x))) -> 6 | K5: =IF($B5="","",_xlfn.LET(_xlpm.x,_xlfn.XLOOKUP($B5,'07. BIA'!$F$6:$F$285,'07. BIA'!$AD$6:$AD$285,""),IF(_xlpm.x=0,"",_xlpm.x))) -> 168
A6: 2 | C6: =IFERROR(VLOOKUP(B6,'04. Products & Services'!$B$6:$E$50,4,FALSE),"") | J6: =IF($B6="","",_xlfn.LET(_xlpm.x,_xlfn.XLOOKUP($B6,'07. BIA'!$F$6:$F$285,'07. BIA'!$AA$6:$AA$285,""),IF(_xlpm.x=0,"",_xlpm.x))) | K6: =IF($B6="","",_xlfn.LET(_xlpm.x,_xlfn.XLOOKUP($B6,'07. BIA'!$F$6:$F$285,'07. BIA'!$AD$6:$AD$285,""),IF(_xlpm.x=0,"",_xlpm.x)))
A7: 3 | C7: =IFERROR(VLOOKUP(B7,'04. Products & Services'!$B$6:$E$50,4,FALSE),"") | J7: =IF($B7="","",_xlfn.LET(_xlpm.x,_xlfn.XLOOKUP($B7,'07. BIA'!$F$6:$F$285,'07. BIA'!$AA$6:$AA$285,""),IF(_xlpm.x=0,"",_xlpm.x))) | K7: =IF($B7="","",_xlfn.LET(_xlpm.x,_xlfn.XLOOKUP($B7,'07. BIA'!$F$6:$F$285,'07. BIA'!$AD$6:$AD$285,""),IF(_xlpm.x=0,"",_xlpm.x)))
A8: 4 | C8: =IFERROR(VLOOKUP(B8,'04. Products & Services'!$B$6:$E$50,4,FALSE),"") | J8: =IF($B8="","",_xlfn.LET(_xlpm.x,_xlfn.XLOOKUP($B8,'07. BIA'!$F$6:$F$285,'07. BIA'!$AA$6:$AA$285,""),IF(_xlpm.x=0,"",_xlpm.x))) | K8: =IF($B8="","",_xlfn.LET(_xlpm.x,_xlfn.XLOOKUP($B8,'07. BIA'!$F$6:$F$285,'07. BIA'!$AD$6:$AD$285,""),IF(_xlpm.x=0,"",_xlpm.x)))
A9: 5 | C9: =IFERROR(VLOOKUP(B9,'04. Products & Services'!$B$6:$E$50,4,FALSE),"") | J9: =IF($B9="","",_xlfn.LET(_xlpm.x,_xlfn.XLOOKUP($B9,'07. BIA'!$F$6:$F$285,'07. BIA'!$AA$6:$AA$285,""),IF(_xlpm.x=0,"",_xlpm.x))) | K9: =IF($B9="","",_xlfn.LET(_xlpm.x,_xlfn.XLOOKUP($B9,'07. BIA'!$F$6:$F$285,'07. BIA'!$AD$6:$AD$285,""),IF(_xlpm.x=0,"",_xlpm.x)))
A10: 6 | C10: =IFERROR(VLOOKUP(B10,'04. Products & Services'!$B$6:$E$50,4,FALSE),"") | J10: =IF($B10="","",_xlfn.LET(_xlpm.x,_xlfn.XLOOKUP($B10,'07. BIA'!$F$6:$F$285,'07. BIA'!$AA$6:$AA$285,""),IF(_xlpm.x=0,"",_xlpm.x))) | K10: =IF($B10="","",_xlfn.LET(_xlpm.x,_xlfn.XLOOKUP($B10,'07. BIA'!$F$6:$F$285,'07. BIA'!$AD$6:$AD$285,""),IF(_xlpm.x=0,"",_xlpm.x)))
A11: 7 | C11: =IFERROR(VLOOKUP(B11,'04. Products & Services'!$B$6:$E$50,4,FALSE),"") | J11: =IF($B11="","",_xlfn.LET(_xlpm.x,_xlfn.XLOOKUP($B11,'07. BIA'!$F$6:$F$285,'07. BIA'!$AA$6:$AA$285,""),IF(_xlpm.x=0,"",_xlpm.x))) | K11: =IF($B11="","",_xlfn.LET(_xlpm.x,_xlfn.XLOOKUP($B11,'07. BIA'!$F$6:$F$285,'07. BIA'!$AD$6:$AD$285,""),IF(_xlpm.x=0,"",_xlpm.x)))
A12: 8 | C12: =IFERROR(VLOOKUP(B12,'04. Products & Services'!$B$6:$E$50,4,FALSE),"") | J12: =IF($B12="","",_xlfn.LET(_xlpm.x,_xlfn.XLOOKUP($B12,'07. BIA'!$F$6:$F$285,'07. BIA'!$AA$6:$AA$285,""),IF(_xlpm.x=0,"",_xlpm.x))) | K12: =IF($B12="","",_xlfn.LET(_xlpm.x,_xlfn.XLOOKUP($B12,'07. BIA'!$F$6:$F$285,'07. BIA'!$AD$6:$AD$285,""),IF(_xlpm.x=0,"",_xlpm.x)))
A13: 9 | C13: =IFERROR(VLOOKUP(B13,'04. Products & Services'!$B$6:$E$50,4,FALSE),"") | J13: =IF($B13="","",_xlfn.LET(_xlpm.x,_xlfn.XLOOKUP($B13,'07. BIA'!$F$6:$F$285,'07. BIA'!$AA$6:$AA$285,""),IF(_xlpm.x=0,"",_xlpm.x))) | K13: =IF($B13="","",_xlfn.LET(_xlpm.x,_xlfn.XLOOKUP($B13,'07. BIA'!$F$6:$F$285,'07. BIA'!$AD$6:$AD$285,""),IF(_xlpm.x=0,"",_xlpm.x)))
A14: 10 | C14: =IFERROR(VLOOKUP(B14,'04. Products & Services'!$B$6:$E$50,4,FALSE),"") | J14: =IF($B14="","",_xlfn.LET(_xlpm.x,_xlfn.XLOOKUP($B14,'07. BIA'!$F$6:$F$285,'07. BIA'!$AA$6:$AA$285,""),IF(_xlpm.x=0,"",_xlpm.x))) | K14: =IF($B14="","",_xlfn.LET(_xlpm.x,_xlfn.XLOOKUP($B14,'07. BIA'!$F$6:$F$285,'07. BIA'!$AD$6:$AD$285,""),IF(_xlpm.x=0,"",_xlpm.x)))
A15: 11 | C15: =IFERROR(VLOOKUP(B15,'04. Products & Services'!$B$6:$E$50,4,FALSE),"") | J15: =IF($B15="","",_xlfn.LET(_xlpm.x,_xlfn.XLOOKUP($B15,'07. BIA'!$F$6:$F$285,'07. BIA'!$AA$6:$AA$285,""),IF(_xlpm.x=0,"",_xlpm.x))) | K15: =IF($B15="","",_xlfn.LET(_xlpm.x,_xlfn.XLOOKUP($B15,'07. BIA'!$F$6:$F$285,'07. BIA'!$AD$6:$AD$285,""),IF(_xlpm.x=0,"",_xlpm.x)))
A16: 12 | C16: =IFERROR(VLOOKUP(B16,'04. Products & Services'!$B$6:$E$50,4,FALSE),"") | J16: =IF($B16="","",_xlfn.LET(_xlpm.x,_xlfn.XLOOKUP($B16,'07. BIA'!$F$6:$F$285,'07. BIA'!$AA$6:$AA$285,""),IF(_xlpm.x=0,"",_xlpm.x))) | K16: =IF($B16="","",_xlfn.LET(_xlpm.x,_xlfn.XLOOKUP($B16,'07. BIA'!$F$6:$F$285,'07. BIA'!$AD$6:$AD$285,""),IF(_xlpm.x=0,"",_xlpm.x)))
A17: 13 | C17: =IFERROR(VLOOKUP(B17,'04. Products & Services'!$B$6:$E$50,4,FALSE),"") | J17: =IF($B17="","",_xlfn.LET(_xlpm.x,_xlfn.XLOOKUP($B17,'07. BIA'!$F$6:$F$285,'07. BIA'!$AA$6:$AA$285,""),IF(_xlpm.x=0,"",_xlpm.x))) | K17: =IF($B17="","",_xlfn.LET(_xlpm.x,_xlfn.XLOOKUP($B17,'07. BIA'!$F$6:$F$285,'07. BIA'!$AD$6:$AD$285,""),IF(_xlpm.x=0,"",_xlpm.x)))
... A211: 207 | C211: =IFERROR(VLOOKUP(B211,'04. Products & Services'!$B$6:$E$50,4,FALSE),"") | J211: =IF($B211="","",_xlfn.LET(_xlpm.x,_xlfn.XLOOKUP($B211,'07. BIA'!$F$6:$F$285,'07. BIA'!$AA$6:$AA$285,""),IF(_xlpm.x=0,"",_xlpm.x))) | K211: =IF($B211="","",_xlfn.LET(_xlpm.x,_xlfn.XLOOKUP($B211,'07. BIA'!$F$6:$F$285,'07. BIA'!$AD$6:$AD$285,""),IF(_xlpm.x=0,"",_xlpm.x)))

Sheet 06. Application & Equipment
A1: Step 3c. Application equip list
A2: one row per dependency | ISO 22301: 8.2.2 Dependencies & supporting resources
A5: Note: | B5: Here list of applications and services related to IT and equipment and applications related to OT to be captured by BU team.
F8: Sl # | G8: ICT | I8: Equipment / Building / Utilities
A9: IT dependencies | C9: Sub dependencies | F9: Column1 | G9: Application | H9: Service | I9: Equipment / Building / Utilities
A10: ICT | C10: Application | F10: 1
A11: Equipment / Building / Utilities | C11: Service | F11: 2
C12: Equipment / Building / Utilities | F12: 3
F13: 4
F14: 5
F15: 6
F16: 7
F17: 8
F18: 9
F19: 10
F20: 11
F21: 12
F22: 13
F23: 14
F24: 15
... F34: 25

Sheet 07. BIA
A1: Step 2 - Business Impact Analysis (Product & Service Level)
A2: ISO 22301: 8.2.2 Business impact analysis
A4: No. | B4: BIA # | C4: Business Unit | D4: Division / Site | E4: Product / Service (auto - value-chain order) | F4: Product / Service ID | G4: Risk Identification | I4: Impact Type | J4: Process Unavailability Impact Over Time (1-5) - anchors in Sheet 9 | S4: Criticality (Corporate cascade) | X4: MBCO & Recovery Targets | AH4: Linked Records (auto)
G5: Dependencies | H5: Will it interrupt the operation? (Y/N) | J5: Up to 6 Hours | K5: Up to 18 Hours | L5: Up to 36 Hours | M5: Up to 3 Days | N5: Up to 1 Week | O5: Up to 2 Weeks | P5: Up to 3 Weeks | Q5: Up to 1 month | R5: More than 1 Month | S5: Max Impact (auto) | T5: Max Impact Type (auto) | U5: Corporate Critical (auto) | V5: BU Critical (Y/N) | W5: Critical - Final (auto) | X5: MBCO - Corporate (auto) | Y5: MBCO - BU | Z5: Rationale / Supporting Reasons | AA5: MTPD (auto) hours | AB5: CEO MTPD | AC5: RTO | AD5: RTO (auto) in hours | AE5: RPO (fill if Data/ICT = Yes) in hours | AF5: Assessment Date | AG5: Valid Until (auto +12 mo) | AH5: Risk IDs | AI5: S&S # | AJ5: R&R IDs
A6: 1 | B6: =IF($E6="","","BIA-"&TEXT(1,"000")) -> BIA-001 | C6: =IFERROR(INDEX(BusinessUnits1,MATCH(A6,'04. Products & Services'!$N$6:$N$50,0)),"") -> ss | D6: =IFERROR(INDEX(DivisionSites,MATCH(A6,'04. Products & Services'!$N$6:$N$50,0)),"") -> hr | E6: =IFERROR(INDEX(ScopeNames,MATCH(A6,'04. Products & Services'!$N$6:$N$50,0)),"") -> cb | F6: =_xlfn.XLOOKUP(E6,'04. Products & Services'!$E$5:$E$50,'04. Products & Services'!$B$5:$B$50,"") -> PS-001 | G6: People | H6: Yes | I6: Financial | J6: 1 | K6: 2 | L6: 3 | M6: 3 | N6: 4 | O6: 4 | S6: =IF(COUNT(J6:R12)=0,"",MAX(J6:R12)) -> 5 | T6: =IF($S$6="","",IF(COUNT(J6:R6)=0,"",IF(MAX(J6:R6)>3,$I6,""))) -> Financial | U6: {=IF($E6="","",_xlfn.LET(_xlpm.matches,_xlfn._xlws.FILTER('04. Products & Services'!$J$6:$J$50,'04. Products & Services'!$E$6:$E$50=$E6,""),_xlpm.n,COUNTIF($E$6:$E6,$E6),_xlpm.v,IFERROR(INDEX(_xlpm.matches,_xlpm.n),""),IF(OR(_xlpm.v="",_xlpm.v=0),"",_xlpm.v)))} -> Yes | V6: Yes | W6: =IF($E6="","",IF(OR($U6="Yes",$V6="Yes"),"Yes",IF(AND($U6="No",$V6="No"),"No",IF(AND($U6="Under Evaluation",$V6="No"),"Under Evaluation","")))) -> Yes | X6: =IF($E6="","",IFERROR(_xlfn.LET(_xlpm.v,INDEX('04. Products & Services'!$K$6:$K$50,MATCH($E6,ScopeNames,0)),IF(_xlpm.v="","",_xlpm.v)),"")) -> fill this with the MBCO | AA6: =IF($E6="","",IF(COUNT(J6:R12)=0,"",IF(MAX(J6:J12)>=4,6,IF(MAX(K6:K12)>=4,18,IF(MAX(L6:L12)>=4,36,IF(MAX(M6:M12)>=4,72,IF(MAX(N6:N12)>=4,168,IF(MAX(O6:O12)>=4,336,IF(MAX(P6:P12)>=4,504,IF(MAX(Q6:Q12)>=4,672,IF(MAX(R6:R12)>=4,"",""))))))))))) -> 6 | AB6: =IF($F6="","",IFERROR(VLOOKUP($F6,'04. Products & Services'!$B$5:$M$50,12,0),"")) | AC6: 7 days | AD6: {=IF(ISBLANK(AC6),"",_xlfn.LET( _xlpm.Num,--_xlfn.TEXTBEFORE(AC6," "), _xlpm.Unit,LOWER(_xlfn.TEXTAFTER(AC6," ")), _xlfn.SWITCH(_xlpm.Unit, "hour",_xlpm.Num, "hours",_xlpm.Num, "day",_xlpm.Num*24, "days",_xlpm.Num*24, "week",_xlpm.Num*24*7, "weeks",_xlpm.Num*24*7, "month",_xlpm.Num*24*(365.25/12), "months",_xlpm.Num*24*(365.25/12), "") ))} -> 168 | AF6: =TODAY() -> 46300 | AG6: =IF($AF6="","",DATE(YEAR($AF6)+1,MONTH($AF6),DAY($AF6))) -> 46665 | AH6: {=IF($B6="","",_xlfn.LET(_xlpm.ids,'15. BCM Risk Register'!$A$6:$A$65,_xlpm.links,'15. BCM Risk Register'!$I$6:$I$65,_xlpm.hit,ISNUMBER(SEARCH(","&$B6&",",","&SUBSTITUTE(_xlpm.links," ","")&",")),IFERROR(_xlfn.TEXTJOIN(", ",TRUE,_xlfn.UNIQUE(_xlfn._xlws.FILTER(_xlpm.ids,_xlpm.hit*(_xlpm.ids<>"")))),"Not Created")))} -> RA-001 | AI6: {=IF($B6="","",_xlfn.LET(_xlpm.ids,'15. BCM Risk Register'!$L$6:$L$65,_xlpm.links,'15. BCM Risk Register'!$I$6:$I$65,_xlpm.hit,ISNUMBER(SEARCH(","&$B6&",",","&SUBSTITUTE(_xlpm.links," ","")&",")),IFERROR(_xlfn.TEXTJOIN(", ",TRUE,_xlfn.UNIQUE(_xlfn._xlws.FILTER(_xlpm.ids,_xlpm.hit*(_xlpm.ids<>"")*(_xlpm.ids<>"Not Created")))),"Not Created")))} -> SS-030 | AJ6: {=IF($B6="","",_xlfn.LET(_xlpm.ids,'15. BCM Risk Register'!$K$6:$K$65,_xlpm.links,'15. BCM Risk Register'!$I$6:$I$65,_xlpm.hit,ISNUMBER(SEARCH(","&$B6&",",","&SUBSTITUTE(_xlpm.links," ","")&",")),IFERROR(_xlfn.TEXTJOIN(", ",TRUE,_xlfn.UNIQUE(_xlfn._xlws.FILTER(_xlpm.ids,_xlpm.hit*(_xlpm.ids<>"")*(_xlpm.ids<>"Not Created")))),"Not Created")))} -> RR-001
G7: ICT | I7: Operational | K7: 5 | T7: =IF($S$6="","",IF(COUNT(J7:R7)=0,"",IF(MAX(J7:R7)>3,$I7,""))) -> Operational
G8: Data / Info | I8: Product / Service Safety | K8: 1 | L8: 1 | M8: 1 | N8: 1 | O8: 1 | P8: 1 | Q8: 1 | R8: 1 | T8: =IF($S$6="","",IF(COUNT(J8:R8)=0,"",IF(MAX(J8:R8)>3,$I8,"")))
G9: 3rd Party | I9: Health, Safety & Environment | K9: 2 | L9: 2 | M9: 2 | N9: 2 | O9: 2 | P9: 2 | Q9: 2 | R9: 2 | T9: =IF($S$6="","",IF(COUNT(J9:R9)=0,"",IF(MAX(J9:R9)>3,$I9,"")))
G10: Equipment / Building / Utilities | I10: Regulatory & Compliance | K10: 3 | L10: 3 | M10: 3 | N10: 3 | O10: 3 | P10: 3 | Q10: 3 | R10: 3 | T10: =IF($S$6="","",IF(COUNT(J10:R10)=0,"",IF(MAX(J10:R10)>3,$I10,"")))
G11: Pre-Service | I11: Reputation | K11: 4 | L11: 4 | M11: 4 | N11: 4 | O11: 4 | P11: 4 | T11: =IF($S$6="","",IF(COUNT(J11:R11)=0,"",IF(MAX(J11:R11)>3,$I11,""))) -> Reputation
G12: Post-Service | I12: Information Technology | J12: 5 | K12: 5 | T12: =IF($S$6="","",IF(COUNT(J12:R12)=0,"",IF(MAX(J12:R12)>3,$I12,""))) -> Information Technology
A13: 2 | B13: =IF($E13="","","BIA-"&TEXT(2,"000")) | C13: =IFERROR(INDEX(BusinessUnits1,MATCH(A13,'04. Products & Services'!$N$6:$N$50,0)),"") | D13: =IFERROR(INDEX(DivisionSites,MATCH(A13,'04. Products & Services'!$N$6:$N$50,0)),"") | E13: =IFERROR(INDEX(ScopeNames,MATCH(A13,'04. Products & Services'!$N$6:$N$50,0)),"") | F13: =_xlfn.XLOOKUP(E13,'04. Products & Services'!$E$5:$E$50,'04. Products & Services'!$B$5:$B$50,"") | G13: People | I13: Financial | S13: =IF(COUNT(J13:R19)=0,"",MAX(J13:R19)) | T13: =IF($S$13="","",IF(COUNT(J13:R13)=0,"",IF(MAX(J13:R13)>3,$I13,""))) | U13: {=IF($E13="","",_xlfn.LET(_xlpm.matches,_xlfn._xlws.FILTER('04. Products & Services'!$J$6:$J$50,'04. Products & Services'!$E$6:$E$50=$E13,""),_xlpm.n,COUNTIF($E$6:$E13,$E13),_xlpm.v,IFERROR(INDEX(_xlpm.matches,_xlpm.n),""),IF(OR(_xlpm.v="",_xlpm.v=0),"",_xlpm.v)))} | W13: =IF($E13="","",IF(OR($U13="Yes",$V13="Yes"),"Yes",IF(AND($U13="No",$V13="No"),"No",IF(AND($U13="Under Evaluation",$V13="No"),"Under Evaluation","")))) | X13: =IF($E13="","",IFERROR(_xlfn.LET(_xlpm.v,INDEX('04. Products & Services'!$K$6:$K$50,MATCH($E13,ScopeNames,0)),IF(_xlpm.v="","",_xlpm.v)),"")) | AA13: =IF($E13="","",IF(COUNT(J13:R19)=0,"",IF(MAX(J13:J19)>=4,6,IF(MAX(K13:K19)>=4,18,IF(MAX(L13:L19)>=4,36,IF(MAX(M13:M19)>=4,72,IF(MAX(N13:N19)>=4,168,IF(MAX(O13:O19)>=4,336,IF(MAX(P13:P19)>=4,504,IF(MAX(Q13:Q19)>=4,672,IF(MAX(R13:R19)>=4,"",""))))))))))) | AB13: =IF($F13="","",IFERROR(VLOOKUP($F13,'04. Products & Services'!$B$5:$M$50,12,0),"")) | AD13: {=IF(ISBLANK(AC13),"",_xlfn.LET( _xlpm.Num,--_xlfn.TEXTBEFORE(AC13," "), _xlpm.Unit,LOWER(_xlfn.TEXTAFTER(AC13," ")), _xlfn.SWITCH(_xlpm.Unit, "hour",_xlpm.Num, "hours",_xlpm.Num, "day",_xlpm.Num*24, "days",_xlpm.Num*24, "week",_xlpm.Num*24*7, "weeks",_xlpm.Num*24*7, "month",_xlpm.Num*24*(365.25/12), "months",_xlpm.Num*24*(365.25/12), "") ))} | AG13: =IF($AF13="","",DATE(YEAR($AF13)+1,MONTH($AF13),DAY($AF13))) | AH13: {=IF($B13="","",_xlfn.LET(_xlpm.ids,'15. BCM Risk Register'!$A$6:$A$65,_xlpm.links,'15. BCM Risk Register'!$I$6:$I$65,_xlpm.hit,ISNUMBER(SEARCH(","&$B13&",",","&SUBSTITUTE(_xlpm.links," ","")&",")),IFERROR(_xlfn.TEXTJOIN(", ",TRUE,_xlfn.UNIQUE(_xlfn._xlws.FILTER(_xlpm.ids,_xlpm.hit*(_xlpm.ids<>"")))),"Not Created")))} | AI13: {=IF($B13="","",_xlfn.LET(_xlpm.ids,'15. BCM Risk Register'!$L$6:$L$65,_xlpm.links,'15. BCM Risk Register'!$I$6:$I$65,_xlpm.hit,ISNUMBER(SEARCH(","&$B13&",",","&SUBSTITUTE(_xlpm.links," ","")&",")),IFERROR(_xlfn.TEXTJOIN(", ",TRUE,_xlfn.UNIQUE(_xlfn._xlws.FILTER(_xlpm.ids,_xlpm.hit*(_xlpm.ids<>"")*(_xlpm.ids<>"Not Created")))),"Not Created")))} | AJ13: {=IF($B13="","",_xlfn.LET(_xlpm.ids,'15. BCM Risk Register'!$K$6:$K$65,_xlpm.links,'15. BCM Risk Register'!$I$6:$I$65,_xlpm.hit,ISNUMBER(SEARCH(","&$B13&",",","&SUBSTITUTE(_xlpm.links," ","")&",")),IFERROR(_xlfn.TEXTJOIN(", ",TRUE,_xlfn.UNIQUE(_xlfn._xlws.FILTER(_xlpm.ids,_xlpm.hit*(_xlpm.ids<>"")*(_xlpm.ids<>"Not Created")))),"Not Created")))}
G14: ICT | I14: Operational | T14: =IF($S$13="","",IF(COUNT(J14:R14)=0,"",IF(MAX(J14:R14)>3,$I14,"")))
G15: Data / Info | I15: Product / Service Safety | T15: =IF($S$13="","",IF(COUNT(J15:R15)=0,"",IF(MAX(J15:R15)>3,$I15,"")))
G16: 3rd Party | I16: Health, Safety & Environment | T16: =IF($S$13="","",IF(COUNT(J16:R16)=0,"",IF(MAX(J16:R16)>3,$I16,"")))
G17: Equipment / Building / Utilities | I17: Regulatory & Compliance | T17: =IF($S$13="","",IF(COUNT(J17:R17)=0,"",IF(MAX(J17:R17)>3,$I17,"")))
G18: Pre-Service | I18: Reputation | T18: =IF($S$13="","",IF(COUNT(J18:R18)=0,"",IF(MAX(J18:R18)>3,$I18,"")))
G19: Post-Service | I19: Information Technology | T19: =IF($S$13="","",IF(COUNT(J19:R19)=0,"",IF(MAX(J19:R19)>3,$I19,"")))
A20: 3 | B20: =IF($E20="","","BIA-"&TEXT(3,"000")) | C20: =IFERROR(INDEX(BusinessUnits1,MATCH(A20,'04. Products & Services'!$N$6:$N$50,0)),"") | D20: =IFERROR(INDEX(DivisionSites,MATCH(A20,'04. Products & Services'!$N$6:$N$50,0)),"") | E20: =IFERROR(INDEX(ScopeNames,MATCH(A20,'04. Products & Services'!$N$6:$N$50,0)),"") | F20: =_xlfn.XLOOKUP(E20,'04. Products & Services'!$E$5:$E$50,'04. Products & Services'!$B$5:$B$50,"") | G20: People | I20: Financial | S20: =IF(COUNT(J20:R26)=0,"",MAX(J20:R26)) | T20: =IF($S$20="","",IF(COUNT(J20:R20)=0,"",IF(MAX(J20:R20)>3,$I20,""))) | U20: {=IF($E20="","",_xlfn.LET(_xlpm.matches,_xlfn._xlws.FILTER('04. Products & Services'!$J$6:$J$50,'04. Products & Services'!$E$6:$E$50=$E20,""),_xlpm.n,COUNTIF($E$6:$E20,$E20),_xlpm.v,IFERROR(INDEX(_xlpm.matches,_xlpm.n),""),IF(OR(_xlpm.v="",_xlpm.v=0),"",_xlpm.v)))} | W20: =IF($E20="","",IF(OR($U20="Yes",$V20="Yes"),"Yes",IF(AND($U20="No",$V20="No"),"No",IF(AND($U20="Under Evaluation",$V20="No"),"Under Evaluation","")))) | X20: =IF($E20="","",IFERROR(_xlfn.LET(_xlpm.v,INDEX('04. Products & Services'!$K$6:$K$50,MATCH($E20,ScopeNames,0)),IF(_xlpm.v="","",_xlpm.v)),"")) | AA20: =IF($E20="","",IF(COUNT(J20:R26)=0,"",IF(MAX(J20:J26)>=4,6,IF(MAX(K20:K26)>=4,18,IF(MAX(L20:L26)>=4,36,IF(MAX(M20:M26)>=4,72,IF(MAX(N20:N26)>=4,168,IF(MAX(O20:O26)>=4,336,IF(MAX(P20:P26)>=4,504,IF(MAX(Q20:Q26)>=4,672,IF(MAX(R20:R26)>=4,"",""))))))))))) | AB20: =IF($F20="","",IFERROR(VLOOKUP($F20,'04. Products & Services'!$B$5:$M$50,12,0),"")) | AD20: {=IF(ISBLANK(AC20),"",_xlfn.LET( _xlpm.Num,--_xlfn.TEXTBEFORE(AC20," "), _xlpm.Unit,LOWER(_xlfn.TEXTAFTER(AC20," ")), _xlfn.SWITCH(_xlpm.Unit, "hour",_xlpm.Num, "hours",_xlpm.Num, "day",_xlpm.Num*24, "days",_xlpm.Num*24, "week",_xlpm.Num*24*7, "weeks",_xlpm.Num*24*7, "month",_xlpm.Num*24*(365.25/12), "months",_xlpm.Num*24*(365.25/12), "") ))} | AG20: =IF($AF20="","",DATE(YEAR($AF20)+1,MONTH($AF20),DAY($AF20))) | AH20: {=IF($B20="","",_xlfn.LET(_xlpm.ids,'15. BCM Risk Register'!$A$6:$A$65,_xlpm.links,'15. BCM Risk Register'!$I$6:$I$65,_xlpm.hit,ISNUMBER(SEARCH(","&$B20&",",","&SUBSTITUTE(_xlpm.links," ","")&",")),IFERROR(_xlfn.TEXTJOIN(", ",TRUE,_xlfn.UNIQUE(_xlfn._xlws.FILTER(_xlpm.ids,_xlpm.hit*(_xlpm.ids<>"")))),"Not Created")))} | AI20: {=IF($B20="","",_xlfn.LET(_xlpm.ids,'15. BCM Risk Register'!$L$6:$L$65,_xlpm.links,'15. BCM Risk Register'!$I$6:$I$65,_xlpm.hit,ISNUMBER(SEARCH(","&$B20&",",","&SUBSTITUTE(_xlpm.links," ","")&",")),IFERROR(_xlfn.TEXTJOIN(", ",TRUE,_xlfn.UNIQUE(_xlfn._xlws.FILTER(_xlpm.ids,_xlpm.hit*(_xlpm.ids<>"")*(_xlpm.ids<>"Not Created")))),"Not Created")))} | AJ20: {=IF($B20="","",_xlfn.LET(_xlpm.ids,'15. BCM Risk Register'!$K$6:$K$65,_xlpm.links,'15. BCM Risk Register'!$I$6:$I$65,_xlpm.hit,ISNUMBER(SEARCH(","&$B20&",",","&SUBSTITUTE(_xlpm.links," ","")&",")),IFERROR(_xlfn.TEXTJOIN(", ",TRUE,_xlfn.UNIQUE(_xlfn._xlws.FILTER(_xlpm.ids,_xlpm.hit*(_xlpm.ids<>"")*(_xlpm.ids<>"Not Created")))),"Not Created")))}
G21: ICT | I21: Operational | T21: =IF($S$20="","",IF(COUNT(J21:R21)=0,"",IF(MAX(J21:R21)>3,$I21,"")))
G22: Data / Info | I22: Product / Service Safety | T22: =IF($S$20="","",IF(COUNT(J22:R22)=0,"",IF(MAX(J22:R22)>3,$I22,"")))
G23: 3rd Party | I23: Health, Safety & Environment | T23: =IF($S$20="","",IF(COUNT(J23:R23)=0,"",IF(MAX(J23:R23)>3,$I23,"")))
G24: Equipment / Building / Utilities | I24: Regulatory & Compliance | T24: =IF($S$20="","",IF(COUNT(J24:R24)=0,"",IF(MAX(J24:R24)>3,$I24,"")))
G25: Pre-Service | I25: Reputation | T25: =IF($S$20="","",IF(COUNT(J25:R25)=0,"",IF(MAX(J25:R25)>3,$I25,"")))
G26: Post-Service | I26: Information Technology | T26: =IF($S$20="","",IF(COUNT(J26:R26)=0,"",IF(MAX(J26:R26)>3,$I26,"")))
A27: 4 | B27: =IF($E27="","","BIA-"&TEXT(4,"000")) | C27: =IFERROR(INDEX(BusinessUnits1,MATCH(A27,'04. Products & Services'!$N$6:$N$50,0)),"") | D27: =IFERROR(INDEX(DivisionSites,MATCH(A27,'04. Products & Services'!$N$6:$N$50,0)),"") | E27: =IFERROR(INDEX(ScopeNames,MATCH(A27,'04. Products & Services'!$N$6:$N$50,0)),"") | F27: =_xlfn.XLOOKUP(E27,'04. Products & Services'!$E$5:$E$50,'04. Products & Services'!$B$5:$B$50,"") | G27: People | I27: Financial | S27: =IF(COUNT(J27:R33)=0,"",MAX(J27:R33)) | T27: =IF($S$27="","",IF(COUNT(J27:R27)=0,"",IF(MAX(J27:R27)>3,$I27,""))) | U27: {=IF($E27="","",_xlfn.LET(_xlpm.matches,_xlfn._xlws.FILTER('04. Products & Services'!$J$6:$J$50,'04. Products & Services'!$E$6:$E$50=$E27,""),_xlpm.n,COUNTIF($E$6:$E27,$E27),_xlpm.v,IFERROR(INDEX(_xlpm.matches,_xlpm.n),""),IF(OR(_xlpm.v="",_xlpm.v=0),"",_xlpm.v)))} | W27: =IF($E27="","",IF(OR($U27="Yes",$V27="Yes"),"Yes",IF(AND($U27="No",$V27="No"),"No",IF(AND($U27="Under Evaluation",$V27="No"),"Under Evaluation","")))) | X27: =IF($E27="","",IFERROR(_xlfn.LET(_xlpm.v,INDEX('04. Products & Services'!$K$6:$K$50,MATCH($E27,ScopeNames,0)),IF(_xlpm.v="","",_xlpm.v)),"")) | AA27: =IF($E27="","",IF(COUNT(J27:R33)=0,"",IF(MAX(J27:J33)>=4,6,IF(MAX(K27:K33)>=4,18,IF(MAX(L27:L33)>=4,36,IF(MAX(M27:M33)>=4,72,IF(MAX(N27:N33)>=4,168,IF(MAX(O27:O33)>=4,336,IF(MAX(P27:P33)>=4,504,IF(MAX(Q27:Q33)>=4,672,IF(MAX(R27:R33)>=4,"",""))))))))))) | AB27: =IF($F27="","",IFERROR(VLOOKUP($F27,'04. Products & Services'!$B$5:$M$50,12,0),"")) | AD27: {=IF(ISBLANK(AC27),"",_xlfn.LET( _xlpm.Num,--_xlfn.TEXTBEFORE(AC27," "), _xlpm.Unit,LOWER(_xlfn.TEXTAFTER(AC27," ")), _xlfn.SWITCH(_xlpm.Unit, "hour",_xlpm.Num, "hours",_xlpm.Num, "day",_xlpm.Num*24, "days",_xlpm.Num*24, "week",_xlpm.Num*24*7, "weeks",_xlpm.Num*24*7, "month",_xlpm.Num*24*(365.25/12), "months",_xlpm.Num*24*(365.25/12), "") ))} | AG27: =IF($AF27="","",DATE(YEAR($AF27)+1,MONTH($AF27),DAY($AF27))) | AH27: {=IF($B27="","",_xlfn.LET(_xlpm.ids,'15. BCM Risk Register'!$A$6:$A$65,_xlpm.links,'15. BCM Risk Register'!$I$6:$I$65,_xlpm.hit,ISNUMBER(SEARCH(","&$B27&",",","&SUBSTITUTE(_xlpm.links," ","")&",")),IFERROR(_xlfn.TEXTJOIN(", ",TRUE,_xlfn.UNIQUE(_xlfn._xlws.FILTER(_xlpm.ids,_xlpm.hit*(_xlpm.ids<>"")))),"Not Created")))} | AI27: {=IF($B27="","",_xlfn.LET(_xlpm.ids,'15. BCM Risk Register'!$L$6:$L$65,_xlpm.links,'15. BCM Risk Register'!$I$6:$I$65,_xlpm.hit,ISNUMBER(SEARCH(","&$B27&",",","&SUBSTITUTE(_xlpm.links," ","")&",")),IFERROR(_xlfn.TEXTJOIN(", ",TRUE,_xlfn.UNIQUE(_xlfn._xlws.FILTER(_xlpm.ids,_xlpm.hit*(_xlpm.ids<>"")*(_xlpm.ids<>"Not Created")))),"Not Created")))} | AJ27: {=IF($B27="","",_xlfn.LET(_xlpm.ids,'15. BCM Risk Register'!$K$6:$K$65,_xlpm.links,'15. BCM Risk Register'!$I$6:$I$65,_xlpm.hit,ISNUMBER(SEARCH(","&$B27&",",","&SUBSTITUTE(_xlpm.links," ","")&",")),IFERROR(_xlfn.TEXTJOIN(", ",TRUE,_xlfn.UNIQUE(_xlfn._xlws.FILTER(_xlpm.ids,_xlpm.hit*(_xlpm.ids<>"")*(_xlpm.ids<>"Not Created")))),"Not Created")))}
G28: ICT | I28: Operational | T28: =IF($S$27="","",IF(COUNT(J28:R28)=0,"",IF(MAX(J28:R28)>3,$I28,"")))
G29: Data / Info | I29: Product / Service Safety | T29: =IF($S$27="","",IF(COUNT(J29:R29)=0,"",IF(MAX(J29:R29)>3,$I29,"")))
G30: 3rd Party | I30: Health, Safety & Environment | T30: =IF($S$27="","",IF(COUNT(J30:R30)=0,"",IF(MAX(J30:R30)>3,$I30,"")))
G31: Equipment / Building / Utilities | I31: Regulatory & Compliance | T31: =IF($S$27="","",IF(COUNT(J31:R31)=0,"",IF(MAX(J31:R31)>3,$I31,"")))
G32: Pre-Service | I32: Reputation | T32: =IF($S$27="","",IF(COUNT(J32:R32)=0,"",IF(MAX(J32:R32)>3,$I32,"")))
G33: Post-Service | I33: Information Technology | T33: =IF($S$27="","",IF(COUNT(J33:R33)=0,"",IF(MAX(J33:R33)>3,$I33,"")))
A34: 5 | B34: =IF($E34="","","BIA-"&TEXT(5,"000")) | C34: =IFERROR(INDEX(BusinessUnits1,MATCH(A34,'04. Products & Services'!$N$6:$N$50,0)),"") | D34: =IFERROR(INDEX(DivisionSites,MATCH(A34,'04. Products & Services'!$N$6:$N$50,0)),"") | E34: =IFERROR(INDEX(ScopeNames,MATCH(A34,'04. Products & Services'!$N$6:$N$50,0)),"") | F34: =_xlfn.XLOOKUP(E34,'04. Products & Services'!$E$5:$E$50,'04. Products & Services'!$B$5:$B$50,"") | G34: People | I34: Financial | S34: =IF(COUNT(J34:R40)=0,"",MAX(J34:R40)) | T34: =IF($S$34="","",IF(COUNT(J34:R34)=0,"",IF(MAX(J34:R34)>3,$I34,""))) | U34: {=IF($E34="","",_xlfn.LET(_xlpm.matches,_xlfn._xlws.FILTER('04. Products & Services'!$J$6:$J$50,'04. Products & Services'!$E$6:$E$50=$E34,""),_xlpm.n,COUNTIF($E$6:$E34,$E34),_xlpm.v,IFERROR(INDEX(_xlpm.matches,_xlpm.n),""),IF(OR(_xlpm.v="",_xlpm.v=0),"",_xlpm.v)))} | W34: =IF($E34="","",IF(OR($U34="Yes",$V34="Yes"),"Yes",IF(AND($U34="No",$V34="No"),"No",IF(AND($U34="Under Evaluation",$V34="No"),"Under Evaluation","")))) | X34: =IF($E34="","",IFERROR(_xlfn.LET(_xlpm.v,INDEX('04. Products & Services'!$K$6:$K$50,MATCH($E34,ScopeNames,0)),IF(_xlpm.v="","",_xlpm.v)),"")) | AA34: =IF($E34="","",IF(COUNT(J34:R40)=0,"",IF(MAX(J34:J40)>=4,6,IF(MAX(K34:K40)>=4,18,IF(MAX(L34:L40)>=4,36,IF(MAX(M34:M40)>=4,72,IF(MAX(N34:N40)>=4,168,IF(MAX(O34:O40)>=4,336,IF(MAX(P34:P40)>=4,504,IF(MAX(Q34:Q40)>=4,672,IF(MAX(R34:R40)>=4,"",""))))))))))) | AB34: =IF($F34="","",IFERROR(VLOOKUP($F34,'04. Products & Services'!$B$5:$M$50,12,0),"")) | AD34: {=IF(ISBLANK(AC34),"",_xlfn.LET( _xlpm.Num,--_xlfn.TEXTBEFORE(AC34," "), _xlpm.Unit,LOWER(_xlfn.TEXTAFTER(AC34," ")), _xlfn.SWITCH(_xlpm.Unit, "hour",_xlpm.Num, "hours",_xlpm.Num, "day",_xlpm.Num*24, "days",_xlpm.Num*24, "week",_xlpm.Num*24*7, "weeks",_xlpm.Num*24*7, "month",_xlpm.Num*24*(365.25/12), "months",_xlpm.Num*24*(365.25/12), "") ))} | AG34: =IF($AF34="","",DATE(YEAR($AF34)+1,MONTH($AF34),DAY($AF34))) | AH34: {=IF($B34="","",_xlfn.LET(_xlpm.ids,'15. BCM Risk Register'!$A$6:$A$65,_xlpm.links,'15. BCM Risk Register'!$I$6:$I$65,_xlpm.hit,ISNUMBER(SEARCH(","&$B34&",",","&SUBSTITUTE(_xlpm.links," ","")&",")),IFERROR(_xlfn.TEXTJOIN(", ",TRUE,_xlfn.UNIQUE(_xlfn._xlws.FILTER(_xlpm.ids,_xlpm.hit*(_xlpm.ids<>"")))),"Not Created")))} | AI34: {=IF($B34="","",_xlfn.LET(_xlpm.ids,'15. BCM Risk Register'!$L$6:$L$65,_xlpm.links,'15. BCM Risk Register'!$I$6:$I$65,_xlpm.hit,ISNUMBER(SEARCH(","&$B34&",",","&SUBSTITUTE(_xlpm.links," ","")&",")),IFERROR(_xlfn.TEXTJOIN(", ",TRUE,_xlfn.UNIQUE(_xlfn._xlws.FILTER(_xlpm.ids,_xlpm.hit*(_xlpm.ids<>"")*(_xlpm.ids<>"Not Created")))),"Not Created")))} | AJ34: {=IF($B34="","",_xlfn.LET(_xlpm.ids,'15. BCM Risk Register'!$K$6:$K$65,_xlpm.links,'15. BCM Risk Register'!$I$6:$I$65,_xlpm.hit,ISNUMBER(SEARCH(","&$B34&",",","&SUBSTITUTE(_xlpm.links," ","")&",")),IFERROR(_xlfn.TEXTJOIN(", ",TRUE,_xlfn.UNIQUE(_xlfn._xlws.FILTER(_xlpm.ids,_xlpm.hit*(_xlpm.ids<>"")*(_xlpm.ids<>"Not Created")))),"Not Created")))}
G35: ICT | I35: Operational | T35: =IF($S$34="","",IF(COUNT(J35:R35)=0,"",IF(MAX(J35:R35)>3,$I35,"")))
G36: Data / Info | I36: Product / Service Safety | T36: =IF($S$34="","",IF(COUNT(J36:R36)=0,"",IF(MAX(J36:R36)>3,$I36,"")))
G37: 3rd Party | I37: Health, Safety & Environment | T37: =IF($S$34="","",IF(COUNT(J37:R37)=0,"",IF(MAX(J37:R37)>3,$I37,"")))
G38: Equipment / Building / Utilities | I38: Regulatory & Compliance | T38: =IF($S$34="","",IF(COUNT(J38:R38)=0,"",IF(MAX(J38:R38)>3,$I38,"")))
G39: Pre-Service | I39: Reputation | T39: =IF($S$34="","",IF(COUNT(J39:R39)=0,"",IF(MAX(J39:R39)>3,$I39,"")))
G40: Post-Service | I40: Information Technology | T40: =IF($S$34="","",IF(COUNT(J40:R40)=0,"",IF(MAX(J40:R40)>3,$I40,"")))
A41: 6 | B41: =IF($E41="","","BIA-"&TEXT(6,"000")) | C41: =IFERROR(INDEX(BusinessUnits1,MATCH(A41,'04. Products & Services'!$N$6:$N$50,0)),"") | D41: =IFERROR(INDEX(DivisionSites,MATCH(A41,'04. Products & Services'!$N$6:$N$50,0)),"") | E41: =IFERROR(INDEX(ScopeNames,MATCH(A41,'04. Products & Services'!$N$6:$N$50,0)),"") | F41: =_xlfn.XLOOKUP(E41,'04. Products & Services'!$E$5:$E$50,'04. Products & Services'!$B$5:$B$50,"") | G41: People | I41: Financial | S41: =IF(COUNT(J41:R47)=0,"",MAX(J41:R47)) | T41: =IF($S$41="","",IF(COUNT(J41:R41)=0,"",IF(MAX(J41:R41)>3,$I41,""))) | U41: {=IF($E41="","",_xlfn.LET(_xlpm.matches,_xlfn._xlws.FILTER('04. Products & Services'!$J$6:$J$50,'04. Products & Services'!$E$6:$E$50=$E41,""),_xlpm.n,COUNTIF($E$6:$E41,$E41),_xlpm.v,IFERROR(INDEX(_xlpm.matches,_xlpm.n),""),IF(OR(_xlpm.v="",_xlpm.v=0),"",_xlpm.v)))} | W41: =IF($E41="","",IF(OR($U41="Yes",$V41="Yes"),"Yes",IF(AND($U41="No",$V41="No"),"No",IF(AND($U41="Under Evaluation",$V41="No"),"Under Evaluation","")))) | X41: =IF($E41="","",IFERROR(_xlfn.LET(_xlpm.v,INDEX('04. Products & Services'!$K$6:$K$50,MATCH($E41,ScopeNames,0)),IF(_xlpm.v="","",_xlpm.v)),"")) | AA41: =IF($E41="","",IF(COUNT(J41:R47)=0,"",IF(MAX(J41:J47)>=4,6,IF(MAX(K41:K47)>=4,18,IF(MAX(L41:L47)>=4,36,IF(MAX(M41:M47)>=4,72,IF(MAX(N41:N47)>=4,168,IF(MAX(O41:O47)>=4,336,IF(MAX(P41:P47)>=4,504,IF(MAX(Q41:Q47)>=4,672,IF(MAX(R41:R47)>=4,"",""))))))))))) | AB41: =IF($F41="","",IFERROR(VLOOKUP($F41,'04. Products & Services'!$B$5:$M$50,12,0),"")) | AD41: {=IF(ISBLANK(AC41),"",_xlfn.LET( _xlpm.Num,--_xlfn.TEXTBEFORE(AC41," "), _xlpm.Unit,LOWER(_xlfn.TEXTAFTER(AC41," ")), _xlfn.SWITCH(_xlpm.Unit, "hour",_xlpm.Num, "hours",_xlpm.Num, "day",_xlpm.Num*24, "days",_xlpm.Num*24, "week",_xlpm.Num*24*7, "weeks",_xlpm.Num*24*7, "month",_xlpm.Num*24*(365.25/12), "months",_xlpm.Num*24*(365.25/12), "") ))} | AG41: =IF($AF41="","",DATE(YEAR($AF41)+1,MONTH($AF41),DAY($AF41))) | AH41: {=IF($B41="","",_xlfn.LET(_xlpm.ids,'15. BCM Risk Register'!$A$6:$A$65,_xlpm.links,'15. BCM Risk Register'!$I$6:$I$65,_xlpm.hit,ISNUMBER(SEARCH(","&$B41&",",","&SUBSTITUTE(_xlpm.links," ","")&",")),IFERROR(_xlfn.TEXTJOIN(", ",TRUE,_xlfn.UNIQUE(_xlfn._xlws.FILTER(_xlpm.ids,_xlpm.hit*(_xlpm.ids<>"")))),"Not Created")))} | AI41: {=IF($B41="","",_xlfn.LET(_xlpm.ids,'15. BCM Risk Register'!$L$6:$L$65,_xlpm.links,'15. BCM Risk Register'!$I$6:$I$65,_xlpm.hit,ISNUMBER(SEARCH(","&$B41&",",","&SUBSTITUTE(_xlpm.links," ","")&",")),IFERROR(_xlfn.TEXTJOIN(", ",TRUE,_xlfn.UNIQUE(_xlfn._xlws.FILTER(_xlpm.ids,_xlpm.hit*(_xlpm.ids<>"")*(_xlpm.ids<>"Not Created")))),"Not Created")))} | AJ41: {=IF($B41="","",_xlfn.LET(_xlpm.ids,'15. BCM Risk Register'!$K$6:$K$65,_xlpm.links,'15. BCM Risk Register'!$I$6:$I$65,_xlpm.hit,ISNUMBER(SEARCH(","&$B41&",",","&SUBSTITUTE(_xlpm.links," ","")&",")),IFERROR(_xlfn.TEXTJOIN(", ",TRUE,_xlfn.UNIQUE(_xlfn._xlws.FILTER(_xlpm.ids,_xlpm.hit*(_xlpm.ids<>"")*(_xlpm.ids<>"Not Created")))),"Not Created")))}
G42: ICT | I42: Operational | T42: =IF($S$41="","",IF(COUNT(J42:R42)=0,"",IF(MAX(J42:R42)>3,$I42,"")))
G43: Data / Info | I43: Product / Service Safety | T43: =IF($S$41="","",IF(COUNT(J43:R43)=0,"",IF(MAX(J43:R43)>3,$I43,"")))
G44: 3rd Party | I44: Health, Safety & Environment | T44: =IF($S$41="","",IF(COUNT(J44:R44)=0,"",IF(MAX(J44:R44)>3,$I44,"")))
G45: Equipment / Building / Utilities | I45: Regulatory & Compliance | T45: =IF($S$41="","",IF(COUNT(J45:R45)=0,"",IF(MAX(J45:R45)>3,$I45,"")))
G46: Pre-Service | I46: Reputation | T46: =IF($S$41="","",IF(COUNT(J46:R46)=0,"",IF(MAX(J46:R46)>3,$I46,"")))
G47: Post-Service | I47: Information Technology | T47: =IF($S$41="","",IF(COUNT(J47:R47)=0,"",IF(MAX(J47:R47)>3,$I47,"")))
A48: 7 | B48: =IF($E48="","","BIA-"&TEXT(7,"000")) | C48: =IFERROR(INDEX(BusinessUnits1,MATCH(A48,'04. Products & Services'!$N$6:$N$50,0)),"") | D48: =IFERROR(INDEX(DivisionSites,MATCH(A48,'04. Products & Services'!$N$6:$N$50,0)),"") | E48: =IFERROR(INDEX(ScopeNames,MATCH(A48,'04. Products & Services'!$N$6:$N$50,0)),"") | F48: =_xlfn.XLOOKUP(E48,'04. Products & Services'!$E$5:$E$50,'04. Products & Services'!$B$5:$B$50,"") | G48: People | I48: Financial | S48: =IF(COUNT(J48:R54)=0,"",MAX(J48:R54)) | T48: =IF($S$48="","",IF(COUNT(J48:R48)=0,"",IF(MAX(J48:R48)>3,$I48,""))) | U48: {=IF($E48="","",_xlfn.LET(_xlpm.matches,_xlfn._xlws.FILTER('04. Products & Services'!$J$6:$J$50,'04. Products & Services'!$E$6:$E$50=$E48,""),_xlpm.n,COUNTIF($E$6:$E48,$E48),_xlpm.v,IFERROR(INDEX(_xlpm.matches,_xlpm.n),""),IF(OR(_xlpm.v="",_xlpm.v=0),"",_xlpm.v)))} | W48: =IF($E48="","",IF(OR($U48="Yes",$V48="Yes"),"Yes",IF(AND($U48="No",$V48="No"),"No",IF(AND($U48="Under Evaluation",$V48="No"),"Under Evaluation","")))) | X48: =IF($E48="","",IFERROR(_xlfn.LET(_xlpm.v,INDEX('04. Products & Services'!$K$6:$K$50,MATCH($E48,ScopeNames,0)),IF(_xlpm.v="","",_xlpm.v)),"")) | AA48: =IF($E48="","",IF(COUNT(J48:R54)=0,"",IF(MAX(J48:J54)>=4,6,IF(MAX(K48:K54)>=4,18,IF(MAX(L48:L54)>=4,36,IF(MAX(M48:M54)>=4,72,IF(MAX(N48:N54)>=4,168,IF(MAX(O48:O54)>=4,336,IF(MAX(P48:P54)>=4,504,IF(MAX(Q48:Q54)>=4,672,IF(MAX(R48:R54)>=4,"",""))))))))))) | AB48: =IF($F48="","",IFERROR(VLOOKUP($F48,'04. Products & Services'!$B$5:$M$50,12,0),"")) | AD48: {=IF(ISBLANK(AC48),"",_xlfn.LET( _xlpm.Num,--_xlfn.TEXTBEFORE(AC48," "), _xlpm.Unit,LOWER(_xlfn.TEXTAFTER(AC48," ")), _xlfn.SWITCH(_xlpm.Unit, "hour",_xlpm.Num, "hours",_xlpm.Num, "day",_xlpm.Num*24, "days",_xlpm.Num*24, "week",_xlpm.Num*24*7, "weeks",_xlpm.Num*24*7, "month",_xlpm.Num*24*(365.25/12), "months",_xlpm.Num*24*(365.25/12), "") ))} | AG48: =IF($AF48="","",DATE(YEAR($AF48)+1,MONTH($AF48),DAY($AF48))) | AH48: {=IF($B48="","",_xlfn.LET(_xlpm.ids,'15. BCM Risk Register'!$A$6:$A$65,_xlpm.links,'15. BCM Risk Register'!$I$6:$I$65,_xlpm.hit,ISNUMBER(SEARCH(","&$B48&",",","&SUBSTITUTE(_xlpm.links," ","")&",")),IFERROR(_xlfn.TEXTJOIN(", ",TRUE,_xlfn.UNIQUE(_xlfn._xlws.FILTER(_xlpm.ids,_xlpm.hit*(_xlpm.ids<>"")))),"Not Created")))} | AI48: {=IF($B48="","",_xlfn.LET(_xlpm.ids,'15. BCM Risk Register'!$L$6:$L$65,_xlpm.links,'15. BCM Risk Register'!$I$6:$I$65,_xlpm.hit,ISNUMBER(SEARCH(","&$B48&",",","&SUBSTITUTE(_xlpm.links," ","")&",")),IFERROR(_xlfn.TEXTJOIN(", ",TRUE,_xlfn.UNIQUE(_xlfn._xlws.FILTER(_xlpm.ids,_xlpm.hit*(_xlpm.ids<>"")*(_xlpm.ids<>"Not Created")))),"Not Created")))} | AJ48: {=IF($B48="","",_xlfn.LET(_xlpm.ids,'15. BCM Risk Register'!$K$6:$K$65,_xlpm.links,'15. BCM Risk Register'!$I$6:$I$65,_xlpm.hit,ISNUMBER(SEARCH(","&$B48&",",","&SUBSTITUTE(_xlpm.links," ","")&",")),IFERROR(_xlfn.TEXTJOIN(", ",TRUE,_xlfn.UNIQUE(_xlfn._xlws.FILTER(_xlpm.ids,_xlpm.hit*(_xlpm.ids<>"")*(_xlpm.ids<>"Not Created")))),"Not Created")))}
G49: ICT | I49: Operational | T49: =IF($S$48="","",IF(COUNT(J49:R49)=0,"",IF(MAX(J49:R49)>3,$I49,"")))
G50: Data / Info | I50: Product / Service Safety | T50: =IF($S$48="","",IF(COUNT(J50:R50)=0,"",IF(MAX(J50:R50)>3,$I50,"")))
G51: 3rd Party | I51: Health, Safety & Environment | T51: =IF($S$48="","",IF(COUNT(J51:R51)=0,"",IF(MAX(J51:R51)>3,$I51,"")))
G52: Equipment / Building / Utilities | I52: Regulatory & Compliance | T52: =IF($S$48="","",IF(COUNT(J52:R52)=0,"",IF(MAX(J52:R52)>3,$I52,"")))
G53: Pre-Service | I53: Reputation | T53: =IF($S$48="","",IF(COUNT(J53:R53)=0,"",IF(MAX(J53:R53)>3,$I53,"")))
G54: Post-Service | I54: Information Technology | T54: =IF($S$48="","",IF(COUNT(J54:R54)=0,"",IF(MAX(J54:R54)>3,$I54,"")))
A55: 8 | B55: =IF($E55="","","BIA-"&TEXT(8,"000")) | C55: =IFERROR(INDEX(BusinessUnits1,MATCH(A55,'04. Products & Services'!$N$6:$N$50,0)),"") | D55: =IFERROR(INDEX(DivisionSites,MATCH(A55,'04. Products & Services'!$N$6:$N$50,0)),"") | E55: =IFERROR(INDEX(ScopeNames,MATCH(A55,'04. Products & Services'!$N$6:$N$50,0)),"") | F55: =_xlfn.XLOOKUP(E55,'04. Products & Services'!$E$5:$E$50,'04. Products & Services'!$B$5:$B$50,"") | G55: People | I55: Financial | S55: =IF(COUNT(J55:R61)=0,"",MAX(J55:R61)) | T55: =IF($S$55="","",IF(COUNT(J55:R55)=0,"",IF(MAX(J55:R55)>3,$I55,""))) | U55: {=IF($E55="","",_xlfn.LET(_xlpm.matches,_xlfn._xlws.FILTER('04. Products & Services'!$J$6:$J$50,'04. Products & Services'!$E$6:$E$50=$E55,""),_xlpm.n,COUNTIF($E$6:$E55,$E55),_xlpm.v,IFERROR(INDEX(_xlpm.matches,_xlpm.n),""),IF(OR(_xlpm.v="",_xlpm.v=0),"",_xlpm.v)))} | W55: =IF($E55="","",IF(OR($U55="Yes",$V55="Yes"),"Yes",IF(AND($U55="No",$V55="No"),"No",IF(AND($U55="Under Evaluation",$V55="No"),"Under Evaluation","")))) | X55: =IF($E55="","",IFERROR(_xlfn.LET(_xlpm.v,INDEX('04. Products & Services'!$K$6:$K$50,MATCH($E55,ScopeNames,0)),IF(_xlpm.v="","",_xlpm.v)),"")) | AA55: =IF($E55="","",IF(COUNT(J55:R61)=0,"",IF(MAX(J55:J61)>=4,6,IF(MAX(K55:K61)>=4,18,IF(MAX(L55:L61)>=4,36,IF(MAX(M55:M61)>=4,72,IF(MAX(N55:N61)>=4,168,IF(MAX(O55:O61)>=4,336,IF(MAX(P55:P61)>=4,504,IF(MAX(Q55:Q61)>=4,672,IF(MAX(R55:R61)>=4,"",""))))))))))) | AB55: =IF($F55="","",IFERROR(VLOOKUP($F55,'04. Products & Services'!$B$5:$M$50,12,0),"")) | AD55: {=IF(ISBLANK(AC55),"",_xlfn.LET( _xlpm.Num,--_xlfn.TEXTBEFORE(AC55," "), _xlpm.Unit,LOWER(_xlfn.TEXTAFTER(AC55," ")), _xlfn.SWITCH(_xlpm.Unit, "hour",_xlpm.Num, "hours",_xlpm.Num, "day",_xlpm.Num*24, "days",_xlpm.Num*24, "week",_xlpm.Num*24*7, "weeks",_xlpm.Num*24*7, "month",_xlpm.Num*24*(365.25/12), "months",_xlpm.Num*24*(365.25/12), "") ))} | AG55: =IF($AF55="","",DATE(YEAR($AF55)+1,MONTH($AF55),DAY($AF55))) | AH55: {=IF($B55="","",_xlfn.LET(_xlpm.ids,'15. BCM Risk Register'!$A$6:$A$65,_xlpm.links,'15. BCM Risk Register'!$I$6:$I$65,_xlpm.hit,ISNUMBER(SEARCH(","&$B55&",",","&SUBSTITUTE(_xlpm.links," ","")&",")),IFERROR(_xlfn.TEXTJOIN(", ",TRUE,_xlfn.UNIQUE(_xlfn._xlws.FILTER(_xlpm.ids,_xlpm.hit*(_xlpm.ids<>"")))),"Not Created")))} | AI55: {=IF($B55="","",_xlfn.LET(_xlpm.ids,'15. BCM Risk Register'!$L$6:$L$65,_xlpm.links,'15. BCM Risk Register'!$I$6:$I$65,_xlpm.hit,ISNUMBER(SEARCH(","&$B55&",",","&SUBSTITUTE(_xlpm.links," ","")&",")),IFERROR(_xlfn.TEXTJOIN(", ",TRUE,_xlfn.UNIQUE(_xlfn._xlws.FILTER(_xlpm.ids,_xlpm.hit*(_xlpm.ids<>"")*(_xlpm.ids<>"Not Created")))),"Not Created")))} | AJ55: {=IF($B55="","",_xlfn.LET(_xlpm.ids,'15. BCM Risk Register'!$K$6:$K$65,_xlpm.links,'15. BCM Risk Register'!$I$6:$I$65,_xlpm.hit,ISNUMBER(SEARCH(","&$B55&",",","&SUBSTITUTE(_xlpm.links," ","")&",")),IFERROR(_xlfn.TEXTJOIN(", ",TRUE,_xlfn.UNIQUE(_xlfn._xlws.FILTER(_xlpm.ids,_xlpm.hit*(_xlpm.ids<>"")*(_xlpm.ids<>"Not Created")))),"Not Created")))}
G56: ICT | I56: Operational | T56: =IF($S$55="","",IF(COUNT(J56:R56)=0,"",IF(MAX(J56:R56)>3,$I56,"")))
G57: Data / Info | I57: Product / Service Safety | T57: =IF($S$55="","",IF(COUNT(J57:R57)=0,"",IF(MAX(J57:R57)>3,$I57,"")))
G58: 3rd Party | I58: Health, Safety & Environment | T58: =IF($S$55="","",IF(COUNT(J58:R58)=0,"",IF(MAX(J58:R58)>3,$I58,"")))
G59: Equipment / Building / Utilities | I59: Regulatory & Compliance | T59: =IF($S$55="","",IF(COUNT(J59:R59)=0,"",IF(MAX(J59:R59)>3,$I59,"")))
G60: Pre-Service | I60: Reputation | T60: =IF($S$55="","",IF(COUNT(J60:R60)=0,"",IF(MAX(J60:R60)>3,$I60,"")))
G61: Post-Service | I61: Information Technology | T61: =IF($S$55="","",IF(COUNT(J61:R61)=0,"",IF(MAX(J61:R61)>3,$I61,"")))
A62: 9 | B62: =IF($E62="","","BIA-"&TEXT(9,"000")) | C62: =IFERROR(INDEX(BusinessUnits1,MATCH(A62,'04. Products & Services'!$N$6:$N$50,0)),"") | D62: =IFERROR(INDEX(DivisionSites,MATCH(A62,'04. Products & Services'!$N$6:$N$50,0)),"") | E62: =IFERROR(INDEX(ScopeNames,MATCH(A62,'04. Products & Services'!$N$6:$N$50,0)),"") | F62: =_xlfn.XLOOKUP(E62,'04. Products & Services'!$E$5:$E$50,'04. Products & Services'!$B$5:$B$50,"") | G62: People | I62: Financial | S62: =IF(COUNT(J62:R68)=0,"",MAX(J62:R68)) | T62: =IF($S$62="","",IF(COUNT(J62:R62)=0,"",IF(MAX(J62:R62)>3,$I62,""))) | U62: {=IF($E62="","",_xlfn.LET(_xlpm.matches,_xlfn._xlws.FILTER('04. Products & Services'!$J$6:$J$50,'04. Products & Services'!$E$6:$E$50=$E62,""),_xlpm.n,COUNTIF($E$6:$E62,$E62),_xlpm.v,IFERROR(INDEX(_xlpm.matches,_xlpm.n),""),IF(OR(_xlpm.v="",_xlpm.v=0),"",_xlpm.v)))} | W62: =IF($E62="","",IF(OR($U62="Yes",$V62="Yes"),"Yes",IF(AND($U62="No",$V62="No"),"No",IF(AND($U62="Under Evaluation",$V62="No"),"Under Evaluation","")))) | X62: =IF($E62="","",IFERROR(_xlfn.LET(_xlpm.v,INDEX('04. Products & Services'!$K$6:$K$50,MATCH($E62,ScopeNames,0)),IF(_xlpm.v="","",_xlpm.v)),"")) | AA62: =IF($E62="","",IF(COUNT(J62:R68)=0,"",IF(MAX(J62:J68)>=4,6,IF(MAX(K62:K68)>=4,18,IF(MAX(L62:L68)>=4,36,IF(MAX(M62:M68)>=4,72,IF(MAX(N62:N68)>=4,168,IF(MAX(O62:O68)>=4,336,IF(MAX(P62:P68)>=4,504,IF(MAX(Q62:Q68)>=4,672,IF(MAX(R62:R68)>=4,"",""))))))))))) | AB62: =IF($F62="","",IFERROR(VLOOKUP($F62,'04. Products & Services'!$B$5:$M$50,12,0),"")) | AD62: {=IF(ISBLANK(AC62),"",_xlfn.LET( _xlpm.Num,--_xlfn.TEXTBEFORE(AC62," "), _xlpm.Unit,LOWER(_xlfn.TEXTAFTER(AC62," ")), _xlfn.SWITCH(_xlpm.Unit, "hour",_xlpm.Num, "hours",_xlpm.Num, "day",_xlpm.Num*24, "days",_xlpm.Num*24, "week",_xlpm.Num*24*7, "weeks",_xlpm.Num*24*7, "month",_xlpm.Num*24*(365.25/12), "months",_xlpm.Num*24*(365.25/12), "") ))} | AG62: =IF($AF62="","",DATE(YEAR($AF62)+1,MONTH($AF62),DAY($AF62))) | AH62: {=IF($B62="","",_xlfn.LET(_xlpm.ids,'15. BCM Risk Register'!$A$6:$A$65,_xlpm.links,'15. BCM Risk Register'!$I$6:$I$65,_xlpm.hit,ISNUMBER(SEARCH(","&$B62&",",","&SUBSTITUTE(_xlpm.links," ","")&",")),IFERROR(_xlfn.TEXTJOIN(", ",TRUE,_xlfn.UNIQUE(_xlfn._xlws.FILTER(_xlpm.ids,_xlpm.hit*(_xlpm.ids<>"")))),"Not Created")))} | AI62: {=IF($B62="","",_xlfn.LET(_xlpm.ids,'15. BCM Risk Register'!$L$6:$L$65,_xlpm.links,'15. BCM Risk Register'!$I$6:$I$65,_xlpm.hit,ISNUMBER(SEARCH(","&$B62&",",","&SUBSTITUTE(_xlpm.links," ","")&",")),IFERROR(_xlfn.TEXTJOIN(", ",TRUE,_xlfn.UNIQUE(_xlfn._xlws.FILTER(_xlpm.ids,_xlpm.hit*(_xlpm.ids<>"")*(_xlpm.ids<>"Not Created")))),"Not Created")))} | AJ62: {=IF($B62="","",_xlfn.LET(_xlpm.ids,'15. BCM Risk Register'!$K$6:$K$65,_xlpm.links,'15. BCM Risk Register'!$I$6:$I$65,_xlpm.hit,ISNUMBER(SEARCH(","&$B62&",",","&SUBSTITUTE(_xlpm.links," ","")&",")),IFERROR(_xlfn.TEXTJOIN(", ",TRUE,_xlfn.UNIQUE(_xlfn._xlws.FILTER(_xlpm.ids,_xlpm.hit*(_xlpm.ids<>"")*(_xlpm.ids<>"Not Created")))),"Not Created")))}
G63: ICT | I63: Operational | T63: =IF($S$62="","",IF(COUNT(J63:R63)=0,"",IF(MAX(J63:R63)>3,$I63,"")))
G64: Data / Info | I64: Product / Service Safety | T64: =IF($S$62="","",IF(COUNT(J64:R64)=0,"",IF(MAX(J64:R64)>3,$I64,"")))
G65: 3rd Party | I65: Health, Safety & Environment | T65: =IF($S$62="","",IF(COUNT(J65:R65)=0,"",IF(MAX(J65:R65)>3,$I65,"")))
G66: Equipment / Building / Utilities | I66: Regulatory & Compliance | T66: =IF($S$62="","",IF(COUNT(J66:R66)=0,"",IF(MAX(J66:R66)>3,$I66,"")))
G67: Pre-Service | I67: Reputation | T67: =IF($S$62="","",IF(COUNT(J67:R67)=0,"",IF(MAX(J67:R67)>3,$I67,"")))
G68: Post-Service | I68: Information Technology | T68: =IF($S$62="","",IF(COUNT(J68:R68)=0,"",IF(MAX(J68:R68)>3,$I68,"")))
A69: 10 | B69: =IF($E69="","","BIA-"&TEXT(10,"000")) | C69: =IFERROR(INDEX(BusinessUnits1,MATCH(A69,'04. Products & Services'!$N$6:$N$50,0)),"") | D69: =IFERROR(INDEX(DivisionSites,MATCH(A69,'04. Products & Services'!$N$6:$N$50,0)),"") | E69: =IFERROR(INDEX(ScopeNames,MATCH(A69,'04. Products & Services'!$N$6:$N$50,0)),"") | F69: =_xlfn.XLOOKUP(E69,'04. Products & Services'!$E$5:$E$50,'04. Products & Services'!$B$5:$B$50,"") | G69: People | I69: Financial | S69: =IF(COUNT(J69:R75)=0,"",MAX(J69:R75)) | T69: =IF($S$69="","",IF(COUNT(J69:R69)=0,"",IF(MAX(J69:R69)>3,$I69,""))) | U69: {=IF($E69="","",_xlfn.LET(_xlpm.matches,_xlfn._xlws.FILTER('04. Products & Services'!$J$6:$J$50,'04. Products & Services'!$E$6:$E$50=$E69,""),_xlpm.n,COUNTIF($E$6:$E69,$E69),_xlpm.v,IFERROR(INDEX(_xlpm.matches,_xlpm.n),""),IF(OR(_xlpm.v="",_xlpm.v=0),"",_xlpm.v)))} | W69: =IF($E69="","",IF(OR($U69="Yes",$V69="Yes"),"Yes",IF(AND($U69="No",$V69="No"),"No",IF(AND($U69="Under Evaluation",$V69="No"),"Under Evaluation","")))) | X69: =IF($E69="","",IFERROR(_xlfn.LET(_xlpm.v,INDEX('04. Products & Services'!$K$6:$K$50,MATCH($E69,ScopeNames,0)),IF(_xlpm.v="","",_xlpm.v)),"")) | AA69: =IF($E69="","",IF(COUNT(J69:R75)=0,"",IF(MAX(J69:J75)>=4,6,IF(MAX(K69:K75)>=4,18,IF(MAX(L69:L75)>=4,36,IF(MAX(M69:M75)>=4,72,IF(MAX(N69:N75)>=4,168,IF(MAX(O69:O75)>=4,336,IF(MAX(P69:P75)>=4,504,IF(MAX(Q69:Q75)>=4,672,IF(MAX(R69:R75)>=4,"",""))))))))))) | AB69: =IF($F69="","",IFERROR(VLOOKUP($F69,'04. Products & Services'!$B$5:$M$50,12,0),"")) | AD69: {=IF(ISBLANK(AC69),"",_xlfn.LET( _xlpm.Num,--_xlfn.TEXTBEFORE(AC69," "), _xlpm.Unit,LOWER(_xlfn.TEXTAFTER(AC69," ")), _xlfn.SWITCH(_xlpm.Unit, "hour",_xlpm.Num, "hours",_xlpm.Num, "day",_xlpm.Num*24, "days",_xlpm.Num*24, "week",_xlpm.Num*24*7, "weeks",_xlpm.Num*24*7, "month",_xlpm.Num*24*(365.25/12), "months",_xlpm.Num*24*(365.25/12), "") ))} | AG69: =IF($AF69="","",DATE(YEAR($AF69)+1,MONTH($AF69),DAY($AF69))) | AH69: {=IF($B69="","",_xlfn.LET(_xlpm.ids,'15. BCM Risk Register'!$A$6:$A$65,_xlpm.links,'15. BCM Risk Register'!$I$6:$I$65,_xlpm.hit,ISNUMBER(SEARCH(","&$B69&",",","&SUBSTITUTE(_xlpm.links," ","")&",")),IFERROR(_xlfn.TEXTJOIN(", ",TRUE,_xlfn.UNIQUE(_xlfn._xlws.FILTER(_xlpm.ids,_xlpm.hit*(_xlpm.ids<>"")))),"Not Created")))} | AI69: {=IF($B69="","",_xlfn.LET(_xlpm.ids,'15. BCM Risk Register'!$L$6:$L$65,_xlpm.links,'15. BCM Risk Register'!$I$6:$I$65,_xlpm.hit,ISNUMBER(SEARCH(","&$B69&",",","&SUBSTITUTE(_xlpm.links," ","")&",")),IFERROR(_xlfn.TEXTJOIN(", ",TRUE,_xlfn.UNIQUE(_xlfn._xlws.FILTER(_xlpm.ids,_xlpm.hit*(_xlpm.ids<>"")*(_xlpm.ids<>"Not Created")))),"Not Created")))} | AJ69: {=IF($B69="","",_xlfn.LET(_xlpm.ids,'15. BCM Risk Register'!$K$6:$K$65,_xlpm.links,'15. BCM Risk Register'!$I$6:$I$65,_xlpm.hit,ISNUMBER(SEARCH(","&$B69&",",","&SUBSTITUTE(_xlpm.links," ","")&",")),IFERROR(_xlfn.TEXTJOIN(", ",TRUE,_xlfn.UNIQUE(_xlfn._xlws.FILTER(_xlpm.ids,_xlpm.hit*(_xlpm.ids<>"")*(_xlpm.ids<>"Not Created")))),"Not Created")))}
G70: ICT | I70: Operational | T70: =IF($S$69="","",IF(COUNT(J70:R70)=0,"",IF(MAX(J70:R70)>3,$I70,"")))
G71: Data / Info | I71: Product / Service Safety | T71: =IF($S$69="","",IF(COUNT(J71:R71)=0,"",IF(MAX(J71:R71)>3,$I71,"")))
G72: 3rd Party | I72: Health, Safety & Environment | T72: =IF($S$69="","",IF(COUNT(J72:R72)=0,"",IF(MAX(J72:R72)>3,$I72,"")))
G73: Equipment / Building / Utilities | I73: Regulatory & Compliance | T73: =IF($S$69="","",IF(COUNT(J73:R73)=0,"",IF(MAX(J73:R73)>3,$I73,"")))
G74: Pre-Service | I74: Reputation | T74: =IF($S$69="","",IF(COUNT(J74:R74)=0,"",IF(MAX(J74:R74)>3,$I74,"")))
G75: Post-Service | I75: Information Technology | T75: =IF($S$69="","",IF(COUNT(J75:R75)=0,"",IF(MAX(J75:R75)>3,$I75,"")))
A76: 11 | B76: =IF($E76="","","BIA-"&TEXT(11,"000")) | C76: =IFERROR(INDEX(BusinessUnits1,MATCH(A76,'04. Products & Services'!$N$6:$N$50,0)),"") | D76: =IFERROR(INDEX(DivisionSites,MATCH(A76,'04. Products & Services'!$N$6:$N$50,0)),"") | E76: =IFERROR(INDEX(ScopeNames,MATCH(A76,'04. Products & Services'!$N$6:$N$50,0)),"") | F76: =_xlfn.XLOOKUP(E76,'04. Products & Services'!$E$5:$E$50,'04. Products & Services'!$B$5:$B$50,"") | G76: People | I76: Financial | S76: =IF(COUNT(J76:R82)=0,"",MAX(J76:R82)) | T76: =IF($S$76="","",IF(COUNT(J76:R76)=0,"",IF(MAX(J76:R76)>3,$I76,""))) | U76: {=IF($E76="","",_xlfn.LET(_xlpm.matches,_xlfn._xlws.FILTER('04. Products & Services'!$J$6:$J$50,'04. Products & Services'!$E$6:$E$50=$E76,""),_xlpm.n,COUNTIF($E$6:$E76,$E76),_xlpm.v,IFERROR(INDEX(_xlpm.matches,_xlpm.n),""),IF(OR(_xlpm.v="",_xlpm.v=0),"",_xlpm.v)))} | W76: =IF($E76="","",IF(OR($U76="Yes",$V76="Yes"),"Yes",IF(AND($U76="No",$V76="No"),"No",IF(AND($U76="Under Evaluation",$V76="No"),"Under Evaluation","")))) | X76: =IF($E76="","",IFERROR(_xlfn.LET(_xlpm.v,INDEX('04. Products & Services'!$K$6:$K$50,MATCH($E76,ScopeNames,0)),IF(_xlpm.v="","",_xlpm.v)),"")) | AA76: =IF($E76="","",IF(COUNT(J76:R82)=0,"",IF(MAX(J76:J82)>=4,6,IF(MAX(K76:K82)>=4,18,IF(MAX(L76:L82)>=4,36,IF(MAX(M76:M82)>=4,72,IF(MAX(N76:N82)>=4,168,IF(MAX(O76:O82)>=4,336,IF(MAX(P76:P82)>=4,504,IF(MAX(Q76:Q82)>=4,672,IF(MAX(R76:R82)>=4,"",""))))))))))) | AB76: =IF($F76="","",IFERROR(VLOOKUP($F76,'04. Products & Services'!$B$5:$M$50,12,0),"")) | AD76: {=IF(ISBLANK(AC76),"",_xlfn.LET( _xlpm.Num,--_xlfn.TEXTBEFORE(AC76," "), _xlpm.Unit,LOWER(_xlfn.TEXTAFTER(AC76," ")), _xlfn.SWITCH(_xlpm.Unit, "hour",_xlpm.Num, "hours",_xlpm.Num, "day",_xlpm.Num*24, "days",_xlpm.Num*24, "week",_xlpm.Num*24*7, "weeks",_xlpm.Num*24*7, "month",_xlpm.Num*24*(365.25/12), "months",_xlpm.Num*24*(365.25/12), "") ))} | AG76: =IF($AF76="","",DATE(YEAR($AF76)+1,MONTH($AF76),DAY($AF76))) | AH76: {=IF($B76="","",_xlfn.LET(_xlpm.ids,'15. BCM Risk Register'!$A$6:$A$65,_xlpm.links,'15. BCM Risk Register'!$I$6:$I$65,_xlpm.hit,ISNUMBER(SEARCH(","&$B76&",",","&SUBSTITUTE(_xlpm.links," ","")&",")),IFERROR(_xlfn.TEXTJOIN(", ",TRUE,_xlfn.UNIQUE(_xlfn._xlws.FILTER(_xlpm.ids,_xlpm.hit*(_xlpm.ids<>"")))),"Not Created")))} | AI76: {=IF($B76="","",_xlfn.LET(_xlpm.ids,'15. BCM Risk Register'!$L$6:$L$65,_xlpm.links,'15. BCM Risk Register'!$I$6:$I$65,_xlpm.hit,ISNUMBER(SEARCH(","&$B76&",",","&SUBSTITUTE(_xlpm.links," ","")&",")),IFERROR(_xlfn.TEXTJOIN(", ",TRUE,_xlfn.UNIQUE(_xlfn._xlws.FILTER(_xlpm.ids,_xlpm.hit*(_xlpm.ids<>"")*(_xlpm.ids<>"Not Created")))),"Not Created")))} | AJ76: {=IF($B76="","",_xlfn.LET(_xlpm.ids,'15. BCM Risk Register'!$K$6:$K$65,_xlpm.links,'15. BCM Risk Register'!$I$6:$I$65,_xlpm.hit,ISNUMBER(SEARCH(","&$B76&",",","&SUBSTITUTE(_xlpm.links," ","")&",")),IFERROR(_xlfn.TEXTJOIN(", ",TRUE,_xlfn.UNIQUE(_xlfn._xlws.FILTER(_xlpm.ids,_xlpm.hit*(_xlpm.ids<>"")*(_xlpm.ids<>"Not Created")))),"Not Created")))}
G77: ICT | I77: Operational | T77: =IF($S$76="","",IF(COUNT(J77:R77)=0,"",IF(MAX(J77:R77)>3,$I77,"")))
G78: Data / Info | I78: Product / Service Safety | T78: =IF($S$76="","",IF(COUNT(J78:R78)=0,"",IF(MAX(J78:R78)>3,$I78,"")))
G79: 3rd Party | I79: Health, Safety & Environment | T79: =IF($S$76="","",IF(COUNT(J79:R79)=0,"",IF(MAX(J79:R79)>3,$I79,"")))
G80: Equipment / Building / Utilities | I80: Regulatory & Compliance | T80: =IF($S$76="","",IF(COUNT(J80:R80)=0,"",IF(MAX(J80:R80)>3,$I80,"")))
G81: Pre-Service | I81: Reputation | T81: =IF($S$76="","",IF(COUNT(J81:R81)=0,"",IF(MAX(J81:R81)>3,$I81,"")))
G82: Post-Service | I82: Information Technology | T82: =IF($S$76="","",IF(COUNT(J82:R82)=0,"",IF(MAX(J82:R82)>3,$I82,"")))
A83: 12 | B83: =IF($E83="","","BIA-"&TEXT(12,"000")) | C83: =IFERROR(INDEX(BusinessUnits1,MATCH(A83,'04. Products & Services'!$N$6:$N$50,0)),"") | D83: =IFERROR(INDEX(DivisionSites,MATCH(A83,'04. Products & Services'!$N$6:$N$50,0)),"") | E83: =IFERROR(INDEX(ScopeNames,MATCH(A83,'04. Products & Services'!$N$6:$N$50,0)),"") | F83: =_xlfn.XLOOKUP(E83,'04. Products & Services'!$E$5:$E$50,'04. Products & Services'!$B$5:$B$50,"") | G83: People | I83: Financial | S83: =IF(COUNT(J83:R89)=0,"",MAX(J83:R89)) | T83: =IF($S$83="","",IF(COUNT(J83:R83)=0,"",IF(MAX(J83:R83)>3,$I83,""))) | U83: {=IF($E83="","",_xlfn.LET(_xlpm.matches,_xlfn._xlws.FILTER('04. Products & Services'!$J$6:$J$50,'04. Products & Services'!$E$6:$E$50=$E83,""),_xlpm.n,COUNTIF($E$6:$E83,$E83),_xlpm.v,IFERROR(INDEX(_xlpm.matches,_xlpm.n),""),IF(OR(_xlpm.v="",_xlpm.v=0),"",_xlpm.v)))} | W83: =IF($E83="","",IF(OR($U83="Yes",$V83="Yes"),"Yes",IF(AND($U83="No",$V83="No"),"No",IF(AND($U83="Under Evaluation",$V83="No"),"Under Evaluation","")))) | X83: =IF($E83="","",IFERROR(_xlfn.LET(_xlpm.v,INDEX('04. Products & Services'!$K$6:$K$50,MATCH($E83,ScopeNames,0)),IF(_xlpm.v="","",_xlpm.v)),"")) | AA83: =IF($E83="","",IF(COUNT(J83:R89)=0,"",IF(MAX(J83:J89)>=4,6,IF(MAX(K83:K89)>=4,18,IF(MAX(L83:L89)>=4,36,IF(MAX(M83:M89)>=4,72,IF(MAX(N83:N89)>=4,168,IF(MAX(O83:O89)>=4,336,IF(MAX(P83:P89)>=4,504,IF(MAX(Q83:Q89)>=4,672,IF(MAX(R83:R89)>=4,"",""))))))))))) | AB83: =IF($F83="","",IFERROR(VLOOKUP($F83,'04. Products & Services'!$B$5:$M$50,12,0),"")) | AD83: {=IF(ISBLANK(AC83),"",_xlfn.LET( _xlpm.Num,--_xlfn.TEXTBEFORE(AC83," "), _xlpm.Unit,LOWER(_xlfn.TEXTAFTER(AC83," ")), _xlfn.SWITCH(_xlpm.Unit, "hour",_xlpm.Num, "hours",_xlpm.Num, "day",_xlpm.Num*24, "days",_xlpm.Num*24, "week",_xlpm.Num*24*7, "weeks",_xlpm.Num*24*7, "month",_xlpm.Num*24*(365.25/12), "months",_xlpm.Num*24*(365.25/12), "") ))} | AG83: =IF($AF83="","",DATE(YEAR($AF83)+1,MONTH($AF83),DAY($AF83))) | AH83: {=IF($B83="","",_xlfn.LET(_xlpm.ids,'15. BCM Risk Register'!$A$6:$A$65,_xlpm.links,'15. BCM Risk Register'!$I$6:$I$65,_xlpm.hit,ISNUMBER(SEARCH(","&$B83&",",","&SUBSTITUTE(_xlpm.links," ","")&",")),IFERROR(_xlfn.TEXTJOIN(", ",TRUE,_xlfn.UNIQUE(_xlfn._xlws.FILTER(_xlpm.ids,_xlpm.hit*(_xlpm.ids<>"")))),"Not Created")))} | AI83: {=IF($B83="","",_xlfn.LET(_xlpm.ids,'15. BCM Risk Register'!$L$6:$L$65,_xlpm.links,'15. BCM Risk Register'!$I$6:$I$65,_xlpm.hit,ISNUMBER(SEARCH(","&$B83&",",","&SUBSTITUTE(_xlpm.links," ","")&",")),IFERROR(_xlfn.TEXTJOIN(", ",TRUE,_xlfn.UNIQUE(_xlfn._xlws.FILTER(_xlpm.ids,_xlpm.hit*(_xlpm.ids<>"")*(_xlpm.ids<>"Not Created")))),"Not Created")))} | AJ83: {=IF($B83="","",_xlfn.LET(_xlpm.ids,'15. BCM Risk Register'!$K$6:$K$65,_xlpm.links,'15. BCM Risk Register'!$I$6:$I$65,_xlpm.hit,ISNUMBER(SEARCH(","&$B83&",",","&SUBSTITUTE(_xlpm.links," ","")&",")),IFERROR(_xlfn.TEXTJOIN(", ",TRUE,_xlfn.UNIQUE(_xlfn._xlws.FILTER(_xlpm.ids,_xlpm.hit*(_xlpm.ids<>"")*(_xlpm.ids<>"Not Created")))),"Not Created")))}
G84: ICT | I84: Operational | T84: =IF($S$83="","",IF(COUNT(J84:R84)=0,"",IF(MAX(J84:R84)>3,$I84,"")))
G85: Data / Info | I85: Product / Service Safety | T85: =IF($S$83="","",IF(COUNT(J85:R85)=0,"",IF(MAX(J85:R85)>3,$I85,"")))
G86: 3rd Party | I86: Health, Safety & Environment | T86: =IF($S$83="","",IF(COUNT(J86:R86)=0,"",IF(MAX(J86:R86)>3,$I86,"")))
G87: Equipment / Building / Utilities | I87: Regulatory & Compliance | T87: =IF($S$83="","",IF(COUNT(J87:R87)=0,"",IF(MAX(J87:R87)>3,$I87,"")))
G88: Pre-Service | I88: Reputation | T88: =IF($S$83="","",IF(COUNT(J88:R88)=0,"",IF(MAX(J88:R88)>3,$I88,"")))
G89: Post-Service | I89: Information Technology | T89: =IF($S$83="","",IF(COUNT(J89:R89)=0,"",IF(MAX(J89:R89)>3,$I89,"")))
A90: 13 | B90: =IF($E90="","","BIA-"&TEXT(13,"000")) | C90: =IFERROR(INDEX(BusinessUnits1,MATCH(A90,'04. Products & Services'!$N$6:$N$50,0)),"") | D90: =IFERROR(INDEX(DivisionSites,MATCH(A90,'04. Products & Services'!$N$6:$N$50,0)),"") | E90: =IFERROR(INDEX(ScopeNames,MATCH(A90,'04. Products & Services'!$N$6:$N$50,0)),"") | F90: =_xlfn.XLOOKUP(E90,'04. Products & Services'!$E$5:$E$50,'04. Products & Services'!$B$5:$B$50,"") | G90: People | I90: Financial | S90: =IF(COUNT(J90:R96)=0,"",MAX(J90:R96)) | T90: =IF($S$90="","",IF(COUNT(J90:R90)=0,"",IF(MAX(J90:R90)>3,$I90,""))) | U90: {=IF($E90="","",_xlfn.LET(_xlpm.matches,_xlfn._xlws.FILTER('04. Products & Services'!$J$6:$J$50,'04. Products & Services'!$E$6:$E$50=$E90,""),_xlpm.n,COUNTIF($E$6:$E90,$E90),_xlpm.v,IFERROR(INDEX(_xlpm.matches,_xlpm.n),""),IF(OR(_xlpm.v="",_xlpm.v=0),"",_xlpm.v)))} | W90: =IF($E90="","",IF(OR($U90="Yes",$V90="Yes"),"Yes",IF(AND($U90="No",$V90="No"),"No",IF(AND($U90="Under Evaluation",$V90="No"),"Under Evaluation","")))) | X90: =IF($E90="","",IFERROR(_xlfn.LET(_xlpm.v,INDEX('04. Products & Services'!$K$6:$K$50,MATCH($E90,ScopeNames,0)),IF(_xlpm.v="","",_xlpm.v)),"")) | AA90: =IF($E90="","",IF(COUNT(J90:R96)=0,"",IF(MAX(J90:J96)>=4,6,IF(MAX(K90:K96)>=4,18,IF(MAX(L90:L96)>=4,36,IF(MAX(M90:M96)>=4,72,IF(MAX(N90:N96)>=4,168,IF(MAX(O90:O96)>=4,336,IF(MAX(P90:P96)>=4,504,IF(MAX(Q90:Q96)>=4,672,IF(MAX(R90:R96)>=4,"",""))))))))))) | AB90: =IF($F90="","",IFERROR(VLOOKUP($F90,'04. Products & Services'!$B$5:$M$50,12,0),"")) | AD90: {=IF(ISBLANK(AC90),"",_xlfn.LET( _xlpm.Num,--_xlfn.TEXTBEFORE(AC90," "), _xlpm.Unit,LOWER(_xlfn.TEXTAFTER(AC90," ")), _xlfn.SWITCH(_xlpm.Unit, "hour",_xlpm.Num, "hours",_xlpm.Num, "day",_xlpm.Num*24, "days",_xlpm.Num*24, "week",_xlpm.Num*24*7, "weeks",_xlpm.Num*24*7, "month",_xlpm.Num*24*(365.25/12), "months",_xlpm.Num*24*(365.25/12), "") ))} | AG90: =IF($AF90="","",DATE(YEAR($AF90)+1,MONTH($AF90),DAY($AF90))) | AH90: {=IF($B90="","",_xlfn.LET(_xlpm.ids,'15. BCM Risk Register'!$A$6:$A$65,_xlpm.links,'15. BCM Risk Register'!$I$6:$I$65,_xlpm.hit,ISNUMBER(SEARCH(","&$B90&",",","&SUBSTITUTE(_xlpm.links," ","")&",")),IFERROR(_xlfn.TEXTJOIN(", ",TRUE,_xlfn.UNIQUE(_xlfn._xlws.FILTER(_xlpm.ids,_xlpm.hit*(_xlpm.ids<>"")))),"Not Created")))} | AI90: {=IF($B90="","",_xlfn.LET(_xlpm.ids,'15. BCM Risk Register'!$L$6:$L$65,_xlpm.links,'15. BCM Risk Register'!$I$6:$I$65,_xlpm.hit,ISNUMBER(SEARCH(","&$B90&",",","&SUBSTITUTE(_xlpm.links," ","")&",")),IFERROR(_xlfn.TEXTJOIN(", ",TRUE,_xlfn.UNIQUE(_xlfn._xlws.FILTER(_xlpm.ids,_xlpm.hit*(_xlpm.ids<>"")*(_xlpm.ids<>"Not Created")))),"Not Created")))} | AJ90: {=IF($B90="","",_xlfn.LET(_xlpm.ids,'15. BCM Risk Register'!$K$6:$K$65,_xlpm.links,'15. BCM Risk Register'!$I$6:$I$65,_xlpm.hit,ISNUMBER(SEARCH(","&$B90&",",","&SUBSTITUTE(_xlpm.links," ","")&",")),IFERROR(_xlfn.TEXTJOIN(", ",TRUE,_xlfn.UNIQUE(_xlfn._xlws.FILTER(_xlpm.ids,_xlpm.hit*(_xlpm.ids<>"")*(_xlpm.ids<>"Not Created")))),"Not Created")))}
G91: ICT | I91: Operational | T91: =IF($S$90="","",IF(COUNT(J91:R91)=0,"",IF(MAX(J91:R91)>3,$I91,"")))
G92: Data / Info | I92: Product / Service Safety | T92: =IF($S$90="","",IF(COUNT(J92:R92)=0,"",IF(MAX(J92:R92)>3,$I92,"")))
G93: 3rd Party | I93: Health, Safety & Environment | T93: =IF($S$90="","",IF(COUNT(J93:R93)=0,"",IF(MAX(J93:R93)>3,$I93,"")))
G94: Equipment / Building / Utilities | I94: Regulatory & Compliance | T94: =IF($S$90="","",IF(COUNT(J94:R94)=0,"",IF(MAX(J94:R94)>3,$I94,"")))
G95: Pre-Service | I95: Reputation | T95: =IF($S$90="","",IF(COUNT(J95:R95)=0,"",IF(MAX(J95:R95)>3,$I95,"")))
G96: Post-Service | I96: Information Technology | T96: =IF($S$90="","",IF(COUNT(J96:R96)=0,"",IF(MAX(J96:R96)>3,$I96,"")))
A97: 14 | B97: =IF($E97="","","BIA-"&TEXT(14,"000")) | C97: =IFERROR(INDEX(BusinessUnits1,MATCH(A97,'04. Products & Services'!$N$6:$N$50,0)),"") | D97: =IFERROR(INDEX(DivisionSites,MATCH(A97,'04. Products & Services'!$N$6:$N$50,0)),"") | E97: =IFERROR(INDEX(ScopeNames,MATCH(A97,'04. Products & Services'!$N$6:$N$50,0)),"") | F97: =_xlfn.XLOOKUP(E97,'04. Products & Services'!$E$5:$E$50,'04. Products & Services'!$B$5:$B$50,"") | G97: People | I97: Financial | S97: =IF(COUNT(J97:R103)=0,"",MAX(J97:R103)) | T97: =IF($S$97="","",IF(COUNT(J97:R97)=0,"",IF(MAX(J97:R97)>3,$I97,""))) | U97: {=IF($E97="","",_xlfn.LET(_xlpm.matches,_xlfn._xlws.FILTER('04. Products & Services'!$J$6:$J$50,'04. Products & Services'!$E$6:$E$50=$E97,""),_xlpm.n,COUNTIF($E$6:$E97,$E97),_xlpm.v,IFERROR(INDEX(_xlpm.matches,_xlpm.n),""),IF(OR(_xlpm.v="",_xlpm.v=0),"",_xlpm.v)))} | W97: =IF($E97="","",IF(OR($U97="Yes",$V97="Yes"),"Yes",IF(AND($U97="No",$V97="No"),"No",IF(AND($U97="Under Evaluation",$V97="No"),"Under Evaluation","")))) | X97: =IF($E97="","",IFERROR(_xlfn.LET(_xlpm.v,INDEX('04. Products & Services'!$K$6:$K$50,MATCH($E97,ScopeNames,0)),IF(_xlpm.v="","",_xlpm.v)),"")) | AA97: =IF($E97="","",IF(COUNT(J97:R103)=0,"",IF(MAX(J97:J103)>=4,6,IF(MAX(K97:K103)>=4,18,IF(MAX(L97:L103)>=4,36,IF(MAX(M97:M103)>=4,72,IF(MAX(N97:N103)>=4,168,IF(MAX(O97:O103)>=4,336,IF(MAX(P97:P103)>=4,504,IF(MAX(Q97:Q103)>=4,672,IF(MAX(R97:R103)>=4,"",""))))))))))) | AB97: =IF($F97="","",IFERROR(VLOOKUP($F97,'04. Products & Services'!$B$5:$M$50,12,0),"")) | AD97: {=IF(ISBLANK(AC97),"",_xlfn.LET( _xlpm.Num,--_xlfn.TEXTBEFORE(AC97," "), _xlpm.Unit,LOWER(_xlfn.TEXTAFTER(AC97," ")), _xlfn.SWITCH(_xlpm.Unit, "hour",_xlpm.Num, "hours",_xlpm.Num, "day",_xlpm.Num*24, "days",_xlpm.Num*24, "week",_xlpm.Num*24*7, "weeks",_xlpm.Num*24*7, "month",_xlpm.Num*24*(365.25/12), "months",_xlpm.Num*24*(365.25/12), "") ))} | AG97: =IF($AF97="","",DATE(YEAR($AF97)+1,MONTH($AF97),DAY($AF97))) | AH97: {=IF($B97="","",_xlfn.LET(_xlpm.ids,'15. BCM Risk Register'!$A$6:$A$65,_xlpm.links,'15. BCM Risk Register'!$I$6:$I$65,_xlpm.hit,ISNUMBER(SEARCH(","&$B97&",",","&SUBSTITUTE(_xlpm.links," ","")&",")),IFERROR(_xlfn.TEXTJOIN(", ",TRUE,_xlfn.UNIQUE(_xlfn._xlws.FILTER(_xlpm.ids,_xlpm.hit*(_xlpm.ids<>"")))),"Not Created")))} | AI97: {=IF($B97="","",_xlfn.LET(_xlpm.ids,'15. BCM Risk Register'!$L$6:$L$65,_xlpm.links,'15. BCM Risk Register'!$I$6:$I$65,_xlpm.hit,ISNUMBER(SEARCH(","&$B97&",",","&SUBSTITUTE(_xlpm.links," ","")&",")),IFERROR(_xlfn.TEXTJOIN(", ",TRUE,_xlfn.UNIQUE(_xlfn._xlws.FILTER(_xlpm.ids,_xlpm.hit*(_xlpm.ids<>"")*(_xlpm.ids<>"Not Created")))),"Not Created")))} | AJ97: {=IF($B97="","",_xlfn.LET(_xlpm.ids,'15. BCM Risk Register'!$K$6:$K$65,_xlpm.links,'15. BCM Risk Register'!$I$6:$I$65,_xlpm.hit,ISNUMBER(SEARCH(","&$B97&",",","&SUBSTITUTE(_xlpm.links," ","")&",")),IFERROR(_xlfn.TEXTJOIN(", ",TRUE,_xlfn.UNIQUE(_xlfn._xlws.FILTER(_xlpm.ids,_xlpm.hit*(_xlpm.ids<>"")*(_xlpm.ids<>"Not Created")))),"Not Created")))}
G98: ICT | I98: Operational | T98: =IF($S$97="","",IF(COUNT(J98:R98)=0,"",IF(MAX(J98:R98)>3,$I98,"")))
G99: Data / Info | I99: Product / Service Safety | T99: =IF($S$97="","",IF(COUNT(J99:R99)=0,"",IF(MAX(J99:R99)>3,$I99,"")))
G100: 3rd Party | I100: Health, Safety & Environment | T100: =IF($S$97="","",IF(COUNT(J100:R100)=0,"",IF(MAX(J100:R100)>3,$I100,"")))
G101: Equipment / Building / Utilities | I101: Regulatory & Compliance | T101: =IF($S$97="","",IF(COUNT(J101:R101)=0,"",IF(MAX(J101:R101)>3,$I101,"")))
...

Sheet 08. Dependency Register
A1: Step 2b - Dependency Register
A2: one row per dependency | ISO 22301: 8.2.2 Dependencies & supporting resources
A4: No. | B4: Dep ID | C4: BIA # (select) | D4: Product / Service (auto) | E4: Product / Service ID | F4: Category (select) | G4: Sub category (For ICT and Equipment) | H4: ICT/ Equipment details | I4: Dependency Name | J4: Description / Detail | K4: SPOF? (Y/N) | L4: Owner | M4: Remarks
A5: 1 | B5: =IF($I5="","","DEP-"&TEXT($A5,"000")) | C5: BIA-001 | D5: =IF($C5="","",IFERROR(_xlfn.XLOOKUP($C5,'07. BIA'!$B$6:$B$285,'07. BIA'!$E$6:$E$285,""),"")) -> cb | E5: =IF($C5="","",IFERROR(_xlfn.XLOOKUP($C5,'07. BIA'!$B$6:$B$285,'07. BIA'!$F$6:$F$285,""),"")) -> PS-001 | F5: People
A6: 2 | B6: =IF($I6="","","DEP-"&TEXT($A6,"000")) | D6: =IF($C6="","",IFERROR(_xlfn.XLOOKUP($C6,'07. BIA'!$B$6:$B$285,'07. BIA'!$E$6:$E$285,""),"")) | E6: =IF($C6="","",IFERROR(_xlfn.XLOOKUP($C6,'07. BIA'!$B$6:$B$285,'07. BIA'!$F$6:$F$285,""),""))
A7: 3 | B7: =IF($I7="","","DEP-"&TEXT($A7,"000")) | D7: =IF($C7="","",IFERROR(_xlfn.XLOOKUP($C7,'07. BIA'!$B$6:$B$285,'07. BIA'!$E$6:$E$285,""),"")) | E7: =IF($C7="","",IFERROR(_xlfn.XLOOKUP($C7,'07. BIA'!$B$6:$B$285,'07. BIA'!$F$6:$F$285,""),""))
A8: 4 | B8: =IF($I8="","","DEP-"&TEXT($A8,"000")) | D8: =IF($C8="","",IFERROR(_xlfn.XLOOKUP($C8,'07. BIA'!$B$6:$B$285,'07. BIA'!$E$6:$E$285,""),"")) | E8: =IF($C8="","",IFERROR(_xlfn.XLOOKUP($C8,'07. BIA'!$B$6:$B$285,'07. BIA'!$F$6:$F$285,""),""))
A9: 5 | B9: =IF($I9="","","DEP-"&TEXT($A9,"000")) | D9: =IF($C9="","",IFERROR(_xlfn.XLOOKUP($C9,'07. BIA'!$B$6:$B$285,'07. BIA'!$E$6:$E$285,""),"")) | E9: =IF($C9="","",IFERROR(_xlfn.XLOOKUP($C9,'07. BIA'!$B$6:$B$285,'07. BIA'!$F$6:$F$285,""),""))
A10: 6 | B10: =IF($I10="","","DEP-"&TEXT($A10,"000")) | D10: =IF($C10="","",IFERROR(_xlfn.XLOOKUP($C10,'07. BIA'!$B$6:$B$285,'07. BIA'!$E$6:$E$285,""),"")) | E10: =IF($C10="","",IFERROR(_xlfn.XLOOKUP($C10,'07. BIA'!$B$6:$B$285,'07. BIA'!$F$6:$F$285,""),""))
A11: 7 | B11: =IF($I11="","","DEP-"&TEXT($A11,"000")) | D11: =IF($C11="","",IFERROR(_xlfn.XLOOKUP($C11,'07. BIA'!$B$6:$B$285,'07. BIA'!$E$6:$E$285,""),"")) | E11: =IF($C11="","",IFERROR(_xlfn.XLOOKUP($C11,'07. BIA'!$B$6:$B$285,'07. BIA'!$F$6:$F$285,""),""))
A12: 8 | B12: =IF($I12="","","DEP-"&TEXT($A12,"000")) | D12: =IF($C12="","",IFERROR(_xlfn.XLOOKUP($C12,'07. BIA'!$B$6:$B$285,'07. BIA'!$E$6:$E$285,""),"")) | E12: =IF($C12="","",IFERROR(_xlfn.XLOOKUP($C12,'07. BIA'!$B$6:$B$285,'07. BIA'!$F$6:$F$285,""),""))
A13: 9 | B13: =IF($I13="","","DEP-"&TEXT($A13,"000")) | D13: =IF($C13="","",IFERROR(_xlfn.XLOOKUP($C13,'07. BIA'!$B$6:$B$285,'07. BIA'!$E$6:$E$285,""),"")) | E13: =IF($C13="","",IFERROR(_xlfn.XLOOKUP($C13,'07. BIA'!$B$6:$B$285,'07. BIA'!$F$6:$F$285,""),""))
A14: 10 | B14: =IF($I14="","","DEP-"&TEXT($A14,"000")) | D14: =IF($C14="","",IFERROR(_xlfn.XLOOKUP($C14,'07. BIA'!$B$6:$B$285,'07. BIA'!$E$6:$E$285,""),"")) | E14: =IF($C14="","",IFERROR(_xlfn.XLOOKUP($C14,'07. BIA'!$B$6:$B$285,'07. BIA'!$F$6:$F$285,""),""))
A15: 11 | B15: =IF($I15="","","DEP-"&TEXT($A15,"000")) | D15: =IF($C15="","",IFERROR(_xlfn.XLOOKUP($C15,'07. BIA'!$B$6:$B$285,'07. BIA'!$E$6:$E$285,""),"")) | E15: =IF($C15="","",IFERROR(_xlfn.XLOOKUP($C15,'07. BIA'!$B$6:$B$285,'07. BIA'!$F$6:$F$285,""),""))
A16: 12 | B16: =IF($I16="","","DEP-"&TEXT($A16,"000")) | D16: =IF($C16="","",IFERROR(_xlfn.XLOOKUP($C16,'07. BIA'!$B$6:$B$285,'07. BIA'!$E$6:$E$285,""),"")) | E16: =IF($C16="","",IFERROR(_xlfn.XLOOKUP($C16,'07. BIA'!$B$6:$B$285,'07. BIA'!$F$6:$F$285,""),""))
A17: 13 | B17: =IF($I17="","","DEP-"&TEXT($A17,"000")) | D17: =IF($C17="","",IFERROR(_xlfn.XLOOKUP($C17,'07. BIA'!$B$6:$B$285,'07. BIA'!$E$6:$E$285,""),"")) | E17: =IF($C17="","",IFERROR(_xlfn.XLOOKUP($C17,'07. BIA'!$B$6:$B$285,'07. BIA'!$F$6:$F$285,""),""))
... A204: 200 | B204: =IF($I204="","","DEP-"&TEXT($A204,"000")) | D204: =IF($C204="","",IFERROR(_xlfn.XLOOKUP($C204,'07. BIA'!$B$6:$B$285,'07. BIA'!$E$6:$E$285,""),"")) | E204: =IF($C204="","",IFERROR(_xlfn.XLOOKUP($C204,'07. BIA'!$B$6:$B$285,'07. BIA'!$F$6:$F$285,""),""))

Sheet 09. Risk Assumption Map
A1: Step 3 - BCM Risk Assessment by Dependency
A2: per the organisation's ERM Framework | ISO 22301: 8.2.3 Risk assessment
A4: Dependency categories | C4: People | D4: ICT | E4: Data / Info | F4: 3rd Party | G4: Equipment / Building / Utilities | H4: Pre-Service | I4: Post-Service
A5: {=lstDepCat} -> People | C5: Mass staff absence | D5: Cyberattack | E5: Critical data loss | F5: Critical supplier failure | G5: Critical site loss | H5: Critical material shortage | I5: Distribution network failure
A6: ICT | C6: Key person loss | D6: Core application outage | E6: Traceability records unavailable | F6: Import route disruption | G6: Production line failure | H6: Raw material or input shortage | I6: Warehouse or depot loss
A7: Data / Info | C7: Skilled operator shortage | D7: Data centre or cloud outage | E7: Quality / compliance records unavailable | F7: Logistics provider failure | G7: Process utility outage | H7: Packaging shortage | I7: Fleet, fuel, or route disruption
A8: 3rd Party | C8: Staff unable to access site | D8: Network or communications outage | E8: Inventory or master-data failure | F8: External utility outage | G8: Critical process equipment failure | H8: Incoming material rejection | I8: Finished-goods storage or transport failure
A9: Equipment / Building / Utilities | C9: Workforce evacuation | D9: Backup or recovery failure | E9: Regulatory records unavailable | F9: Outsourced service failure | G9: Maintenance or spare-parts shortage | H9: Material stock-out | I9: Customer channel or demand disruption
A10: Pre-Service
A11: Post-Service

Sheet 10. Risk Assessment
A1: Step 3 - BCM Risk Assessment by Dependency
A2: per the organisation's ERM Framework | ISO 22301: 8.2.3 Risk assessment
A4: Slot | B4: Risk ID # / BIA # (assoc.) | C4: BU | D4: Division | E4: Dependency categories | F4: Applicable BIA #s | G4: Risk Assumption (select or type) / Associated Product / Service (auto) | H4: Business Disruption Scenario (auto) | I4: ERM / Site Risk Register Ref# | J4: Implemented Controls | K4: Residual Likelihood (1-5) | L4: Likelihood Rating (auto) | M4: Residual Impact (1-5) | N4: Impact Rating (auto) | O4: Risk Reference (auto - ERM) | P4: Risk Rating (auto) | Q4: BCP Priority (auto) 1=Critical...4=Low | R4: Remarks | S4: S&S # (auto) | T4: R&R IDs (auto) | U4: Risk Owner | V4: Assessment Date | W4: Review Date | X4: Approver | Y4: Evidence Reference | Z4: Completion Check | AA4: Climate Relevance | AB4: Climate-Related Disruption Scenario | AC4: Climate-Sensitive Dependency / Interested Party
A5: 1 | B5: =IF($G5="","","RA-"&TEXT($A5,"000")) -> RA-001 | C5: ss | D5: hr | E5: People | F5: {=IF(C5="","",_xlfn.LET(_xlpm.bu,_xlfn.SCAN("",'07. BIA'!$C$6:$C$285,_xlfn.LAMBDA(_xlpm.a,_xlpm.v,IF(_xlpm.v="",_xlpm.a,_xlpm.v))),_xlpm.div,_xlfn.SCAN("",'07. BIA'!$D$6:$D$285,_xlfn.LAMBDA(_xlpm.a,_xlpm.v,IF(_xlpm.v="",_xlpm.a,_xlpm.v))),_xlpm.item,_xlfn.SCAN("",'07. BIA'!$E$6:$E$285,_xlfn.LAMBDA(_xlpm.a,_xlpm.v,IF(_xlpm.v="",_xlpm.a,_xlpm.v))),_xlpm.srcDep,LOWER(SUBSTITUTE(SUBSTITUTE(SUBSTITUTE('07. BIA'!$G$6:$G$285," ",""),"-",""),"/","")),_xlpm.rawKey,LOWER(SUBSTITUTE(SUBSTITUTE(SUBSTITUTE(E5," ",""),"-",""),"/","")),_xlpm.key,IF(_xlpm.rawKey="data","datainfo",_xlpm.rawKey),IF(D5="",IFERROR(_xlfn.TEXTJOIN(",",TRUE,_xlfn.UNIQUE(_xlfn._xlws.FILTER(_xlpm.item,(_xlpm.bu=C5)*(_xlpm.item<>"")))),""),IF(E5="","",IFERROR(_xlfn.TEXTJOIN(",",TRUE,_xlfn.UNIQUE(_xlfn._xlws.FILTER(_xlpm.item,(_xlpm.bu=C5)*(_xlpm.div=D5)*(_xlpm.srcDep=_xlpm.key)*('07. BIA'!$H$6:$H$285="Yes")))),"")))))} -> cb | G5: Workforce evacuation | H5: =IF($G5="","","Inability to deliver the associated products/services due to ["&$G5&"]") -> Inability to deliver the associated products/services due to [Workforce evacuation] | K5: 4 | L5: =IF($K5="","",CHOOSE($K5,"Rare","Infrequent","Occasional","Frequent","Almost Certain")) -> Frequent | M5: 4 | N5: =IF($M5="","",CHOOSE($M5,"Negligible","Minor","Medium","Critical","Catastrophic")) -> Critical | O5: =IF(OR($K5="",$M5=""),"",INDEX('20. ERM RA Guidance'!$E$79:$I$83,6-$K5,$M5)) -> 21 | P5: =IF($O5="","",IF($O5>=20,"Critical",IF($O5>=12,"Significant",IF($O5>=7,"Moderate","Low")))) -> Critical | Q5: =IF($P5="","",IF($P5="Critical",1,IF($P5="Significant",2,IF($P5="Moderate",3,4)))) -> 1 | S5: {=IF($B5="","",IFERROR(_xlfn.TEXTJOIN(",",TRUE,_xlfn.UNIQUE(_xlfn._xlws.FILTER('11. Strategies & Solutions'!$C$5:$C$64,('11. Strategies & Solutions'!$B$5:$B$64=$B5)*('11. Strategies & Solutions'!$C$5:$C$64<>"")))),"Not Created"))} -> SS-030 | T5: {=IF($B5="","",_xlfn.LET(_xlpm.ss,_xlfn._xlws.FILTER('11. Strategies & Solutions'!$C$5:$C$64,('11. Strategies & Solutions'!$B$5:$B$64=$B5)*('11. Strategies & Solutions'!$C$5:$C$64<>""),""),IFERROR(_xlfn.TEXTJOIN(",",TRUE,_xlfn.UNIQUE(_xlfn._xlws.FILTER('14. Recovery & Response'!$B$6:$B$105,ISNUMBER(_xlfn.XMATCH('14. Recovery & Response'!$C$6:$C$105,_xlpm.ss))*('14. Recovery & Response'!$B$6:$B$105<>"")))),"Not Created")))} -> RR-001 | Z5: =IF($B5="","",IF(AND($C5<>"",$D5<>"",$E5<>"",$F5<>"",$G5<>"",$H5<>"",$J5<>"",$K5<>"",$M5<>"",$U5<>"",ISNUMBER($V5),ISNUMBER($W5),$X5<>"",$Y5<>""),"Complete","Incomplete")) -> Incomplete
A6: 2 | B6: =IF($G6="","","RA-"&TEXT($A6,"000")) | F6: {=IF(C6="","",_xlfn.LET(_xlpm.bu,_xlfn.SCAN("",'07. BIA'!$C$6:$C$285,_xlfn.LAMBDA(_xlpm.a,_xlpm.v,IF(_xlpm.v="",_xlpm.a,_xlpm.v))),_xlpm.div,_xlfn.SCAN("",'07. BIA'!$D$6:$D$285,_xlfn.LAMBDA(_xlpm.a,_xlpm.v,IF(_xlpm.v="",_xlpm.a,_xlpm.v))),_xlpm.item,_xlfn.SCAN("",'07. BIA'!$E$6:$E$285,_xlfn.LAMBDA(_xlpm.a,_xlpm.v,IF(_xlpm.v="",_xlpm.a,_xlpm.v))),_xlpm.srcDep,LOWER(SUBSTITUTE(SUBSTITUTE(SUBSTITUTE('07. BIA'!$G$6:$G$285," ",""),"-",""),"/","")),_xlpm.rawKey,LOWER(SUBSTITUTE(SUBSTITUTE(SUBSTITUTE(E6," ",""),"-",""),"/","")),_xlpm.key,IF(_xlpm.rawKey="data","datainfo",_xlpm.rawKey),IF(D6="",IFERROR(_xlfn.TEXTJOIN(",",TRUE,_xlfn.UNIQUE(_xlfn._xlws.FILTER(_xlpm.item,(_xlpm.bu=C6)*(_xlpm.item<>"")))),""),IF(E6="","",IFERROR(_xlfn.TEXTJOIN(",",TRUE,_xlfn.UNIQUE(_xlfn._xlws.FILTER(_xlpm.item,(_xlpm.bu=C6)*(_xlpm.div=D6)*(_xlpm.srcDep=_xlpm.key)*('07. BIA'!$H$6:$H$285="Yes")))),"")))))} | H6: =IF($G6="","","Inability to deliver the associated products/services due to ["&$G6&"]") | L6: =IF($K6="","",CHOOSE($K6,"Rare","Infrequent","Occasional","Frequent","Almost Certain")) | N6: =IF($M6="","",CHOOSE($M6,"Negligible","Minor","Medium","Critical","Catastrophic")) | O6: =IF(OR($K6="",$M6=""),"",INDEX('20. ERM RA Guidance'!$E$79:$I$83,6-$K6,$M6)) | P6: =IF($O6="","",IF($O6>=20,"Critical",IF($O6>=12,"Significant",IF($O6>=7,"Moderate","Low")))) | Q6: =IF($P6="","",IF($P6="Critical",1,IF($P6="Significant",2,IF($P6="Moderate",3,4)))) | S6: {=IF($B6="","",IFERROR(_xlfn.TEXTJOIN(",",TRUE,_xlfn.UNIQUE(_xlfn._xlws.FILTER('11. Strategies & Solutions'!$C$5:$C$64,('11. Strategies & Solutions'!$B$5:$B$64=$B6)*('11. Strategies & Solutions'!$C$5:$C$64<>"")))),"Not Created"))} | T6: {=IF($B6="","",_xlfn.LET(_xlpm.ss,_xlfn._xlws.FILTER('11. Strategies & Solutions'!$C$5:$C$64,('11. Strategies & Solutions'!$B$5:$B$64=$B6)*('11. Strategies & Solutions'!$C$5:$C$64<>""),""),IFERROR(_xlfn.TEXTJOIN(",",TRUE,_xlfn.UNIQUE(_xlfn._xlws.FILTER('14. Recovery & Response'!$B$6:$B$105,ISNUMBER(_xlfn.XMATCH('14. Recovery & Response'!$C$6:$C$105,_xlpm.ss))*('14. Recovery & Response'!$B$6:$B$105<>"")))),"Not Created")))} | Z6: =IF($B6="","",IF(AND($C6<>"",$D6<>"",$E6<>"",$F6<>"",$G6<>"",$H6<>"",$J6<>"",$K6<>"",$M6<>"",$U6<>"",ISNUMBER($V6),ISNUMBER($W6),$X6<>"",$Y6<>""),"Complete","Incomplete"))
A7: 3 | B7: =IF($G7="","","RA-"&TEXT($A7,"000")) | F7: {=IF(C7="","",_xlfn.LET(_xlpm.bu,_xlfn.SCAN("",'07. BIA'!$C$6:$C$285,_xlfn.LAMBDA(_xlpm.a,_xlpm.v,IF(_xlpm.v="",_xlpm.a,_xlpm.v))),_xlpm.div,_xlfn.SCAN("",'07. BIA'!$D$6:$D$285,_xlfn.LAMBDA(_xlpm.a,_xlpm.v,IF(_xlpm.v="",_xlpm.a,_xlpm.v))),_xlpm.item,_xlfn.SCAN("",'07. BIA'!$E$6:$E$285,_xlfn.LAMBDA(_xlpm.a,_xlpm.v,IF(_xlpm.v="",_xlpm.a,_xlpm.v))),_xlpm.srcDep,LOWER(SUBSTITUTE(SUBSTITUTE(SUBSTITUTE('07. BIA'!$G$6:$G$285," ",""),"-",""),"/","")),_xlpm.rawKey,LOWER(SUBSTITUTE(SUBSTITUTE(SUBSTITUTE(E7," ",""),"-",""),"/","")),_xlpm.key,IF(_xlpm.rawKey="data","datainfo",_xlpm.rawKey),IF(D7="",IFERROR(_xlfn.TEXTJOIN(",",TRUE,_xlfn.UNIQUE(_xlfn._xlws.FILTER(_xlpm.item,(_xlpm.bu=C7)*(_xlpm.item<>"")))),""),IF(E7="","",IFERROR(_xlfn.TEXTJOIN(",",TRUE,_xlfn.UNIQUE(_xlfn._xlws.FILTER(_xlpm.item,(_xlpm.bu=C7)*(_xlpm.div=D7)*(_xlpm.srcDep=_xlpm.key)*('07. BIA'!$H$6:$H$285="Yes")))),"")))))} | H7: =IF($G7="","","Inability to deliver the associated products/services due to ["&$G7&"]") | L7: =IF($K7="","",CHOOSE($K7,"Rare","Infrequent","Occasional","Frequent","Almost Certain")) | N7: =IF($M7="","",CHOOSE($M7,"Negligible","Minor","Medium","Critical","Catastrophic")) | O7: =IF(OR($K7="",$M7=""),"",INDEX('20. ERM RA Guidance'!$E$79:$I$83,6-$K7,$M7)) | P7: =IF($O7="","",IF($O7>=20,"Critical",IF($O7>=12,"Significant",IF($O7>=7,"Moderate","Low")))) | Q7: =IF($P7="","",IF($P7="Critical",1,IF($P7="Significant",2,IF($P7="Moderate",3,4)))) | S7: {=IF($B7="","",IFERROR(_xlfn.TEXTJOIN(",",TRUE,_xlfn.UNIQUE(_xlfn._xlws.FILTER('11. Strategies & Solutions'!$C$5:$C$64,('11. Strategies & Solutions'!$B$5:$B$64=$B7)*('11. Strategies & Solutions'!$C$5:$C$64<>"")))),"Not Created"))} | T7: {=IF($B7="","",_xlfn.LET(_xlpm.ss,_xlfn._xlws.FILTER('11. Strategies & Solutions'!$C$5:$C$64,('11. Strategies & Solutions'!$B$5:$B$64=$B7)*('11. Strategies & Solutions'!$C$5:$C$64<>""),""),IFERROR(_xlfn.TEXTJOIN(",",TRUE,_xlfn.UNIQUE(_xlfn._xlws.FILTER('14. Recovery & Response'!$B$6:$B$105,ISNUMBER(_xlfn.XMATCH('14. Recovery & Response'!$C$6:$C$105,_xlpm.ss))*('14. Recovery & Response'!$B$6:$B$105<>"")))),"Not Created")))} | Z7: =IF($B7="","",IF(AND($C7<>"",$D7<>"",$E7<>"",$F7<>"",$G7<>"",$H7<>"",$J7<>"",$K7<>"",$M7<>"",$U7<>"",ISNUMBER($V7),ISNUMBER($W7),$X7<>"",$Y7<>""),"Complete","Incomplete"))
A8: 4 | B8: =IF($G8="","","RA-"&TEXT($A8,"000")) | F8: {=IF(C8="","",_xlfn.LET(_xlpm.bu,_xlfn.SCAN("",'07. BIA'!$C$6:$C$285,_xlfn.LAMBDA(_xlpm.a,_xlpm.v,IF(_xlpm.v="",_xlpm.a,_xlpm.v))),_xlpm.div,_xlfn.SCAN("",'07. BIA'!$D$6:$D$285,_xlfn.LAMBDA(_xlpm.a,_xlpm.v,IF(_xlpm.v="",_xlpm.a,_xlpm.v))),_xlpm.item,_xlfn.SCAN("",'07. BIA'!$E$6:$E$285,_xlfn.LAMBDA(_xlpm.a,_xlpm.v,IF(_xlpm.v="",_xlpm.a,_xlpm.v))),_xlpm.srcDep,LOWER(SUBSTITUTE(SUBSTITUTE(SUBSTITUTE('07. BIA'!$G$6:$G$285," ",""),"-",""),"/","")),_xlpm.rawKey,LOWER(SUBSTITUTE(SUBSTITUTE(SUBSTITUTE(E8," ",""),"-",""),"/","")),_xlpm.key,IF(_xlpm.rawKey="data","datainfo",_xlpm.rawKey),IF(D8="",IFERROR(_xlfn.TEXTJOIN(",",TRUE,_xlfn.UNIQUE(_xlfn._xlws.FILTER(_xlpm.item,(_xlpm.bu=C8)*(_xlpm.item<>"")))),""),IF(E8="","",IFERROR(_xlfn.TEXTJOIN(",",TRUE,_xlfn.UNIQUE(_xlfn._xlws.FILTER(_xlpm.item,(_xlpm.bu=C8)*(_xlpm.div=D8)*(_xlpm.srcDep=_xlpm.key)*('07. BIA'!$H$6:$H$285="Yes")))),"")))))} | H8: =IF($G8="","","Inability to deliver the associated products/services due to ["&$G8&"]") | L8: =IF($K8="","",CHOOSE($K8,"Rare","Infrequent","Occasional","Frequent","Almost Certain")) | N8: =IF($M8="","",CHOOSE($M8,"Negligible","Minor","Medium","Critical","Catastrophic")) | O8: =IF(OR($K8="",$M8=""),"",INDEX('20. ERM RA Guidance'!$E$79:$I$83,6-$K8,$M8)) | P8: =IF($O8="","",IF($O8>=20,"Critical",IF($O8>=12,"Significant",IF($O8>=7,"Moderate","Low")))) | Q8: =IF($P8="","",IF($P8="Critical",1,IF($P8="Significant",2,IF($P8="Moderate",3,4)))) | S8: {=IF($B8="","",IFERROR(_xlfn.TEXTJOIN(",",TRUE,_xlfn.UNIQUE(_xlfn._xlws.FILTER('11. Strategies & Solutions'!$C$5:$C$64,('11. Strategies & Solutions'!$B$5:$B$64=$B8)*('11. Strategies & Solutions'!$C$5:$C$64<>"")))),"Not Created"))} | T8: {=IF($B8="","",_xlfn.LET(_xlpm.ss,_xlfn._xlws.FILTER('11. Strategies & Solutions'!$C$5:$C$64,('11. Strategies & Solutions'!$B$5:$B$64=$B8)*('11. Strategies & Solutions'!$C$5:$C$64<>""),""),IFERROR(_xlfn.TEXTJOIN(",",TRUE,_xlfn.UNIQUE(_xlfn._xlws.FILTER('14. Recovery & Response'!$B$6:$B$105,ISNUMBER(_xlfn.XMATCH('14. Recovery & Response'!$C$6:$C$105,_xlpm.ss))*('14. Recovery & Response'!$B$6:$B$105<>"")))),"Not Created")))} | Z8: =IF($B8="","",IF(AND($C8<>"",$D8<>"",$E8<>"",$F8<>"",$G8<>"",$H8<>"",$J8<>"",$K8<>"",$M8<>"",$U8<>"",ISNUMBER($V8),ISNUMBER($W8),$X8<>"",$Y8<>""),"Complete","Incomplete"))
A9: 5 | B9: =IF($G9="","","RA-"&TEXT($A9,"000")) | F9: {=IF(C9="","",_xlfn.LET(_xlpm.bu,_xlfn.SCAN("",'07. BIA'!$C$6:$C$285,_xlfn.LAMBDA(_xlpm.a,_xlpm.v,IF(_xlpm.v="",_xlpm.a,_xlpm.v))),_xlpm.div,_xlfn.SCAN("",'07. BIA'!$D$6:$D$285,_xlfn.LAMBDA(_xlpm.a,_xlpm.v,IF(_xlpm.v="",_xlpm.a,_xlpm.v))),_xlpm.item,_xlfn.SCAN("",'07. BIA'!$E$6:$E$285,_xlfn.LAMBDA(_xlpm.a,_xlpm.v,IF(_xlpm.v="",_xlpm.a,_xlpm.v))),_xlpm.srcDep,LOWER(SUBSTITUTE(SUBSTITUTE(SUBSTITUTE('07. BIA'!$G$6:$G$285," ",""),"-",""),"/","")),_xlpm.rawKey,LOWER(SUBSTITUTE(SUBSTITUTE(SUBSTITUTE(E9," ",""),"-",""),"/","")),_xlpm.key,IF(_xlpm.rawKey="data","datainfo",_xlpm.rawKey),IF(D9="",IFERROR(_xlfn.TEXTJOIN(",",TRUE,_xlfn.UNIQUE(_xlfn._xlws.FILTER(_xlpm.item,(_xlpm.bu=C9)*(_xlpm.item<>"")))),""),IF(E9="","",IFERROR(_xlfn.TEXTJOIN(",",TRUE,_xlfn.UNIQUE(_xlfn._xlws.FILTER(_xlpm.item,(_xlpm.bu=C9)*(_xlpm.div=D9)*(_xlpm.srcDep=_xlpm.key)*('07. BIA'!$H$6:$H$285="Yes")))),"")))))} | H9: =IF($G9="","","Inability to deliver the associated products/services due to ["&$G9&"]") | L9: =IF($K9="","",CHOOSE($K9,"Rare","Infrequent","Occasional","Frequent","Almost Certain")) | N9: =IF($M9="","",CHOOSE($M9,"Negligible","Minor","Medium","Critical","Catastrophic")) | O9: =IF(OR($K9="",$M9=""),"",INDEX('20. ERM RA Guidance'!$E$79:$I$83,6-$K9,$M9)) | P9: =IF($O9="","",IF($O9>=20,"Critical",IF($O9>=12,"Significant",IF($O9>=7,"Moderate","Low")))) | Q9: =IF($P9="","",IF($P9="Critical",1,IF($P9="Significant",2,IF($P9="Moderate",3,4)))) | S9: {=IF($B9="","",IFERROR(_xlfn.TEXTJOIN(",",TRUE,_xlfn.UNIQUE(_xlfn._xlws.FILTER('11. Strategies & Solutions'!$C$5:$C$64,('11. Strategies & Solutions'!$B$5:$B$64=$B9)*('11. Strategies & Solutions'!$C$5:$C$64<>"")))),"Not Created"))} | T9: {=IF($B9="","",_xlfn.LET(_xlpm.ss,_xlfn._xlws.FILTER('11. Strategies & Solutions'!$C$5:$C$64,('11. Strategies & Solutions'!$B$5:$B$64=$B9)*('11. Strategies & Solutions'!$C$5:$C$64<>""),""),IFERROR(_xlfn.TEXTJOIN(",",TRUE,_xlfn.UNIQUE(_xlfn._xlws.FILTER('14. Recovery & Response'!$B$6:$B$105,ISNUMBER(_xlfn.XMATCH('14. Recovery & Response'!$C$6:$C$105,_xlpm.ss))*('14. Recovery & Response'!$B$6:$B$105<>"")))),"Not Created")))} | Z9: =IF($B9="","",IF(AND($C9<>"",$D9<>"",$E9<>"",$F9<>"",$G9<>"",$H9<>"",$J9<>"",$K9<>"",$M9<>"",$U9<>"",ISNUMBER($V9),ISNUMBER($W9),$X9<>"",$Y9<>""),"Complete","Incomplete"))
A10: 6 | B10: =IF($G10="","","RA-"&TEXT($A10,"000")) | F10: {=IF(C10="","",_xlfn.LET(_xlpm.bu,_xlfn.SCAN("",'07. BIA'!$C$6:$C$285,_xlfn.LAMBDA(_xlpm.a,_xlpm.v,IF(_xlpm.v="",_xlpm.a,_xlpm.v))),_xlpm.div,_xlfn.SCAN("",'07. BIA'!$D$6:$D$285,_xlfn.LAMBDA(_xlpm.a,_xlpm.v,IF(_xlpm.v="",_xlpm.a,_xlpm.v))),_xlpm.item,_xlfn.SCAN("",'07. BIA'!$E$6:$E$285,_xlfn.LAMBDA(_xlpm.a,_xlpm.v,IF(_xlpm.v="",_xlpm.a,_xlpm.v))),_xlpm.srcDep,LOWER(SUBSTITUTE(SUBSTITUTE(SUBSTITUTE('07. BIA'!$G$6:$G$285," ",""),"-",""),"/","")),_xlpm.rawKey,LOWER(SUBSTITUTE(SUBSTITUTE(SUBSTITUTE(E10," ",""),"-",""),"/","")),_xlpm.key,IF(_xlpm.rawKey="data","datainfo",_xlpm.rawKey),IF(D10="",IFERROR(_xlfn.TEXTJOIN(",",TRUE,_xlfn.UNIQUE(_xlfn._xlws.FILTER(_xlpm.item,(_xlpm.bu=C10)*(_xlpm.item<>"")))),""),IF(E10="","",IFERROR(_xlfn.TEXTJOIN(",",TRUE,_xlfn.UNIQUE(_xlfn._xlws.FILTER(_xlpm.item,(_xlpm.bu=C10)*(_xlpm.div=D10)*(_xlpm.srcDep=_xlpm.key)*('07. BIA'!$H$6:$H$285="Yes")))),"")))))} | H10: =IF($G10="","","Inability to deliver the associated products/services due to ["&$G10&"]") | L10: =IF($K10="","",CHOOSE($K10,"Rare","Infrequent","Occasional","Frequent","Almost Certain")) | N10: =IF($M10="","",CHOOSE($M10,"Negligible","Minor","Medium","Critical","Catastrophic")) | O10: =IF(OR($K10="",$M10=""),"",INDEX('20. ERM RA Guidance'!$E$79:$I$83,6-$K10,$M10)) | P10: =IF($O10="","",IF($O10>=20,"Critical",IF($O10>=12,"Significant",IF($O10>=7,"Moderate","Low")))) | Q10: =IF($P10="","",IF($P10="Critical",1,IF($P10="Significant",2,IF($P10="Moderate",3,4)))) | S10: {=IF($B10="","",IFERROR(_xlfn.TEXTJOIN(",",TRUE,_xlfn.UNIQUE(_xlfn._xlws.FILTER('11. Strategies & Solutions'!$C$5:$C$64,('11. Strategies & Solutions'!$B$5:$B$64=$B10)*('11. Strategies & Solutions'!$C$5:$C$64<>"")))),"Not Created"))} | T10: {=IF($B10="","",_xlfn.LET(_xlpm.ss,_xlfn._xlws.FILTER('11. Strategies & Solutions'!$C$5:$C$64,('11. Strategies & Solutions'!$B$5:$B$64=$B10)*('11. Strategies & Solutions'!$C$5:$C$64<>""),""),IFERROR(_xlfn.TEXTJOIN(",",TRUE,_xlfn.UNIQUE(_xlfn._xlws.FILTER('14. Recovery & Response'!$B$6:$B$105,ISNUMBER(_xlfn.XMATCH('14. Recovery & Response'!$C$6:$C$105,_xlpm.ss))*('14. Recovery & Response'!$B$6:$B$105<>"")))),"Not Created")))} | Z10: =IF($B10="","",IF(AND($C10<>"",$D10<>"",$E10<>"",$F10<>"",$G10<>"",$H10<>"",$J10<>"",$K10<>"",$M10<>"",$U10<>"",ISNUMBER($V10),ISNUMBER($W10),$X10<>"",$Y10<>""),"Complete","Incomplete"))
A11: 7 | B11: =IF($G11="","","RA-"&TEXT($A11,"000")) | F11: {=IF(C11="","",_xlfn.LET(_xlpm.bu,_xlfn.SCAN("",'07. BIA'!$C$6:$C$285,_xlfn.LAMBDA(_xlpm.a,_xlpm.v,IF(_xlpm.v="",_xlpm.a,_xlpm.v))),_xlpm.div,_xlfn.SCAN("",'07. BIA'!$D$6:$D$285,_xlfn.LAMBDA(_xlpm.a,_xlpm.v,IF(_xlpm.v="",_xlpm.a,_xlpm.v))),_xlpm.item,_xlfn.SCAN("",'07. BIA'!$E$6:$E$285,_xlfn.LAMBDA(_xlpm.a,_xlpm.v,IF(_xlpm.v="",_xlpm.a,_xlpm.v))),_xlpm.srcDep,LOWER(SUBSTITUTE(SUBSTITUTE(SUBSTITUTE('07. BIA'!$G$6:$G$285," ",""),"-",""),"/","")),_xlpm.rawKey,LOWER(SUBSTITUTE(SUBSTITUTE(SUBSTITUTE(E11," ",""),"-",""),"/","")),_xlpm.key,IF(_xlpm.rawKey="data","datainfo",_xlpm.rawKey),IF(D11="",IFERROR(_xlfn.TEXTJOIN(",",TRUE,_xlfn.UNIQUE(_xlfn._xlws.FILTER(_xlpm.item,(_xlpm.bu=C11)*(_xlpm.item<>"")))),""),IF(E11="","",IFERROR(_xlfn.TEXTJOIN(",",TRUE,_xlfn.UNIQUE(_xlfn._xlws.FILTER(_xlpm.item,(_xlpm.bu=C11)*(_xlpm.div=D11)*(_xlpm.srcDep=_xlpm.key)*('07. BIA'!$H$6:$H$285="Yes")))),"")))))} | H11: =IF($G11="","","Inability to deliver the associated products/services due to ["&$G11&"]") | L11: =IF($K11="","",CHOOSE($K11,"Rare","Infrequent","Occasional","Frequent","Almost Certain")) | N11: =IF($M11="","",CHOOSE($M11,"Negligible","Minor","Medium","Critical","Catastrophic")) | O11: =IF(OR($K11="",$M11=""),"",INDEX('20. ERM RA Guidance'!$E$79:$I$83,6-$K11,$M11)) | P11: =IF($O11="","",IF($O11>=20,"Critical",IF($O11>=12,"Significant",IF($O11>=7,"Moderate","Low")))) | Q11: =IF($P11="","",IF($P11="Critical",1,IF($P11="Significant",2,IF($P11="Moderate",3,4)))) | S11: {=IF($B11="","",IFERROR(_xlfn.TEXTJOIN(",",TRUE,_xlfn.UNIQUE(_xlfn._xlws.FILTER('11. Strategies & Solutions'!$C$5:$C$64,('11. Strategies & Solutions'!$B$5:$B$64=$B11)*('11. Strategies & Solutions'!$C$5:$C$64<>"")))),"Not Created"))} | T11: {=IF($B11="","",_xlfn.LET(_xlpm.ss,_xlfn._xlws.FILTER('11. Strategies & Solutions'!$C$5:$C$64,('11. Strategies & Solutions'!$B$5:$B$64=$B11)*('11. Strategies & Solutions'!$C$5:$C$64<>""),""),IFERROR(_xlfn.TEXTJOIN(",",TRUE,_xlfn.UNIQUE(_xlfn._xlws.FILTER('14. Recovery & Response'!$B$6:$B$105,ISNUMBER(_xlfn.XMATCH('14. Recovery & Response'!$C$6:$C$105,_xlpm.ss))*('14. Recovery & Response'!$B$6:$B$105<>"")))),"Not Created")))} | Z11: =IF($B11="","",IF(AND($C11<>"",$D11<>"",$E11<>"",$F11<>"",$G11<>"",$H11<>"",$J11<>"",$K11<>"",$M11<>"",$U11<>"",ISNUMBER($V11),ISNUMBER($W11),$X11<>"",$Y11<>""),"Complete","Incomplete"))
A12: 8 | B12: =IF($G12="","","RA-"&TEXT($A12,"000")) | F12: {=IF(C12="","",_xlfn.LET(_xlpm.bu,_xlfn.SCAN("",'07. BIA'!$C$6:$C$285,_xlfn.LAMBDA(_xlpm.a,_xlpm.v,IF(_xlpm.v="",_xlpm.a,_xlpm.v))),_xlpm.div,_xlfn.SCAN("",'07. BIA'!$D$6:$D$285,_xlfn.LAMBDA(_xlpm.a,_xlpm.v,IF(_xlpm.v="",_xlpm.a,_xlpm.v))),_xlpm.item,_xlfn.SCAN("",'07. BIA'!$E$6:$E$285,_xlfn.LAMBDA(_xlpm.a,_xlpm.v,IF(_xlpm.v="",_xlpm.a,_xlpm.v))),_xlpm.srcDep,LOWER(SUBSTITUTE(SUBSTITUTE(SUBSTITUTE('07. BIA'!$G$6:$G$285," ",""),"-",""),"/","")),_xlpm.rawKey,LOWER(SUBSTITUTE(SUBSTITUTE(SUBSTITUTE(E12," ",""),"-",""),"/","")),_xlpm.key,IF(_xlpm.rawKey="data","datainfo",_xlpm.rawKey),IF(D12="",IFERROR(_xlfn.TEXTJOIN(",",TRUE,_xlfn.UNIQUE(_xlfn._xlws.FILTER(_xlpm.item,(_xlpm.bu=C12)*(_xlpm.item<>"")))),""),IF(E12="","",IFERROR(_xlfn.TEXTJOIN(",",TRUE,_xlfn.UNIQUE(_xlfn._xlws.FILTER(_xlpm.item,(_xlpm.bu=C12)*(_xlpm.div=D12)*(_xlpm.srcDep=_xlpm.key)*('07. BIA'!$H$6:$H$285="Yes")))),"")))))} | H12: =IF($G12="","","Inability to deliver the associated products/services due to ["&$G12&"]") | L12: =IF($K12="","",CHOOSE($K12,"Rare","Infrequent","Occasional","Frequent","Almost Certain")) | N12: =IF($M12="","",CHOOSE($M12,"Negligible","Minor","Medium","Critical","Catastrophic")) | O12: =IF(OR($K12="",$M12=""),"",INDEX('20. ERM RA Guidance'!$E$79:$I$83,6-$K12,$M12)) | P12: =IF($O12="","",IF($O12>=20,"Critical",IF($O12>=12,"Significant",IF($O12>=7,"Moderate","Low")))) | Q12: =IF($P12="","",IF($P12="Critical",1,IF($P12="Significant",2,IF($P12="Moderate",3,4)))) | S12: {=IF($B12="","",IFERROR(_xlfn.TEXTJOIN(",",TRUE,_xlfn.UNIQUE(_xlfn._xlws.FILTER('11. Strategies & Solutions'!$C$5:$C$64,('11. Strategies & Solutions'!$B$5:$B$64=$B12)*('11. Strategies & Solutions'!$C$5:$C$64<>"")))),"Not Created"))} | T12: {=IF($B12="","",_xlfn.LET(_xlpm.ss,_xlfn._xlws.FILTER('11. Strategies & Solutions'!$C$5:$C$64,('11. Strategies & Solutions'!$B$5:$B$64=$B12)*('11. Strategies & Solutions'!$C$5:$C$64<>""),""),IFERROR(_xlfn.TEXTJOIN(",",TRUE,_xlfn.UNIQUE(_xlfn._xlws.FILTER('14. Recovery & Response'!$B$6:$B$105,ISNUMBER(_xlfn.XMATCH('14. Recovery & Response'!$C$6:$C$105,_xlpm.ss))*('14. Recovery & Response'!$B$6:$B$105<>"")))),"Not Created")))} | Z12: =IF($B12="","",IF(AND($C12<>"",$D12<>"",$E12<>"",$F12<>"",$G12<>"",$H12<>"",$J12<>"",$K12<>"",$M12<>"",$U12<>"",ISNUMBER($V12),ISNUMBER($W12),$X12<>"",$Y12<>""),"Complete","Incomplete"))
A13: 9 | B13: =IF($G13="","","RA-"&TEXT($A13,"000")) | F13: {=IF(C13="","",_xlfn.LET(_xlpm.bu,_xlfn.SCAN("",'07. BIA'!$C$6:$C$285,_xlfn.LAMBDA(_xlpm.a,_xlpm.v,IF(_xlpm.v="",_xlpm.a,_xlpm.v))),_xlpm.div,_xlfn.SCAN("",'07. BIA'!$D$6:$D$285,_xlfn.LAMBDA(_xlpm.a,_xlpm.v,IF(_xlpm.v="",_xlpm.a,_xlpm.v))),_xlpm.item,_xlfn.SCAN("",'07. BIA'!$E$6:$E$285,_xlfn.LAMBDA(_xlpm.a,_xlpm.v,IF(_xlpm.v="",_xlpm.a,_xlpm.v))),_xlpm.srcDep,LOWER(SUBSTITUTE(SUBSTITUTE(SUBSTITUTE('07. BIA'!$G$6:$G$285," ",""),"-",""),"/","")),_xlpm.rawKey,LOWER(SUBSTITUTE(SUBSTITUTE(SUBSTITUTE(E13," ",""),"-",""),"/","")),_xlpm.key,IF(_xlpm.rawKey="data","datainfo",_xlpm.rawKey),IF(D13="",IFERROR(_xlfn.TEXTJOIN(",",TRUE,_xlfn.UNIQUE(_xlfn._xlws.FILTER(_xlpm.item,(_xlpm.bu=C13)*(_xlpm.item<>"")))),""),IF(E13="","",IFERROR(_xlfn.TEXTJOIN(",",TRUE,_xlfn.UNIQUE(_xlfn._xlws.FILTER(_xlpm.item,(_xlpm.bu=C13)*(_xlpm.div=D13)*(_xlpm.srcDep=_xlpm.key)*('07. BIA'!$H$6:$H$285="Yes")))),"")))))} | H13: =IF($G13="","","Inability to deliver the associated products/services due to ["&$G13&"]") | L13: =IF($K13="","",CHOOSE($K13,"Rare","Infrequent","Occasional","Frequent","Almost Certain")) | N13: =IF($M13="","",CHOOSE($M13,"Negligible","Minor","Medium","Critical","Catastrophic")) | O13: =IF(OR($K13="",$M13=""),"",INDEX('20. ERM RA Guidance'!$E$79:$I$83,6-$K13,$M13)) | P13: =IF($O13="","",IF($O13>=20,"Critical",IF($O13>=12,"Significant",IF($O13>=7,"Moderate","Low")))) | Q13: =IF($P13="","",IF($P13="Critical",1,IF($P13="Significant",2,IF($P13="Moderate",3,4)))) | S13: {=IF($B13="","",IFERROR(_xlfn.TEXTJOIN(",",TRUE,_xlfn.UNIQUE(_xlfn._xlws.FILTER('11. Strategies & Solutions'!$C$5:$C$64,('11. Strategies & Solutions'!$B$5:$B$64=$B13)*('11. Strategies & Solutions'!$C$5:$C$64<>"")))),"Not Created"))} | T13: {=IF($B13="","",_xlfn.LET(_xlpm.ss,_xlfn._xlws.FILTER('11. Strategies & Solutions'!$C$5:$C$64,('11. Strategies & Solutions'!$B$5:$B$64=$B13)*('11. Strategies & Solutions'!$C$5:$C$64<>""),""),IFERROR(_xlfn.TEXTJOIN(",",TRUE,_xlfn.UNIQUE(_xlfn._xlws.FILTER('14. Recovery & Response'!$B$6:$B$105,ISNUMBER(_xlfn.XMATCH('14. Recovery & Response'!$C$6:$C$105,_xlpm.ss))*('14. Recovery & Response'!$B$6:$B$105<>"")))),"Not Created")))} | Z13: =IF($B13="","",IF(AND($C13<>"",$D13<>"",$E13<>"",$F13<>"",$G13<>"",$H13<>"",$J13<>"",$K13<>"",$M13<>"",$U13<>"",ISNUMBER($V13),ISNUMBER($W13),$X13<>"",$Y13<>""),"Complete","Incomplete"))
A14: 10 | B14: =IF($G14="","","RA-"&TEXT($A14,"000")) | F14: {=IF(C14="","",_xlfn.LET(_xlpm.bu,_xlfn.SCAN("",'07. BIA'!$C$6:$C$285,_xlfn.LAMBDA(_xlpm.a,_xlpm.v,IF(_xlpm.v="",_xlpm.a,_xlpm.v))),_xlpm.div,_xlfn.SCAN("",'07. BIA'!$D$6:$D$285,_xlfn.LAMBDA(_xlpm.a,_xlpm.v,IF(_xlpm.v="",_xlpm.a,_xlpm.v))),_xlpm.item,_xlfn.SCAN("",'07. BIA'!$E$6:$E$285,_xlfn.LAMBDA(_xlpm.a,_xlpm.v,IF(_xlpm.v="",_xlpm.a,_xlpm.v))),_xlpm.srcDep,LOWER(SUBSTITUTE(SUBSTITUTE(SUBSTITUTE('07. BIA'!$G$6:$G$285," ",""),"-",""),"/","")),_xlpm.rawKey,LOWER(SUBSTITUTE(SUBSTITUTE(SUBSTITUTE(E14," ",""),"-",""),"/","")),_xlpm.key,IF(_xlpm.rawKey="data","datainfo",_xlpm.rawKey),IF(D14="",IFERROR(_xlfn.TEXTJOIN(",",TRUE,_xlfn.UNIQUE(_xlfn._xlws.FILTER(_xlpm.item,(_xlpm.bu=C14)*(_xlpm.item<>"")))),""),IF(E14="","",IFERROR(_xlfn.TEXTJOIN(",",TRUE,_xlfn.UNIQUE(_xlfn._xlws.FILTER(_xlpm.item,(_xlpm.bu=C14)*(_xlpm.div=D14)*(_xlpm.srcDep=_xlpm.key)*('07. BIA'!$H$6:$H$285="Yes")))),"")))))} | H14: =IF($G14="","","Inability to deliver the associated products/services due to ["&$G14&"]") | L14: =IF($K14="","",CHOOSE($K14,"Rare","Infrequent","Occasional","Frequent","Almost Certain")) | N14: =IF($M14="","",CHOOSE($M14,"Negligible","Minor","Medium","Critical","Catastrophic")) | O14: =IF(OR($K14="",$M14=""),"",INDEX('20. ERM RA Guidance'!$E$79:$I$83,6-$K14,$M14)) | P14: =IF($O14="","",IF($O14>=20,"Critical",IF($O14>=12,"Significant",IF($O14>=7,"Moderate","Low")))) | Q14: =IF($P14="","",IF($P14="Critical",1,IF($P14="Significant",2,IF($P14="Moderate",3,4)))) | S14: {=IF($B14="","",IFERROR(_xlfn.TEXTJOIN(",",TRUE,_xlfn.UNIQUE(_xlfn._xlws.FILTER('11. Strategies & Solutions'!$C$5:$C$64,('11. Strategies & Solutions'!$B$5:$B$64=$B14)*('11. Strategies & Solutions'!$C$5:$C$64<>"")))),"Not Created"))} | T14: {=IF($B14="","",_xlfn.LET(_xlpm.ss,_xlfn._xlws.FILTER('11. Strategies & Solutions'!$C$5:$C$64,('11. Strategies & Solutions'!$B$5:$B$64=$B14)*('11. Strategies & Solutions'!$C$5:$C$64<>""),""),IFERROR(_xlfn.TEXTJOIN(",",TRUE,_xlfn.UNIQUE(_xlfn._xlws.FILTER('14. Recovery & Response'!$B$6:$B$105,ISNUMBER(_xlfn.XMATCH('14. Recovery & Response'!$C$6:$C$105,_xlpm.ss))*('14. Recovery & Response'!$B$6:$B$105<>"")))),"Not Created")))} | Z14: =IF($B14="","",IF(AND($C14<>"",$D14<>"",$E14<>"",$F14<>"",$G14<>"",$H14<>"",$J14<>"",$K14<>"",$M14<>"",$U14<>"",ISNUMBER($V14),ISNUMBER($W14),$X14<>"",$Y14<>""),"Complete","Incomplete"))
A15: 11 | B15: =IF($G15="","","RA-"&TEXT($A15,"000")) | F15: {=IF(C15="","",_xlfn.LET(_xlpm.bu,_xlfn.SCAN("",'07. BIA'!$C$6:$C$285,_xlfn.LAMBDA(_xlpm.a,_xlpm.v,IF(_xlpm.v="",_xlpm.a,_xlpm.v))),_xlpm.div,_xlfn.SCAN("",'07. BIA'!$D$6:$D$285,_xlfn.LAMBDA(_xlpm.a,_xlpm.v,IF(_xlpm.v="",_xlpm.a,_xlpm.v))),_xlpm.item,_xlfn.SCAN("",'07. BIA'!$E$6:$E$285,_xlfn.LAMBDA(_xlpm.a,_xlpm.v,IF(_xlpm.v="",_xlpm.a,_xlpm.v))),_xlpm.srcDep,LOWER(SUBSTITUTE(SUBSTITUTE(SUBSTITUTE('07. BIA'!$G$6:$G$285," ",""),"-",""),"/","")),_xlpm.rawKey,LOWER(SUBSTITUTE(SUBSTITUTE(SUBSTITUTE(E15," ",""),"-",""),"/","")),_xlpm.key,IF(_xlpm.rawKey="data","datainfo",_xlpm.rawKey),IF(D15="",IFERROR(_xlfn.TEXTJOIN(",",TRUE,_xlfn.UNIQUE(_xlfn._xlws.FILTER(_xlpm.item,(_xlpm.bu=C15)*(_xlpm.item<>"")))),""),IF(E15="","",IFERROR(_xlfn.TEXTJOIN(",",TRUE,_xlfn.UNIQUE(_xlfn._xlws.FILTER(_xlpm.item,(_xlpm.bu=C15)*(_xlpm.div=D15)*(_xlpm.srcDep=_xlpm.key)*('07. BIA'!$H$6:$H$285="Yes")))),"")))))} | H15: =IF($G15="","","Inability to deliver the associated products/services due to ["&$G15&"]") | L15: =IF($K15="","",CHOOSE($K15,"Rare","Infrequent","Occasional","Frequent","Almost Certain")) | N15: =IF($M15="","",CHOOSE($M15,"Negligible","Minor","Medium","Critical","Catastrophic")) | O15: =IF(OR($K15="",$M15=""),"",INDEX('20. ERM RA Guidance'!$E$79:$I$83,6-$K15,$M15)) | P15: =IF($O15="","",IF($O15>=20,"Critical",IF($O15>=12,"Significant",IF($O15>=7,"Moderate","Low")))) | Q15: =IF($P15="","",IF($P15="Critical",1,IF($P15="Significant",2,IF($P15="Moderate",3,4)))) | S15: {=IF($B15="","",IFERROR(_xlfn.TEXTJOIN(",",TRUE,_xlfn.UNIQUE(_xlfn._xlws.FILTER('11. Strategies & Solutions'!$C$5:$C$64,('11. Strategies & Solutions'!$B$5:$B$64=$B15)*('11. Strategies & Solutions'!$C$5:$C$64<>"")))),"Not Created"))} | T15: {=IF($B15="","",_xlfn.LET(_xlpm.ss,_xlfn._xlws.FILTER('11. Strategies & Solutions'!$C$5:$C$64,('11. Strategies & Solutions'!$B$5:$B$64=$B15)*('11. Strategies & Solutions'!$C$5:$C$64<>""),""),IFERROR(_xlfn.TEXTJOIN(",",TRUE,_xlfn.UNIQUE(_xlfn._xlws.FILTER('14. Recovery & Response'!$B$6:$B$105,ISNUMBER(_xlfn.XMATCH('14. Recovery & Response'!$C$6:$C$105,_xlpm.ss))*('14. Recovery & Response'!$B$6:$B$105<>"")))),"Not Created")))} | Z15: =IF($B15="","",IF(AND($C15<>"",$D15<>"",$E15<>"",$F15<>"",$G15<>"",$H15<>"",$J15<>"",$K15<>"",$M15<>"",$U15<>"",ISNUMBER($V15),ISNUMBER($W15),$X15<>"",$Y15<>""),"Complete","Incomplete"))
A16: 12 | B16: =IF($G16="","","RA-"&TEXT($A16,"000")) | F16: {=IF(C16="","",_xlfn.LET(_xlpm.bu,_xlfn.SCAN("",'07. BIA'!$C$6:$C$285,_xlfn.LAMBDA(_xlpm.a,_xlpm.v,IF(_xlpm.v="",_xlpm.a,_xlpm.v))),_xlpm.div,_xlfn.SCAN("",'07. BIA'!$D$6:$D$285,_xlfn.LAMBDA(_xlpm.a,_xlpm.v,IF(_xlpm.v="",_xlpm.a,_xlpm.v))),_xlpm.item,_xlfn.SCAN("",'07. BIA'!$E$6:$E$285,_xlfn.LAMBDA(_xlpm.a,_xlpm.v,IF(_xlpm.v="",_xlpm.a,_xlpm.v))),_xlpm.srcDep,LOWER(SUBSTITUTE(SUBSTITUTE(SUBSTITUTE('07. BIA'!$G$6:$G$285," ",""),"-",""),"/","")),_xlpm.rawKey,LOWER(SUBSTITUTE(SUBSTITUTE(SUBSTITUTE(E16," ",""),"-",""),"/","")),_xlpm.key,IF(_xlpm.rawKey="data","datainfo",_xlpm.rawKey),IF(D16="",IFERROR(_xlfn.TEXTJOIN(",",TRUE,_xlfn.UNIQUE(_xlfn._xlws.FILTER(_xlpm.item,(_xlpm.bu=C16)*(_xlpm.item<>"")))),""),IF(E16="","",IFERROR(_xlfn.TEXTJOIN(",",TRUE,_xlfn.UNIQUE(_xlfn._xlws.FILTER(_xlpm.item,(_xlpm.bu=C16)*(_xlpm.div=D16)*(_xlpm.srcDep=_xlpm.key)*('07. BIA'!$H$6:$H$285="Yes")))),"")))))} | H16: =IF($G16="","","Inability to deliver the associated products/services due to ["&$G16&"]") | L16: =IF($K16="","",CHOOSE($K16,"Rare","Infrequent","Occasional","Frequent","Almost Certain")) | N16: =IF($M16="","",CHOOSE($M16,"Negligible","Minor","Medium","Critical","Catastrophic")) | O16: =IF(OR($K16="",$M16=""),"",INDEX('20. ERM RA Guidance'!$E$79:$I$83,6-$K16,$M16)) | P16: =IF($O16="","",IF($O16>=20,"Critical",IF($O16>=12,"Significant",IF($O16>=7,"Moderate","Low")))) | Q16: =IF($P16="","",IF($P16="Critical",1,IF($P16="Significant",2,IF($P16="Moderate",3,4)))) | S16: {=IF($B16="","",IFERROR(_xlfn.TEXTJOIN(",",TRUE,_xlfn.UNIQUE(_xlfn._xlws.FILTER('11. Strategies & Solutions'!$C$5:$C$64,('11. Strategies & Solutions'!$B$5:$B$64=$B16)*('11. Strategies & Solutions'!$C$5:$C$64<>"")))),"Not Created"))} | T16: {=IF($B16="","",_xlfn.LET(_xlpm.ss,_xlfn._xlws.FILTER('11. Strategies & Solutions'!$C$5:$C$64,('11. Strategies & Solutions'!$B$5:$B$64=$B16)*('11. Strategies & Solutions'!$C$5:$C$64<>""),""),IFERROR(_xlfn.TEXTJOIN(",",TRUE,_xlfn.UNIQUE(_xlfn._xlws.FILTER('14. Recovery & Response'!$B$6:$B$105,ISNUMBER(_xlfn.XMATCH('14. Recovery & Response'!$C$6:$C$105,_xlpm.ss))*('14. Recovery & Response'!$B$6:$B$105<>"")))),"Not Created")))} | Z16: =IF($B16="","",IF(AND($C16<>"",$D16<>"",$E16<>"",$F16<>"",$G16<>"",$H16<>"",$J16<>"",$K16<>"",$M16<>"",$U16<>"",ISNUMBER($V16),ISNUMBER($W16),$X16<>"",$Y16<>""),"Complete","Incomplete"))
A17: 13 | B17: =IF($G17="","","RA-"&TEXT($A17,"000")) | F17: {=IF(C17="","",_xlfn.LET(_xlpm.bu,_xlfn.SCAN("",'07. BIA'!$C$6:$C$285,_xlfn.LAMBDA(_xlpm.a,_xlpm.v,IF(_xlpm.v="",_xlpm.a,_xlpm.v))),_xlpm.div,_xlfn.SCAN("",'07. BIA'!$D$6:$D$285,_xlfn.LAMBDA(_xlpm.a,_xlpm.v,IF(_xlpm.v="",_xlpm.a,_xlpm.v))),_xlpm.item,_xlfn.SCAN("",'07. BIA'!$E$6:$E$285,_xlfn.LAMBDA(_xlpm.a,_xlpm.v,IF(_xlpm.v="",_xlpm.a,_xlpm.v))),_xlpm.srcDep,LOWER(SUBSTITUTE(SUBSTITUTE(SUBSTITUTE('07. BIA'!$G$6:$G$285," ",""),"-",""),"/","")),_xlpm.rawKey,LOWER(SUBSTITUTE(SUBSTITUTE(SUBSTITUTE(E17," ",""),"-",""),"/","")),_xlpm.key,IF(_xlpm.rawKey="data","datainfo",_xlpm.rawKey),IF(D17="",IFERROR(_xlfn.TEXTJOIN(",",TRUE,_xlfn.UNIQUE(_xlfn._xlws.FILTER(_xlpm.item,(_xlpm.bu=C17)*(_xlpm.item<>"")))),""),IF(E17="","",IFERROR(_xlfn.TEXTJOIN(",",TRUE,_xlfn.UNIQUE(_xlfn._xlws.FILTER(_xlpm.item,(_xlpm.bu=C17)*(_xlpm.div=D17)*(_xlpm.srcDep=_xlpm.key)*('07. BIA'!$H$6:$H$285="Yes")))),"")))))} | H17: =IF($G17="","","Inability to deliver the associated products/services due to ["&$G17&"]") | L17: =IF($K17="","",CHOOSE($K17,"Rare","Infrequent","Occasional","Frequent","Almost Certain")) | N17: =IF($M17="","",CHOOSE($M17,"Negligible","Minor","Medium","Critical","Catastrophic")) | O17: =IF(OR($K17="",$M17=""),"",INDEX('20. ERM RA Guidance'!$E$79:$I$83,6-$K17,$M17)) | P17: =IF($O17="","",IF($O17>=20,"Critical",IF($O17>=12,"Significant",IF($O17>=7,"Moderate","Low")))) | Q17: =IF($P17="","",IF($P17="Critical",1,IF($P17="Significant",2,IF($P17="Moderate",3,4)))) | S17: {=IF($B17="","",IFERROR(_xlfn.TEXTJOIN(",",TRUE,_xlfn.UNIQUE(_xlfn._xlws.FILTER('11. Strategies & Solutions'!$C$5:$C$64,('11. Strategies & Solutions'!$B$5:$B$64=$B17)*('11. Strategies & Solutions'!$C$5:$C$64<>"")))),"Not Created"))} | T17: {=IF($B17="","",_xlfn.LET(_xlpm.ss,_xlfn._xlws.FILTER('11. Strategies & Solutions'!$C$5:$C$64,('11. Strategies & Solutions'!$B$5:$B$64=$B17)*('11. Strategies & Solutions'!$C$5:$C$64<>""),""),IFERROR(_xlfn.TEXTJOIN(",",TRUE,_xlfn.UNIQUE(_xlfn._xlws.FILTER('14. Recovery & Response'!$B$6:$B$105,ISNUMBER(_xlfn.XMATCH('14. Recovery & Response'!$C$6:$C$105,_xlpm.ss))*('14. Recovery & Response'!$B$6:$B$105<>"")))),"Not Created")))} | Z17: =IF($B17="","",IF(AND($C17<>"",$D17<>"",$E17<>"",$F17<>"",$G17<>"",$H17<>"",$J17<>"",$K17<>"",$M17<>"",$U17<>"",ISNUMBER($V17),ISNUMBER($W17),$X17<>"",$Y17<>""),"Complete","Incomplete"))
... A34: 30 | B34: =IF($G34="","","RA-"&TEXT($A34,"000")) | F34: {=IF(C34="","",_xlfn.LET(_xlpm.bu,_xlfn.SCAN("",'07. BIA'!$C$6:$C$285,_xlfn.LAMBDA(_xlpm.a,_xlpm.v,IF(_xlpm.v="",_xlpm.a,_xlpm.v))),_xlpm.div,_xlfn.SCAN("",'07. BIA'!$D$6:$D$285,_xlfn.LAMBDA(_xlpm.a,_xlpm.v,IF(_xlpm.v="",_xlpm.a,_xlpm.v))),_xlpm.item,_xlfn.SCAN("",'07. BIA'!$E$6:$E$285,_xlfn.LAMBDA(_xlpm.a,_xlpm.v,IF(_xlpm.v="",_xlpm.a,_xlpm.v))),_xlpm.srcDep,LOWER(SUBSTITUTE(SUBSTITUTE(SUBSTITUTE('07. BIA'!$G$6:$G$285," ",""),"-",""),"/","")),_xlpm.rawKey,LOWER(SUBSTITUTE(SUBSTITUTE(SUBSTITUTE(E34," ",""),"-",""),"/","")),_xlpm.key,IF(_xlpm.rawKey="data","datainfo",_xlpm.rawKey),IF(D34="",IFERROR(_xlfn.TEXTJOIN(",",TRUE,_xlfn.UNIQUE(_xlfn._xlws.FILTER(_xlpm.item,(_xlpm.bu=C34)*(_xlpm.item<>"")))),""),IF(E34="","",IFERROR(_xlfn.TEXTJOIN(",",TRUE,_xlfn.UNIQUE(_xlfn._xlws.FILTER(_xlpm.item,(_xlpm.bu=C34)*(_xlpm.div=D34)*(_xlpm.srcDep=_xlpm.key)*('07. BIA'!$H$6:$H$285="Yes")))),"")))))} | H34: =IF($G34="","","Inability to deliver the associated products/services due to ["&$G34&"]") | L34: =IF($K34="","",CHOOSE($K34,"Rare","Infrequent","Occasional","Frequent","Almost Certain")) | N34: =IF($M34="","",CHOOSE($M34,"Negligible","Minor","Medium","Critical","Catastrophic")) | O34: =IF(OR($K34="",$M34=""),"",INDEX('20. ERM RA Guidance'!$E$79:$I$83,6-$K34,$M34)) | P34: =IF($O34="","",IF($O34>=20,"Critical",IF($O34>=12,"Significant",IF($O34>=7,"Moderate","Low")))) | Q34: =IF($P34="","",IF($P34="Critical",1,IF($P34="Significant",2,IF($P34="Moderate",3,4)))) | S34: {=IF($B34="","",IFERROR(_xlfn.TEXTJOIN(",",TRUE,_xlfn.UNIQUE(_xlfn._xlws.FILTER('11. Strategies & Solutions'!$C$5:$C$64,('11. Strategies & Solutions'!$B$5:$B$64=$B34)*('11. Strategies & Solutions'!$C$5:$C$64<>"")))),"Not Created"))} | T34: {=IF($B34="","",_xlfn.LET(_xlpm.ss,_xlfn._xlws.FILTER('11. Strategies & Solutions'!$C$5:$C$64,('11. Strategies & Solutions'!$B$5:$B$64=$B34)*('11. Strategies & Solutions'!$C$5:$C$64<>""),""),IFERROR(_xlfn.TEXTJOIN(",",TRUE,_xlfn.UNIQUE(_xlfn._xlws.FILTER('14. Recovery & Response'!$B$6:$B$105,ISNUMBER(_xlfn.XMATCH('14. Recovery & Response'!$C$6:$C$105,_xlpm.ss))*('14. Recovery & Response'!$B$6:$B$105<>"")))),"Not Created")))} | Z34: =IF($B34="","",IF(AND($C34<>"",$D34<>"",$E34<>"",$F34<>"",$G34<>"",$H34<>"",$J34<>"",$K34<>"",$M34<>"",$U34<>"",ISNUMBER($V34),ISNUMBER($W34),$X34<>"",$Y34<>""),"Complete","Incomplete"))

Sheet 11. Strategies & Solutions
A1: Step 4 - Continuity Strategies & Solutions + MVO Operating Mode
A2: Requirement flags turn RED if Yes with no matching row in 5b | ISO 22301: 8.3 BC strategies and solutions
A4: No. | B4: Risk ID | C4: S&S ID | D4: Dependency | E4: Risk Assumption | F4: Disruption Scenario | G4: Products / Services | H4: Strategy | I4: Strategy Details / Do nothing Justification | J4: People | K4: ICT | L4: 3rd Party | M4: Data Backup | N4: Equipment / Building / Utilities | O4: Fund | P4: Action Owner | Q4: Start Date | R4: Due Date | S4: Completion Date | T4: Status | U4: 1:1 Check | V4: R&R IDs (auto) | W4: Remarks
A5: 1 | C5: =IF($B5="","","SS-"&TEXT($A5,"000")) | D5: {=IF($B5="","",IFERROR(_xlfn.XLOOKUP($B5,INDEX(RiskAssessment[],0,2),INDEX(RiskAssessment[],0,5),""),""))} | E5: {=IF($B5="","",IFERROR(_xlfn.XLOOKUP($B5,INDEX(RiskAssessment[],0,2),INDEX(RiskAssessment[],0,7),""),""))} | F5: {=IF($B5="","",IFERROR(_xlfn.XLOOKUP($B5,INDEX(RiskAssessment[],0,2),INDEX(RiskAssessment[],0,8),""),""))} | G5: =IF($B5="","",_xlfn.XLOOKUP($B5,'10. Risk Assessment'!$B$5:$B$34,'10. Risk Assessment'!$F$5:$F$34,"")) | T5: {=IF($B5="","",_xlfn.LET(_xlpm.flag,$J5:$O5,_xlpm.total,COUNTIFS('12. Requirements Register'!$C$5:$C$304,$C5,'12. Requirements Register'!$E$5:$E$304,$J$4:$O$4),_xlpm.readyCount,COUNTIFS('12. Requirements Register'!$C$5:$C$304,$C5,'12. Requirements Register'!$E$5:$E$304,$J$4:$O$4,'12. Requirements Register'!$M$5:$M$304,"Ready"),_xlpm.reqOK,SUM(--(_xlpm.flag="Yes")*--(_xlpm.total>0)*--(_xlpm.readyCount=_xlpm.total))=COUNTIF(_xlpm.flag,"Yes"),_xlpm.core,AND($H5<>"",$I5<>"",$P5<>"",$Q5<>"",$R5<>"",$V5<>"",$V5<>"Not Created"),IF($S5<>"",IF(AND($S5<=TODAY(),_xlpm.core,_xlpm.reqOK),"Completed","Incomplete"),IF($Q5="","Planned",IF(TODAY()<$Q5,"Planned",IF($R5="","In Progress",IF(TODAY()<=$R5,"In Progress","Overdue")))))))} | U5: =IF($B5="","",IF(COUNTIFS($B$5:$B$64,$B5,$G$5:$G$64,$G5,$H$5:$H$64,$H5)>1,"DUPLICATE","OK")) | V5: {=IF($C5="","",IFERROR(_xlfn.LET(_xlpm.x,_xlfn.UNIQUE(_xlfn._xlws.FILTER('14. Recovery & Response'!$B$6:$B$105,('14. Recovery & Response'!$C$6:$C$105=$C5)*('14. Recovery & Response'!$B$6:$B$105<>""))),_xlfn.TEXTJOIN(",",TRUE,_xlpm.x)),"Not Created"))}
A6: 2 | C6: =IF($B6="","","SS-"&TEXT($A6,"000")) | D6: {=IF($B6="","",IFERROR(_xlfn.XLOOKUP($B6,INDEX(RiskAssessment[],0,2),INDEX(RiskAssessment[],0,5),""),""))} | E6: {=IF($B6="","",IFERROR(_xlfn.XLOOKUP($B6,INDEX(RiskAssessment[],0,2),INDEX(RiskAssessment[],0,7),""),""))} | F6: {=IF($B6="","",IFERROR(_xlfn.XLOOKUP($B6,INDEX(RiskAssessment[],0,2),INDEX(RiskAssessment[],0,8),""),""))} | G6: =IF($B6="","",_xlfn.XLOOKUP($B6,'10. Risk Assessment'!$B$5:$B$34,'10. Risk Assessment'!$F$5:$F$34,"")) | T6: {=IF($B6="","",_xlfn.LET(_xlpm.flag,$J6:$O6,_xlpm.total,COUNTIFS('12. Requirements Register'!$C$5:$C$304,$C6,'12. Requirements Register'!$E$5:$E$304,$J$4:$O$4),_xlpm.readyCount,COUNTIFS('12. Requirements Register'!$C$5:$C$304,$C6,'12. Requirements Register'!$E$5:$E$304,$J$4:$O$4,'12. Requirements Register'!$M$5:$M$304,"Ready"),_xlpm.reqOK,SUM(--(_xlpm.flag="Yes")*--(_xlpm.total>0)*--(_xlpm.readyCount=_xlpm.total))=COUNTIF(_xlpm.flag,"Yes"),_xlpm.core,AND($H6<>"",$I6<>"",$P6<>"",$Q6<>"",$R6<>"",$V6<>"",$V6<>"Not Created"),IF($S6<>"",IF(AND($S6<=TODAY(),_xlpm.core,_xlpm.reqOK),"Completed","Incomplete"),IF($Q6="","Planned",IF(TODAY()<$Q6,"Planned",IF($R6="","In Progress",IF(TODAY()<=$R6,"In Progress","Overdue")))))))} | U6: =IF($B6="","",IF(COUNTIFS($B$5:$B$64,$B6,$G$5:$G$64,$G6,$H$5:$H$64,$H6)>1,"DUPLICATE","OK")) | V6: {=IF($C6="","",IFERROR(_xlfn.LET(_xlpm.x,_xlfn.UNIQUE(_xlfn._xlws.FILTER('14. Recovery & Response'!$B$6:$B$105,('14. Recovery & Response'!$C$6:$C$105=$C6)*('14. Recovery & Response'!$B$6:$B$105<>""))),_xlfn.TEXTJOIN(",",TRUE,_xlpm.x)),"Not Created"))}
A7: 3 | C7: =IF($B7="","","SS-"&TEXT($A7,"000")) | D7: {=IF($B7="","",IFERROR(_xlfn.XLOOKUP($B7,INDEX(RiskAssessment[],0,2),INDEX(RiskAssessment[],0,5),""),""))} | E7: {=IF($B7="","",IFERROR(_xlfn.XLOOKUP($B7,INDEX(RiskAssessment[],0,2),INDEX(RiskAssessment[],0,7),""),""))} | F7: {=IF($B7="","",IFERROR(_xlfn.XLOOKUP($B7,INDEX(RiskAssessment[],0,2),INDEX(RiskAssessment[],0,8),""),""))} | G7: =IF($B7="","",_xlfn.XLOOKUP($B7,'10. Risk Assessment'!$B$5:$B$34,'10. Risk Assessment'!$F$5:$F$34,"")) | T7: {=IF($B7="","",_xlfn.LET(_xlpm.flag,$J7:$O7,_xlpm.total,COUNTIFS('12. Requirements Register'!$C$5:$C$304,$C7,'12. Requirements Register'!$E$5:$E$304,$J$4:$O$4),_xlpm.readyCount,COUNTIFS('12. Requirements Register'!$C$5:$C$304,$C7,'12. Requirements Register'!$E$5:$E$304,$J$4:$O$4,'12. Requirements Register'!$M$5:$M$304,"Ready"),_xlpm.reqOK,SUM(--(_xlpm.flag="Yes")*--(_xlpm.total>0)*--(_xlpm.readyCount=_xlpm.total))=COUNTIF(_xlpm.flag,"Yes"),_xlpm.core,AND($H7<>"",$I7<>"",$P7<>"",$Q7<>"",$R7<>"",$V7<>"",$V7<>"Not Created"),IF($S7<>"",IF(AND($S7<=TODAY(),_xlpm.core,_xlpm.reqOK),"Completed","Incomplete"),IF($Q7="","Planned",IF(TODAY()<$Q7,"Planned",IF($R7="","In Progress",IF(TODAY()<=$R7,"In Progress","Overdue")))))))} | U7: =IF($B7="","",IF(COUNTIFS($B$5:$B$64,$B7,$G$5:$G$64,$G7,$H$5:$H$64,$H7)>1,"DUPLICATE","OK")) | V7: {=IF($C7="","",IFERROR(_xlfn.LET(_xlpm.x,_xlfn.UNIQUE(_xlfn._xlws.FILTER('14. Recovery & Response'!$B$6:$B$105,('14. Recovery & Response'!$C$6:$C$105=$C7)*('14. Recovery & Response'!$B$6:$B$105<>""))),_xlfn.TEXTJOIN(",",TRUE,_xlpm.x)),"Not Created"))}
A8: 4 | C8: =IF($B8="","","SS-"&TEXT($A8,"000")) | D8: {=IF($B8="","",IFERROR(_xlfn.XLOOKUP($B8,INDEX(RiskAssessment[],0,2),INDEX(RiskAssessment[],0,5),""),""))} | E8: {=IF($B8="","",IFERROR(_xlfn.XLOOKUP($B8,INDEX(RiskAssessment[],0,2),INDEX(RiskAssessment[],0,7),""),""))} | F8: {=IF($B8="","",IFERROR(_xlfn.XLOOKUP($B8,INDEX(RiskAssessment[],0,2),INDEX(RiskAssessment[],0,8),""),""))} | G8: =IF($B8="","",_xlfn.XLOOKUP($B8,'10. Risk Assessment'!$B$5:$B$34,'10. Risk Assessment'!$F$5:$F$34,"")) | T8: {=IF($B8="","",_xlfn.LET(_xlpm.flag,$J8:$O8,_xlpm.total,COUNTIFS('12. Requirements Register'!$C$5:$C$304,$C8,'12. Requirements Register'!$E$5:$E$304,$J$4:$O$4),_xlpm.readyCount,COUNTIFS('12. Requirements Register'!$C$5:$C$304,$C8,'12. Requirements Register'!$E$5:$E$304,$J$4:$O$4,'12. Requirements Register'!$M$5:$M$304,"Ready"),_xlpm.reqOK,SUM(--(_xlpm.flag="Yes")*--(_xlpm.total>0)*--(_xlpm.readyCount=_xlpm.total))=COUNTIF(_xlpm.flag,"Yes"),_xlpm.core,AND($H8<>"",$I8<>"",$P8<>"",$Q8<>"",$R8<>"",$V8<>"",$V8<>"Not Created"),IF($S8<>"",IF(AND($S8<=TODAY(),_xlpm.core,_xlpm.reqOK),"Completed","Incomplete"),IF($Q8="","Planned",IF(TODAY()<$Q8,"Planned",IF($R8="","In Progress",IF(TODAY()<=$R8,"In Progress","Overdue")))))))} | U8: =IF($B8="","",IF(COUNTIFS($B$5:$B$64,$B8,$G$5:$G$64,$G8,$H$5:$H$64,$H8)>1,"DUPLICATE","OK")) | V8: {=IF($C8="","",IFERROR(_xlfn.LET(_xlpm.x,_xlfn.UNIQUE(_xlfn._xlws.FILTER('14. Recovery & Response'!$B$6:$B$105,('14. Recovery & Response'!$C$6:$C$105=$C8)*('14. Recovery & Response'!$B$6:$B$105<>""))),_xlfn.TEXTJOIN(",",TRUE,_xlpm.x)),"Not Created"))}
A9: 5 | C9: =IF($B9="","","SS-"&TEXT($A9,"000")) | D9: {=IF($B9="","",IFERROR(_xlfn.XLOOKUP($B9,INDEX(RiskAssessment[],0,2),INDEX(RiskAssessment[],0,5),""),""))} | E9: {=IF($B9="","",IFERROR(_xlfn.XLOOKUP($B9,INDEX(RiskAssessment[],0,2),INDEX(RiskAssessment[],0,7),""),""))} | F9: {=IF($B9="","",IFERROR(_xlfn.XLOOKUP($B9,INDEX(RiskAssessment[],0,2),INDEX(RiskAssessment[],0,8),""),""))} | G9: =IF($B9="","",_xlfn.XLOOKUP($B9,'10. Risk Assessment'!$B$5:$B$34,'10. Risk Assessment'!$F$5:$F$34,"")) | T9: {=IF($B9="","",_xlfn.LET(_xlpm.flag,$J9:$O9,_xlpm.total,COUNTIFS('12. Requirements Register'!$C$5:$C$304,$C9,'12. Requirements Register'!$E$5:$E$304,$J$4:$O$4),_xlpm.readyCount,COUNTIFS('12. Requirements Register'!$C$5:$C$304,$C9,'12. Requirements Register'!$E$5:$E$304,$J$4:$O$4,'12. Requirements Register'!$M$5:$M$304,"Ready"),_xlpm.reqOK,SUM(--(_xlpm.flag="Yes")*--(_xlpm.total>0)*--(_xlpm.readyCount=_xlpm.total))=COUNTIF(_xlpm.flag,"Yes"),_xlpm.core,AND($H9<>"",$I9<>"",$P9<>"",$Q9<>"",$R9<>"",$V9<>"",$V9<>"Not Created"),IF($S9<>"",IF(AND($S9<=TODAY(),_xlpm.core,_xlpm.reqOK),"Completed","Incomplete"),IF($Q9="","Planned",IF(TODAY()<$Q9,"Planned",IF($R9="","In Progress",IF(TODAY()<=$R9,"In Progress","Overdue")))))))} | U9: =IF($B9="","",IF(COUNTIFS($B$5:$B$64,$B9,$G$5:$G$64,$G9,$H$5:$H$64,$H9)>1,"DUPLICATE","OK")) | V9: {=IF($C9="","",IFERROR(_xlfn.LET(_xlpm.x,_xlfn.UNIQUE(_xlfn._xlws.FILTER('14. Recovery & Response'!$B$6:$B$105,('14. Recovery & Response'!$C$6:$C$105=$C9)*('14. Recovery & Response'!$B$6:$B$105<>""))),_xlfn.TEXTJOIN(",",TRUE,_xlpm.x)),"Not Created"))}
A10: 6 | C10: =IF($B10="","","SS-"&TEXT($A10,"000")) | D10: {=IF($B10="","",IFERROR(_xlfn.XLOOKUP($B10,INDEX(RiskAssessment[],0,2),INDEX(RiskAssessment[],0,5),""),""))} | E10: {=IF($B10="","",IFERROR(_xlfn.XLOOKUP($B10,INDEX(RiskAssessment[],0,2),INDEX(RiskAssessment[],0,7),""),""))} | F10: {=IF($B10="","",IFERROR(_xlfn.XLOOKUP($B10,INDEX(RiskAssessment[],0,2),INDEX(RiskAssessment[],0,8),""),""))} | G10: =IF($B10="","",_xlfn.XLOOKUP($B10,'10. Risk Assessment'!$B$5:$B$34,'10. Risk Assessment'!$F$5:$F$34,"")) | T10: {=IF($B10="","",_xlfn.LET(_xlpm.flag,$J10:$O10,_xlpm.total,COUNTIFS('12. Requirements Register'!$C$5:$C$304,$C10,'12. Requirements Register'!$E$5:$E$304,$J$4:$O$4),_xlpm.readyCount,COUNTIFS('12. Requirements Register'!$C$5:$C$304,$C10,'12. Requirements Register'!$E$5:$E$304,$J$4:$O$4,'12. Requirements Register'!$M$5:$M$304,"Ready"),_xlpm.reqOK,SUM(--(_xlpm.flag="Yes")*--(_xlpm.total>0)*--(_xlpm.readyCount=_xlpm.total))=COUNTIF(_xlpm.flag,"Yes"),_xlpm.core,AND($H10<>"",$I10<>"",$P10<>"",$Q10<>"",$R10<>"",$V10<>"",$V10<>"Not Created"),IF($S10<>"",IF(AND($S10<=TODAY(),_xlpm.core,_xlpm.reqOK),"Completed","Incomplete"),IF($Q10="","Planned",IF(TODAY()<$Q10,"Planned",IF($R10="","In Progress",IF(TODAY()<=$R10,"In Progress","Overdue")))))))} | U10: =IF($B10="","",IF(COUNTIFS($B$5:$B$64,$B10,$G$5:$G$64,$G10,$H$5:$H$64,$H10)>1,"DUPLICATE","OK")) | V10: {=IF($C10="","",IFERROR(_xlfn.LET(_xlpm.x,_xlfn.UNIQUE(_xlfn._xlws.FILTER('14. Recovery & Response'!$B$6:$B$105,('14. Recovery & Response'!$C$6:$C$105=$C10)*('14. Recovery & Response'!$B$6:$B$105<>""))),_xlfn.TEXTJOIN(",",TRUE,_xlpm.x)),"Not Created"))}
A11: 7 | C11: =IF($B11="","","SS-"&TEXT($A11,"000")) | D11: {=IF($B11="","",IFERROR(_xlfn.XLOOKUP($B11,INDEX(RiskAssessment[],0,2),INDEX(RiskAssessment[],0,5),""),""))} | E11: {=IF($B11="","",IFERROR(_xlfn.XLOOKUP($B11,INDEX(RiskAssessment[],0,2),INDEX(RiskAssessment[],0,7),""),""))} | F11: {=IF($B11="","",IFERROR(_xlfn.XLOOKUP($B11,INDEX(RiskAssessment[],0,2),INDEX(RiskAssessment[],0,8),""),""))} | G11: =IF($B11="","",_xlfn.XLOOKUP($B11,'10. Risk Assessment'!$B$5:$B$34,'10. Risk Assessment'!$F$5:$F$34,"")) | T11: {=IF($B11="","",_xlfn.LET(_xlpm.flag,$J11:$O11,_xlpm.total,COUNTIFS('12. Requirements Register'!$C$5:$C$304,$C11,'12. Requirements Register'!$E$5:$E$304,$J$4:$O$4),_xlpm.readyCount,COUNTIFS('12. Requirements Register'!$C$5:$C$304,$C11,'12. Requirements Register'!$E$5:$E$304,$J$4:$O$4,'12. Requirements Register'!$M$5:$M$304,"Ready"),_xlpm.reqOK,SUM(--(_xlpm.flag="Yes")*--(_xlpm.total>0)*--(_xlpm.readyCount=_xlpm.total))=COUNTIF(_xlpm.flag,"Yes"),_xlpm.core,AND($H11<>"",$I11<>"",$P11<>"",$Q11<>"",$R11<>"",$V11<>"",$V11<>"Not Created"),IF($S11<>"",IF(AND($S11<=TODAY(),_xlpm.core,_xlpm.reqOK),"Completed","Incomplete"),IF($Q11="","Planned",IF(TODAY()<$Q11,"Planned",IF($R11="","In Progress",IF(TODAY()<=$R11,"In Progress","Overdue")))))))} | U11: =IF($B11="","",IF(COUNTIFS($B$5:$B$64,$B11,$G$5:$G$64,$G11,$H$5:$H$64,$H11)>1,"DUPLICATE","OK")) | V11: {=IF($C11="","",IFERROR(_xlfn.LET(_xlpm.x,_xlfn.UNIQUE(_xlfn._xlws.FILTER('14. Recovery & Response'!$B$6:$B$105,('14. Recovery & Response'!$C$6:$C$105=$C11)*('14. Recovery & Response'!$B$6:$B$105<>""))),_xlfn.TEXTJOIN(",",TRUE,_xlpm.x)),"Not Created"))}
A12: 8 | C12: =IF($B12="","","SS-"&TEXT($A12,"000")) | D12: {=IF($B12="","",IFERROR(_xlfn.XLOOKUP($B12,INDEX(RiskAssessment[],0,2),INDEX(RiskAssessment[],0,5),""),""))} | E12: {=IF($B12="","",IFERROR(_xlfn.XLOOKUP($B12,INDEX(RiskAssessment[],0,2),INDEX(RiskAssessment[],0,7),""),""))} | F12: {=IF($B12="","",IFERROR(_xlfn.XLOOKUP($B12,INDEX(RiskAssessment[],0,2),INDEX(RiskAssessment[],0,8),""),""))} | G12: =IF($B12="","",_xlfn.XLOOKUP($B12,'10. Risk Assessment'!$B$5:$B$34,'10. Risk Assessment'!$F$5:$F$34,"")) | T12: {=IF($B12="","",_xlfn.LET(_xlpm.flag,$J12:$O12,_xlpm.total,COUNTIFS('12. Requirements Register'!$C$5:$C$304,$C12,'12. Requirements Register'!$E$5:$E$304,$J$4:$O$4),_xlpm.readyCount,COUNTIFS('12. Requirements Register'!$C$5:$C$304,$C12,'12. Requirements Register'!$E$5:$E$304,$J$4:$O$4,'12. Requirements Register'!$M$5:$M$304,"Ready"),_xlpm.reqOK,SUM(--(_xlpm.flag="Yes")*--(_xlpm.total>0)*--(_xlpm.readyCount=_xlpm.total))=COUNTIF(_xlpm.flag,"Yes"),_xlpm.core,AND($H12<>"",$I12<>"",$P12<>"",$Q12<>"",$R12<>"",$V12<>"",$V12<>"Not Created"),IF($S12<>"",IF(AND($S12<=TODAY(),_xlpm.core,_xlpm.reqOK),"Completed","Incomplete"),IF($Q12="","Planned",IF(TODAY()<$Q12,"Planned",IF($R12="","In Progress",IF(TODAY()<=$R12,"In Progress","Overdue")))))))} | U12: =IF($B12="","",IF(COUNTIFS($B$5:$B$64,$B12,$G$5:$G$64,$G12,$H$5:$H$64,$H12)>1,"DUPLICATE","OK")) | V12: {=IF($C12="","",IFERROR(_xlfn.LET(_xlpm.x,_xlfn.UNIQUE(_xlfn._xlws.FILTER('14. Recovery & Response'!$B$6:$B$105,('14. Recovery & Response'!$C$6:$C$105=$C12)*('14. Recovery & Response'!$B$6:$B$105<>""))),_xlfn.TEXTJOIN(",",TRUE,_xlpm.x)),"Not Created"))}
A13: 9 | C13: =IF($B13="","","SS-"&TEXT($A13,"000")) | D13: {=IF($B13="","",IFERROR(_xlfn.XLOOKUP($B13,INDEX(RiskAssessment[],0,2),INDEX(RiskAssessment[],0,5),""),""))} | E13: {=IF($B13="","",IFERROR(_xlfn.XLOOKUP($B13,INDEX(RiskAssessment[],0,2),INDEX(RiskAssessment[],0,7),""),""))} | F13: {=IF($B13="","",IFERROR(_xlfn.XLOOKUP($B13,INDEX(RiskAssessment[],0,2),INDEX(RiskAssessment[],0,8),""),""))} | G13: =IF($B13="","",_xlfn.XLOOKUP($B13,'10. Risk Assessment'!$B$5:$B$34,'10. Risk Assessment'!$F$5:$F$34,"")) | T13: {=IF($B13="","",_xlfn.LET(_xlpm.flag,$J13:$O13,_xlpm.total,COUNTIFS('12. Requirements Register'!$C$5:$C$304,$C13,'12. Requirements Register'!$E$5:$E$304,$J$4:$O$4),_xlpm.readyCount,COUNTIFS('12. Requirements Register'!$C$5:$C$304,$C13,'12. Requirements Register'!$E$5:$E$304,$J$4:$O$4,'12. Requirements Register'!$M$5:$M$304,"Ready"),_xlpm.reqOK,SUM(--(_xlpm.flag="Yes")*--(_xlpm.total>0)*--(_xlpm.readyCount=_xlpm.total))=COUNTIF(_xlpm.flag,"Yes"),_xlpm.core,AND($H13<>"",$I13<>"",$P13<>"",$Q13<>"",$R13<>"",$V13<>"",$V13<>"Not Created"),IF($S13<>"",IF(AND($S13<=TODAY(),_xlpm.core,_xlpm.reqOK),"Completed","Incomplete"),IF($Q13="","Planned",IF(TODAY()<$Q13,"Planned",IF($R13="","In Progress",IF(TODAY()<=$R13,"In Progress","Overdue")))))))} | U13: =IF($B13="","",IF(COUNTIFS($B$5:$B$64,$B13,$G$5:$G$64,$G13,$H$5:$H$64,$H13)>1,"DUPLICATE","OK")) | V13: {=IF($C13="","",IFERROR(_xlfn.LET(_xlpm.x,_xlfn.UNIQUE(_xlfn._xlws.FILTER('14. Recovery & Response'!$B$6:$B$105,('14. Recovery & Response'!$C$6:$C$105=$C13)*('14. Recovery & Response'!$B$6:$B$105<>""))),_xlfn.TEXTJOIN(",",TRUE,_xlpm.x)),"Not Created"))}
A14: 10 | C14: =IF($B14="","","SS-"&TEXT($A14,"000")) | D14: {=IF($B14="","",IFERROR(_xlfn.XLOOKUP($B14,INDEX(RiskAssessment[],0,2),INDEX(RiskAssessment[],0,5),""),""))} | E14: {=IF($B14="","",IFERROR(_xlfn.XLOOKUP($B14,INDEX(RiskAssessment[],0,2),INDEX(RiskAssessment[],0,7),""),""))} | F14: {=IF($B14="","",IFERROR(_xlfn.XLOOKUP($B14,INDEX(RiskAssessment[],0,2),INDEX(RiskAssessment[],0,8),""),""))} | G14: =IF($B14="","",_xlfn.XLOOKUP($B14,'10. Risk Assessment'!$B$5:$B$34,'10. Risk Assessment'!$F$5:$F$34,"")) | T14: {=IF($B14="","",_xlfn.LET(_xlpm.flag,$J14:$O14,_xlpm.total,COUNTIFS('12. Requirements Register'!$C$5:$C$304,$C14,'12. Requirements Register'!$E$5:$E$304,$J$4:$O$4),_xlpm.readyCount,COUNTIFS('12. Requirements Register'!$C$5:$C$304,$C14,'12. Requirements Register'!$E$5:$E$304,$J$4:$O$4,'12. Requirements Register'!$M$5:$M$304,"Ready"),_xlpm.reqOK,SUM(--(_xlpm.flag="Yes")*--(_xlpm.total>0)*--(_xlpm.readyCount=_xlpm.total))=COUNTIF(_xlpm.flag,"Yes"),_xlpm.core,AND($H14<>"",$I14<>"",$P14<>"",$Q14<>"",$R14<>"",$V14<>"",$V14<>"Not Created"),IF($S14<>"",IF(AND($S14<=TODAY(),_xlpm.core,_xlpm.reqOK),"Completed","Incomplete"),IF($Q14="","Planned",IF(TODAY()<$Q14,"Planned",IF($R14="","In Progress",IF(TODAY()<=$R14,"In Progress","Overdue")))))))} | U14: =IF($B14="","",IF(COUNTIFS($B$5:$B$64,$B14,$G$5:$G$64,$G14,$H$5:$H$64,$H14)>1,"DUPLICATE","OK")) | V14: {=IF($C14="","",IFERROR(_xlfn.LET(_xlpm.x,_xlfn.UNIQUE(_xlfn._xlws.FILTER('14. Recovery & Response'!$B$6:$B$105,('14. Recovery & Response'!$C$6:$C$105=$C14)*('14. Recovery & Response'!$B$6:$B$105<>""))),_xlfn.TEXTJOIN(",",TRUE,_xlpm.x)),"Not Created"))}
A15: 11 | C15: =IF($B15="","","SS-"&TEXT($A15,"000")) | D15: {=IF($B15="","",IFERROR(_xlfn.XLOOKUP($B15,INDEX(RiskAssessment[],0,2),INDEX(RiskAssessment[],0,5),""),""))} | E15: {=IF($B15="","",IFERROR(_xlfn.XLOOKUP($B15,INDEX(RiskAssessment[],0,2),INDEX(RiskAssessment[],0,7),""),""))} | F15: {=IF($B15="","",IFERROR(_xlfn.XLOOKUP($B15,INDEX(RiskAssessment[],0,2),INDEX(RiskAssessment[],0,8),""),""))} | G15: =IF($B15="","",_xlfn.XLOOKUP($B15,'10. Risk Assessment'!$B$5:$B$34,'10. Risk Assessment'!$F$5:$F$34,"")) | T15: {=IF($B15="","",_xlfn.LET(_xlpm.flag,$J15:$O15,_xlpm.total,COUNTIFS('12. Requirements Register'!$C$5:$C$304,$C15,'12. Requirements Register'!$E$5:$E$304,$J$4:$O$4),_xlpm.readyCount,COUNTIFS('12. Requirements Register'!$C$5:$C$304,$C15,'12. Requirements Register'!$E$5:$E$304,$J$4:$O$4,'12. Requirements Register'!$M$5:$M$304,"Ready"),_xlpm.reqOK,SUM(--(_xlpm.flag="Yes")*--(_xlpm.total>0)*--(_xlpm.readyCount=_xlpm.total))=COUNTIF(_xlpm.flag,"Yes"),_xlpm.core,AND($H15<>"",$I15<>"",$P15<>"",$Q15<>"",$R15<>"",$V15<>"",$V15<>"Not Created"),IF($S15<>"",IF(AND($S15<=TODAY(),_xlpm.core,_xlpm.reqOK),"Completed","Incomplete"),IF($Q15="","Planned",IF(TODAY()<$Q15,"Planned",IF($R15="","In Progress",IF(TODAY()<=$R15,"In Progress","Overdue")))))))} | U15: =IF($B15="","",IF(COUNTIFS($B$5:$B$64,$B15,$G$5:$G$64,$G15,$H$5:$H$64,$H15)>1,"DUPLICATE","OK")) | V15: {=IF($C15="","",IFERROR(_xlfn.LET(_xlpm.x,_xlfn.UNIQUE(_xlfn._xlws.FILTER('14. Recovery & Response'!$B$6:$B$105,('14. Recovery & Response'!$C$6:$C$105=$C15)*('14. Recovery & Response'!$B$6:$B$105<>""))),_xlfn.TEXTJOIN(",",TRUE,_xlpm.x)),"Not Created"))}
A16: 12 | C16: =IF($B16="","","SS-"&TEXT($A16,"000")) | D16: {=IF($B16="","",IFERROR(_xlfn.XLOOKUP($B16,INDEX(RiskAssessment[],0,2),INDEX(RiskAssessment[],0,5),""),""))} | E16: {=IF($B16="","",IFERROR(_xlfn.XLOOKUP($B16,INDEX(RiskAssessment[],0,2),INDEX(RiskAssessment[],0,7),""),""))} | F16: {=IF($B16="","",IFERROR(_xlfn.XLOOKUP($B16,INDEX(RiskAssessment[],0,2),INDEX(RiskAssessment[],0,8),""),""))} | G16: =IF($B16="","",_xlfn.XLOOKUP($B16,'10. Risk Assessment'!$B$5:$B$34,'10. Risk Assessment'!$F$5:$F$34,"")) | T16: {=IF($B16="","",_xlfn.LET(_xlpm.flag,$J16:$O16,_xlpm.total,COUNTIFS('12. Requirements Register'!$C$5:$C$304,$C16,'12. Requirements Register'!$E$5:$E$304,$J$4:$O$4),_xlpm.readyCount,COUNTIFS('12. Requirements Register'!$C$5:$C$304,$C16,'12. Requirements Register'!$E$5:$E$304,$J$4:$O$4,'12. Requirements Register'!$M$5:$M$304,"Ready"),_xlpm.reqOK,SUM(--(_xlpm.flag="Yes")*--(_xlpm.total>0)*--(_xlpm.readyCount=_xlpm.total))=COUNTIF(_xlpm.flag,"Yes"),_xlpm.core,AND($H16<>"",$I16<>"",$P16<>"",$Q16<>"",$R16<>"",$V16<>"",$V16<>"Not Created"),IF($S16<>"",IF(AND($S16<=TODAY(),_xlpm.core,_xlpm.reqOK),"Completed","Incomplete"),IF($Q16="","Planned",IF(TODAY()<$Q16,"Planned",IF($R16="","In Progress",IF(TODAY()<=$R16,"In Progress","Overdue")))))))} | U16: =IF($B16="","",IF(COUNTIFS($B$5:$B$64,$B16,$G$5:$G$64,$G16,$H$5:$H$64,$H16)>1,"DUPLICATE","OK")) | V16: {=IF($C16="","",IFERROR(_xlfn.LET(_xlpm.x,_xlfn.UNIQUE(_xlfn._xlws.FILTER('14. Recovery & Response'!$B$6:$B$105,('14. Recovery & Response'!$C$6:$C$105=$C16)*('14. Recovery & Response'!$B$6:$B$105<>""))),_xlfn.TEXTJOIN(",",TRUE,_xlpm.x)),"Not Created"))}
... A33: 29 | C33: =IF($B33="","","SS-"&TEXT($A33,"000")) | D33: {=IF($B33="","",IFERROR(_xlfn.XLOOKUP($B33,INDEX(RiskAssessment[],0,2),INDEX(RiskAssessment[],0,5),""),""))} | E33: {=IF($B33="","",IFERROR(_xlfn.XLOOKUP($B33,INDEX(RiskAssessment[],0,2),INDEX(RiskAssessment[],0,7),""),""))} | F33: {=IF($B33="","",IFERROR(_xlfn.XLOOKUP($B33,INDEX(RiskAssessment[],0,2),INDEX(RiskAssessment[],0,8),""),""))} | G33: =IF($B33="","",_xlfn.XLOOKUP($B33,'10. Risk Assessment'!$B$5:$B$34,'10. Risk Assessment'!$F$5:$F$34,"")) | T33: {=IF($B33="","",_xlfn.LET(_xlpm.flag,$J33:$O33,_xlpm.total,COUNTIFS('12. Requirements Register'!$C$5:$C$304,$C33,'12. Requirements Register'!$E$5:$E$304,$J$4:$O$4),_xlpm.readyCount,COUNTIFS('12. Requirements Register'!$C$5:$C$304,$C33,'12. Requirements Register'!$E$5:$E$304,$J$4:$O$4,'12. Requirements Register'!$M$5:$M$304,"Ready"),_xlpm.reqOK,SUM(--(_xlpm.flag="Yes")*--(_xlpm.total>0)*--(_xlpm.readyCount=_xlpm.total))=COUNTIF(_xlpm.flag,"Yes"),_xlpm.core,AND($H33<>"",$I33<>"",$P33<>"",$Q33<>"",$R33<>"",$V33<>"",$V33<>"Not Created"),IF($S33<>"",IF(AND($S33<=TODAY(),_xlpm.core,_xlpm.reqOK),"Completed","Incomplete"),IF($Q33="","Planned",IF(TODAY()<$Q33,"Planned",IF($R33="","In Progress",IF(TODAY()<=$R33,"In Progress","Overdue")))))))} | U33: =IF($B33="","",IF(COUNTIFS($B$5:$B$64,$B33,$G$5:$G$64,$G33,$H$5:$H$64,$H33)>1,"DUPLICATE","OK")) | V33: {=IF($C33="","",IFERROR(_xlfn.LET(_xlpm.x,_xlfn.UNIQUE(_xlfn._xlws.FILTER('14. Recovery & Response'!$B$6:$B$105,('14. Recovery & Response'!$C$6:$C$105=$C33)*('14. Recovery & Response'!$B$6:$B$105<>""))),_xlfn.TEXTJOIN(",",TRUE,_xlpm.x)),"Not Created"))}
A34: 30 | B34: RA-001 | C34: =IF($B34="","","SS-"&TEXT($A34,"000")) -> SS-030 | D34: {=IF($B34="","",IFERROR(_xlfn.XLOOKUP($B34,INDEX(RiskAssessment[],0,2),INDEX(RiskAssessment[],0,5),""),""))} -> People | E34: {=IF($B34="","",IFERROR(_xlfn.XLOOKUP($B34,INDEX(RiskAssessment[],0,2),INDEX(RiskAssessment[],0,7),""),""))} -> Workforce evacuation | F34: {=IF($B34="","",IFERROR(_xlfn.XLOOKUP($B34,INDEX(RiskAssessment[],0,2),INDEX(RiskAssessment[],0,8),""),""))} -> Inability to deliver the associated products/services due to [Workforce evacuation] | G34: =IF($B34="","",_xlfn.XLOOKUP($B34,'10. Risk Assessment'!$B$5:$B$34,'10. Risk Assessment'!$F$5:$F$34,"")) -> cb | H34: Alternative Site / Relocation | T34: {=IF($B34="","",_xlfn.LET(_xlpm.flag,$J34:$O34,_xlpm.total,COUNTIFS('12. Requirements Register'!$C$5:$C$304,$C34,'12. Requirements Register'!$E$5:$E$304,$J$4:$O$4),_xlpm.readyCount,COUNTIFS('12. Requirements Register'!$C$5:$C$304,$C34,'12. Requirements Register'!$E$5:$E$304,$J$4:$O$4,'12. Requirements Register'!$M$5:$M$304,"Ready"),_xlpm.reqOK,SUM(--(_xlpm.flag="Yes")*--(_xlpm.total>0)*--(_xlpm.readyCount=_xlpm.total))=COUNTIF(_xlpm.flag,"Yes"),_xlpm.core,AND($H34<>"",$I34<>"",$P34<>"",$Q34<>"",$R34<>"",$V34<>"",$V34<>"Not Created"),IF($S34<>"",IF(AND($S34<=TODAY(),_xlpm.core,_xlpm.reqOK),"Completed","Incomplete"),IF($Q34="","Planned",IF(TODAY()<$Q34,"Planned",IF($R34="","In Progress",IF(TODAY()<=$R34,"In Progress","Overdue")))))))} -> Planned | U34: =IF($B34="","",IF(COUNTIFS($B$5:$B$64,$B34,$G$5:$G$64,$G34,$H$5:$H$64,$H34)>1,"DUPLICATE","OK")) -> OK | V34: {=IF($C34="","",IFERROR(_xlfn.LET(_xlpm.x,_xlfn.UNIQUE(_xlfn._xlws.FILTER('14. Recovery & Response'!$B$6:$B$105,('14. Recovery & Response'!$C$6:$C$105=$C34)*('14. Recovery & Response'!$B$6:$B$105<>""))),_xlfn.TEXTJOIN(",",TRUE,_xlpm.x)),"Not Created"))} -> RR-001
A35: 31 | C35: =IF($B35="","","SS-"&TEXT($A35,"000")) | D35: {=IF($B35="","",IFERROR(_xlfn.XLOOKUP($B35,INDEX(RiskAssessment[],0,2),INDEX(RiskAssessment[],0,5),""),""))} | E35: {=IF($B35="","",IFERROR(_xlfn.XLOOKUP($B35,INDEX(RiskAssessment[],0,2),INDEX(RiskAssessment[],0,7),""),""))} | F35: {=IF($B35="","",IFERROR(_xlfn.XLOOKUP($B35,INDEX(RiskAssessment[],0,2),INDEX(RiskAssessment[],0,8),""),""))} | G35: =IF($B35="","",_xlfn.XLOOKUP($B35,'10. Risk Assessment'!$B$5:$B$34,'10. Risk Assessment'!$F$5:$F$34,"")) | T35: {=IF($B35="","",_xlfn.LET(_xlpm.flag,$J35:$O35,_xlpm.total,COUNTIFS('12. Requirements Register'!$C$5:$C$304,$C35,'12. Requirements Register'!$E$5:$E$304,$J$4:$O$4),_xlpm.readyCount,COUNTIFS('12. Requirements Register'!$C$5:$C$304,$C35,'12. Requirements Register'!$E$5:$E$304,$J$4:$O$4,'12. Requirements Register'!$M$5:$M$304,"Ready"),_xlpm.reqOK,SUM(--(_xlpm.flag="Yes")*--(_xlpm.total>0)*--(_xlpm.readyCount=_xlpm.total))=COUNTIF(_xlpm.flag,"Yes"),_xlpm.core,AND($H35<>"",$I35<>"",$P35<>"",$Q35<>"",$R35<>"",$V35<>"",$V35<>"Not Created"),IF($S35<>"",IF(AND($S35<=TODAY(),_xlpm.core,_xlpm.reqOK),"Completed","Incomplete"),IF($Q35="","Planned",IF(TODAY()<$Q35,"Planned",IF($R35="","In Progress",IF(TODAY()<=$R35,"In Progress","Overdue")))))))} | U35: =IF($B35="","",IF(COUNTIFS($B$5:$B$64,$B35,$G$5:$G$64,$G35,$H$5:$H$64,$H35)>1,"DUPLICATE","OK")) | V35: {=IF($C35="","",IFERROR(_xlfn.LET(_xlpm.x,_xlfn.UNIQUE(_xlfn._xlws.FILTER('14. Recovery & Response'!$B$6:$B$105,('14. Recovery & Response'!$C$6:$C$105=$C35)*('14. Recovery & Response'!$B$6:$B$105<>""))),_xlfn.TEXTJOIN(",",TRUE,_xlpm.x)),"Not Created"))}
A36: 32 | C36: =IF($B36="","","SS-"&TEXT($A36,"000")) | D36: {=IF($B36="","",IFERROR(_xlfn.XLOOKUP($B36,INDEX(RiskAssessment[],0,2),INDEX(RiskAssessment[],0,5),""),""))} | E36: {=IF($B36="","",IFERROR(_xlfn.XLOOKUP($B36,INDEX(RiskAssessment[],0,2),INDEX(RiskAssessment[],0,7),""),""))} | F36: {=IF($B36="","",IFERROR(_xlfn.XLOOKUP($B36,INDEX(RiskAssessment[],0,2),INDEX(RiskAssessment[],0,8),""),""))} | G36: =IF($B36="","",_xlfn.XLOOKUP($B36,'10. Risk Assessment'!$B$5:$B$34,'10. Risk Assessment'!$F$5:$F$34,"")) | T36: {=IF($B36="","",_xlfn.LET(_xlpm.flag,$J36:$O36,_xlpm.total,COUNTIFS('12. Requirements Register'!$C$5:$C$304,$C36,'12. Requirements Register'!$E$5:$E$304,$J$4:$O$4),_xlpm.readyCount,COUNTIFS('12. Requirements Register'!$C$5:$C$304,$C36,'12. Requirements Register'!$E$5:$E$304,$J$4:$O$4,'12. Requirements Register'!$M$5:$M$304,"Ready"),_xlpm.reqOK,SUM(--(_xlpm.flag="Yes")*--(_xlpm.total>0)*--(_xlpm.readyCount=_xlpm.total))=COUNTIF(_xlpm.flag,"Yes"),_xlpm.core,AND($H36<>"",$I36<>"",$P36<>"",$Q36<>"",$R36<>"",$V36<>"",$V36<>"Not Created"),IF($S36<>"",IF(AND($S36<=TODAY(),_xlpm.core,_xlpm.reqOK),"Completed","Incomplete"),IF($Q36="","Planned",IF(TODAY()<$Q36,"Planned",IF($R36="","In Progress",IF(TODAY()<=$R36,"In Progress","Overdue")))))))} | U36: =IF($B36="","",IF(COUNTIFS($B$5:$B$64,$B36,$G$5:$G$64,$G36,$H$5:$H$64,$H36)>1,"DUPLICATE","OK")) | V36: {=IF($C36="","",IFERROR(_xlfn.LET(_xlpm.x,_xlfn.UNIQUE(_xlfn._xlws.FILTER('14. Recovery & Response'!$B$6:$B$105,('14. Recovery & Response'!$C$6:$C$105=$C36)*('14. Recovery & Response'!$B$6:$B$105<>""))),_xlfn.TEXTJOIN(",",TRUE,_xlpm.x)),"Not Created"))}
A37: 33 | C37: =IF($B37="","","SS-"&TEXT($A37,"000")) | D37: {=IF($B37="","",IFERROR(_xlfn.XLOOKUP($B37,INDEX(RiskAssessment[],0,2),INDEX(RiskAssessment[],0,5),""),""))} | E37: {=IF($B37="","",IFERROR(_xlfn.XLOOKUP($B37,INDEX(RiskAssessment[],0,2),INDEX(RiskAssessment[],0,7),""),""))} | F37: {=IF($B37="","",IFERROR(_xlfn.XLOOKUP($B37,INDEX(RiskAssessment[],0,2),INDEX(RiskAssessment[],0,8),""),""))} | G37: =IF($B37="","",_xlfn.XLOOKUP($B37,'10. Risk Assessment'!$B$5:$B$34,'10. Risk Assessment'!$F$5:$F$34,"")) | T37: {=IF($B37="","",_xlfn.LET(_xlpm.flag,$J37:$O37,_xlpm.total,COUNTIFS('12. Requirements Register'!$C$5:$C$304,$C37,'12. Requirements Register'!$E$5:$E$304,$J$4:$O$4),_xlpm.readyCount,COUNTIFS('12. Requirements Register'!$C$5:$C$304,$C37,'12. Requirements Register'!$E$5:$E$304,$J$4:$O$4,'12. Requirements Register'!$M$5:$M$304,"Ready"),_xlpm.reqOK,SUM(--(_xlpm.flag="Yes")*--(_xlpm.total>0)*--(_xlpm.readyCount=_xlpm.total))=COUNTIF(_xlpm.flag,"Yes"),_xlpm.core,AND($H37<>"",$I37<>"",$P37<>"",$Q37<>"",$R37<>"",$V37<>"",$V37<>"Not Created"),IF($S37<>"",IF(AND($S37<=TODAY(),_xlpm.core,_xlpm.reqOK),"Completed","Incomplete"),IF($Q37="","Planned",IF(TODAY()<$Q37,"Planned",IF($R37="","In Progress",IF(TODAY()<=$R37,"In Progress","Overdue")))))))} | U37: =IF($B37="","",IF(COUNTIFS($B$5:$B$64,$B37,$G$5:$G$64,$G37,$H$5:$H$64,$H37)>1,"DUPLICATE","OK")) | V37: {=IF($C37="","",IFERROR(_xlfn.LET(_xlpm.x,_xlfn.UNIQUE(_xlfn._xlws.FILTER('14. Recovery & Response'!$B$6:$B$105,('14. Recovery & Response'!$C$6:$C$105=$C37)*('14. Recovery & Response'!$B$6:$B$105<>""))),_xlfn.TEXTJOIN(",",TRUE,_xlpm.x)),"Not Created"))}
A38: 34 | C38: =IF($B38="","","SS-"&TEXT($A38,"000")) | D38: {=IF($B38="","",IFERROR(_xlfn.XLOOKUP($B38,INDEX(RiskAssessment[],0,2),INDEX(RiskAssessment[],0,5),""),""))} | E38: {=IF($B38="","",IFERROR(_xlfn.XLOOKUP($B38,INDEX(RiskAssessment[],0,2),INDEX(RiskAssessment[],0,7),""),""))} | F38: {=IF($B38="","",IFERROR(_xlfn.XLOOKUP($B38,INDEX(RiskAssessment[],0,2),INDEX(RiskAssessment[],0,8),""),""))} | G38: =IF($B38="","",_xlfn.XLOOKUP($B38,'10. Risk Assessment'!$B$5:$B$34,'10. Risk Assessment'!$F$5:$F$34,"")) | T38: {=IF($B38="","",_xlfn.LET(_xlpm.flag,$J38:$O38,_xlpm.total,COUNTIFS('12. Requirements Register'!$C$5:$C$304,$C38,'12. Requirements Register'!$E$5:$E$304,$J$4:$O$4),_xlpm.readyCount,COUNTIFS('12. Requirements Register'!$C$5:$C$304,$C38,'12. Requirements Register'!$E$5:$E$304,$J$4:$O$4,'12. Requirements Register'!$M$5:$M$304,"Ready"),_xlpm.reqOK,SUM(--(_xlpm.flag="Yes")*--(_xlpm.total>0)*--(_xlpm.readyCount=_xlpm.total))=COUNTIF(_xlpm.flag,"Yes"),_xlpm.core,AND($H38<>"",$I38<>"",$P38<>"",$Q38<>"",$R38<>"",$V38<>"",$V38<>"Not Created"),IF($S38<>"",IF(AND($S38<=TODAY(),_xlpm.core,_xlpm.reqOK),"Completed","Incomplete"),IF($Q38="","Planned",IF(TODAY()<$Q38,"Planned",IF($R38="","In Progress",IF(TODAY()<=$R38,"In Progress","Overdue")))))))} | U38: =IF($B38="","",IF(COUNTIFS($B$5:$B$64,$B38,$G$5:$G$64,$G38,$H$5:$H$64,$H38)>1,"DUPLICATE","OK")) | V38: {=IF($C38="","",IFERROR(_xlfn.LET(_xlpm.x,_xlfn.UNIQUE(_xlfn._xlws.FILTER('14. Recovery & Response'!$B$6:$B$105,('14. Recovery & Response'!$C$6:$C$105=$C38)*('14. Recovery & Response'!$B$6:$B$105<>""))),_xlfn.TEXTJOIN(",",TRUE,_xlpm.x)),"Not Created"))}
A39: 35 | C39: =IF($B39="","","SS-"&TEXT($A39,"000")) | D39: {=IF($B39="","",IFERROR(_xlfn.XLOOKUP($B39,INDEX(RiskAssessment[],0,2),INDEX(RiskAssessment[],0,5),""),""))} | E39: {=IF($B39="","",IFERROR(_xlfn.XLOOKUP($B39,INDEX(RiskAssessment[],0,2),INDEX(RiskAssessment[],0,7),""),""))} | F39: {=IF($B39="","",IFERROR(_xlfn.XLOOKUP($B39,INDEX(RiskAssessment[],0,2),INDEX(RiskAssessment[],0,8),""),""))} | G39: =IF($B39="","",_xlfn.XLOOKUP($B39,'10. Risk Assessment'!$B$5:$B$34,'10. Risk Assessment'!$F$5:$F$34,"")) | T39: {=IF($B39="","",_xlfn.LET(_xlpm.flag,$J39:$O39,_xlpm.total,COUNTIFS('12. Requirements Register'!$C$5:$C$304,$C39,'12. Requirements Register'!$E$5:$E$304,$J$4:$O$4),_xlpm.readyCount,COUNTIFS('12. Requirements Register'!$C$5:$C$304,$C39,'12. Requirements Register'!$E$5:$E$304,$J$4:$O$4,'12. Requirements Register'!$M$5:$M$304,"Ready"),_xlpm.reqOK,SUM(--(_xlpm.flag="Yes")*--(_xlpm.total>0)*--(_xlpm.readyCount=_xlpm.total))=COUNTIF(_xlpm.flag,"Yes"),_xlpm.core,AND($H39<>"",$I39<>"",$P39<>"",$Q39<>"",$R39<>"",$V39<>"",$V39<>"Not Created"),IF($S39<>"",IF(AND($S39<=TODAY(),_xlpm.core,_xlpm.reqOK),"Completed","Incomplete"),IF($Q39="","Planned",IF(TODAY()<$Q39,"Planned",IF($R39="","In Progress",IF(TODAY()<=$R39,"In Progress","Overdue")))))))} | U39: =IF($B39="","",IF(COUNTIFS($B$5:$B$64,$B39,$G$5:$G$64,$G39,$H$5:$H$64,$H39)>1,"DUPLICATE","OK")) | V39: {=IF($C39="","",IFERROR(_xlfn.LET(_xlpm.x,_xlfn.UNIQUE(_xlfn._xlws.FILTER('14. Recovery & Response'!$B$6:$B$105,('14. Recovery & Response'!$C$6:$C$105=$C39)*('14. Recovery & Response'!$B$6:$B$105<>""))),_xlfn.TEXTJOIN(",",TRUE,_xlpm.x)),"Not Created"))}
A40: 36 | C40: =IF($B40="","","SS-"&TEXT($A40,"000")) | D40: {=IF($B40="","",IFERROR(_xlfn.XLOOKUP($B40,INDEX(RiskAssessment[],0,2),INDEX(RiskAssessment[],0,5),""),""))} | E40: {=IF($B40="","",IFERROR(_xlfn.XLOOKUP($B40,INDEX(RiskAssessment[],0,2),INDEX(RiskAssessment[],0,7),""),""))} | F40: {=IF($B40="","",IFERROR(_xlfn.XLOOKUP($B40,INDEX(RiskAssessment[],0,2),INDEX(RiskAssessment[],0,8),""),""))} | G40: =IF($B40="","",_xlfn.XLOOKUP($B40,'10. Risk Assessment'!$B$5:$B$34,'10. Risk Assessment'!$F$5:$F$34,"")) | T40: {=IF($B40="","",_xlfn.LET(_xlpm.flag,$J40:$O40,_xlpm.total,COUNTIFS('12. Requirements Register'!$C$5:$C$304,$C40,'12. Requirements Register'!$E$5:$E$304,$J$4:$O$4),_xlpm.readyCount,COUNTIFS('12. Requirements Register'!$C$5:$C$304,$C40,'12. Requirements Register'!$E$5:$E$304,$J$4:$O$4,'12. Requirements Register'!$M$5:$M$304,"Ready"),_xlpm.reqOK,SUM(--(_xlpm.flag="Yes")*--(_xlpm.total>0)*--(_xlpm.readyCount=_xlpm.total))=COUNTIF(_xlpm.flag,"Yes"),_xlpm.core,AND($H40<>"",$I40<>"",$P40<>"",$Q40<>"",$R40<>"",$V40<>"",$V40<>"Not Created"),IF($S40<>"",IF(AND($S40<=TODAY(),_xlpm.core,_xlpm.reqOK),"Completed","Incomplete"),IF($Q40="","Planned",IF(TODAY()<$Q40,"Planned",IF($R40="","In Progress",IF(TODAY()<=$R40,"In Progress","Overdue")))))))} | U40: =IF($B40="","",IF(COUNTIFS($B$5:$B$64,$B40,$G$5:$G$64,$G40,$H$5:$H$64,$H40)>1,"DUPLICATE","OK")) | V40: {=IF($C40="","",IFERROR(_xlfn.LET(_xlpm.x,_xlfn.UNIQUE(_xlfn._xlws.FILTER('14. Recovery & Response'!$B$6:$B$105,('14. Recovery & Response'!$C$6:$C$105=$C40)*('14. Recovery & Response'!$B$6:$B$105<>""))),_xlfn.TEXTJOIN(",",TRUE,_xlpm.x)),"Not Created"))}
A41: 37 | C41: =IF($B41="","","SS-"&TEXT($A41,"000")) | D41: {=IF($B41="","",IFERROR(_xlfn.XLOOKUP($B41,INDEX(RiskAssessment[],0,2),INDEX(RiskAssessment[],0,5),""),""))} | E41: {=IF($B41="","",IFERROR(_xlfn.XLOOKUP($B41,INDEX(RiskAssessment[],0,2),INDEX(RiskAssessment[],0,7),""),""))} | F41: {=IF($B41="","",IFERROR(_xlfn.XLOOKUP($B41,INDEX(RiskAssessment[],0,2),INDEX(RiskAssessment[],0,8),""),""))} | G41: =IF($B41="","",_xlfn.XLOOKUP($B41,'10. Risk Assessment'!$B$5:$B$34,'10. Risk Assessment'!$F$5:$F$34,"")) | T41: {=IF($B41="","",_xlfn.LET(_xlpm.flag,$J41:$O41,_xlpm.total,COUNTIFS('12. Requirements Register'!$C$5:$C$304,$C41,'12. Requirements Register'!$E$5:$E$304,$J$4:$O$4),_xlpm.readyCount,COUNTIFS('12. Requirements Register'!$C$5:$C$304,$C41,'12. Requirements Register'!$E$5:$E$304,$J$4:$O$4,'12. Requirements Register'!$M$5:$M$304,"Ready"),_xlpm.reqOK,SUM(--(_xlpm.flag="Yes")*--(_xlpm.total>0)*--(_xlpm.readyCount=_xlpm.total))=COUNTIF(_xlpm.flag,"Yes"),_xlpm.core,AND($H41<>"",$I41<>"",$P41<>"",$Q41<>"",$R41<>"",$V41<>"",$V41<>"Not Created"),IF($S41<>"",IF(AND($S41<=TODAY(),_xlpm.core,_xlpm.reqOK),"Completed","Incomplete"),IF($Q41="","Planned",IF(TODAY()<$Q41,"Planned",IF($R41="","In Progress",IF(TODAY()<=$R41,"In Progress","Overdue")))))))} | U41: =IF($B41="","",IF(COUNTIFS($B$5:$B$64,$B41,$G$5:$G$64,$G41,$H$5:$H$64,$H41)>1,"DUPLICATE","OK")) | V41: {=IF($C41="","",IFERROR(_xlfn.LET(_xlpm.x,_xlfn.UNIQUE(_xlfn._xlws.FILTER('14. Recovery & Response'!$B$6:$B$105,('14. Recovery & Response'!$C$6:$C$105=$C41)*('14. Recovery & Response'!$B$6:$B$105<>""))),_xlfn.TEXTJOIN(",",TRUE,_xlpm.x)),"Not Created"))}
A42: 38 | C42: =IF($B42="","","SS-"&TEXT($A42,"000")) | D42: {=IF($B42="","",IFERROR(_xlfn.XLOOKUP($B42,INDEX(RiskAssessment[],0,2),INDEX(RiskAssessment[],0,5),""),""))} | E42: {=IF($B42="","",IFERROR(_xlfn.XLOOKUP($B42,INDEX(RiskAssessment[],0,2),INDEX(RiskAssessment[],0,7),""),""))} | F42: {=IF($B42="","",IFERROR(_xlfn.XLOOKUP($B42,INDEX(RiskAssessment[],0,2),INDEX(RiskAssessment[],0,8),""),""))} | G42: =IF($B42="","",_xlfn.XLOOKUP($B42,'10. Risk Assessment'!$B$5:$B$34,'10. Risk Assessment'!$F$5:$F$34,"")) | T42: {=IF($B42="","",_xlfn.LET(_xlpm.flag,$J42:$O42,_xlpm.total,COUNTIFS('12. Requirements Register'!$C$5:$C$304,$C42,'12. Requirements Register'!$E$5:$E$304,$J$4:$O$4),_xlpm.readyCount,COUNTIFS('12. Requirements Register'!$C$5:$C$304,$C42,'12. Requirements Register'!$E$5:$E$304,$J$4:$O$4,'12. Requirements Register'!$M$5:$M$304,"Ready"),_xlpm.reqOK,SUM(--(_xlpm.flag="Yes")*--(_xlpm.total>0)*--(_xlpm.readyCount=_xlpm.total))=COUNTIF(_xlpm.flag,"Yes"),_xlpm.core,AND($H42<>"",$I42<>"",$P42<>"",$Q42<>"",$R42<>"",$V42<>"",$V42<>"Not Created"),IF($S42<>"",IF(AND($S42<=TODAY(),_xlpm.core,_xlpm.reqOK),"Completed","Incomplete"),IF($Q42="","Planned",IF(TODAY()<$Q42,"Planned",IF($R42="","In Progress",IF(TODAY()<=$R42,"In Progress","Overdue")))))))} | U42: =IF($B42="","",IF(COUNTIFS($B$5:$B$64,$B42,$G$5:$G$64,$G42,$H$5:$H$64,$H42)>1,"DUPLICATE","OK")) | V42: {=IF($C42="","",IFERROR(_xlfn.LET(_xlpm.x,_xlfn.UNIQUE(_xlfn._xlws.FILTER('14. Recovery & Response'!$B$6:$B$105,('14. Recovery & Response'!$C$6:$C$105=$C42)*('14. Recovery & Response'!$B$6:$B$105<>""))),_xlfn.TEXTJOIN(",",TRUE,_xlpm.x)),"Not Created"))}
A43: 39 | C43: =IF($B43="","","SS-"&TEXT($A43,"000")) | D43: {=IF($B43="","",IFERROR(_xlfn.XLOOKUP($B43,INDEX(RiskAssessment[],0,2),INDEX(RiskAssessment[],0,5),""),""))} | E43: {=IF($B43="","",IFERROR(_xlfn.XLOOKUP($B43,INDEX(RiskAssessment[],0,2),INDEX(RiskAssessment[],0,7),""),""))} | F43: {=IF($B43="","",IFERROR(_xlfn.XLOOKUP($B43,INDEX(RiskAssessment[],0,2),INDEX(RiskAssessment[],0,8),""),""))} | G43: =IF($B43="","",_xlfn.XLOOKUP($B43,'10. Risk Assessment'!$B$5:$B$34,'10. Risk Assessment'!$F$5:$F$34,"")) | T43: {=IF($B43="","",_xlfn.LET(_xlpm.flag,$J43:$O43,_xlpm.total,COUNTIFS('12. Requirements Register'!$C$5:$C$304,$C43,'12. Requirements Register'!$E$5:$E$304,$J$4:$O$4),_xlpm.readyCount,COUNTIFS('12. Requirements Register'!$C$5:$C$304,$C43,'12. Requirements Register'!$E$5:$E$304,$J$4:$O$4,'12. Requirements Register'!$M$5:$M$304,"Ready"),_xlpm.reqOK,SUM(--(_xlpm.flag="Yes")*--(_xlpm.total>0)*--(_xlpm.readyCount=_xlpm.total))=COUNTIF(_xlpm.flag,"Yes"),_xlpm.core,AND($H43<>"",$I43<>"",$P43<>"",$Q43<>"",$R43<>"",$V43<>"",$V43<>"Not Created"),IF($S43<>"",IF(AND($S43<=TODAY(),_xlpm.core,_xlpm.reqOK),"Completed","Incomplete"),IF($Q43="","Planned",IF(TODAY()<$Q43,"Planned",IF($R43="","In Progress",IF(TODAY()<=$R43,"In Progress","Overdue")))))))} | U43: =IF($B43="","",IF(COUNTIFS($B$5:$B$64,$B43,$G$5:$G$64,$G43,$H$5:$H$64,$H43)>1,"DUPLICATE","OK")) | V43: {=IF($C43="","",IFERROR(_xlfn.LET(_xlpm.x,_xlfn.UNIQUE(_xlfn._xlws.FILTER('14. Recovery & Response'!$B$6:$B$105,('14. Recovery & Response'!$C$6:$C$105=$C43)*('14. Recovery & Response'!$B$6:$B$105<>""))),_xlfn.TEXTJOIN(",",TRUE,_xlpm.x)),"Not Created"))}
A44: 40 | C44: =IF($B44="","","SS-"&TEXT($A44,"000")) | D44: {=IF($B44="","",IFERROR(_xlfn.XLOOKUP($B44,INDEX(RiskAssessment[],0,2),INDEX(RiskAssessment[],0,5),""),""))} | E44: {=IF($B44="","",IFERROR(_xlfn.XLOOKUP($B44,INDEX(RiskAssessment[],0,2),INDEX(RiskAssessment[],0,7),""),""))} | F44: {=IF($B44="","",IFERROR(_xlfn.XLOOKUP($B44,INDEX(RiskAssessment[],0,2),INDEX(RiskAssessment[],0,8),""),""))} | G44: =IF($B44="","",_xlfn.XLOOKUP($B44,'10. Risk Assessment'!$B$5:$B$34,'10. Risk Assessment'!$F$5:$F$34,"")) | T44: {=IF($B44="","",_xlfn.LET(_xlpm.flag,$J44:$O44,_xlpm.total,COUNTIFS('12. Requirements Register'!$C$5:$C$304,$C44,'12. Requirements Register'!$E$5:$E$304,$J$4:$O$4),_xlpm.readyCount,COUNTIFS('12. Requirements Register'!$C$5:$C$304,$C44,'12. Requirements Register'!$E$5:$E$304,$J$4:$O$4,'12. Requirements Register'!$M$5:$M$304,"Ready"),_xlpm.reqOK,SUM(--(_xlpm.flag="Yes")*--(_xlpm.total>0)*--(_xlpm.readyCount=_xlpm.total))=COUNTIF(_xlpm.flag,"Yes"),_xlpm.core,AND($H44<>"",$I44<>"",$P44<>"",$Q44<>"",$R44<>"",$V44<>"",$V44<>"Not Created"),IF($S44<>"",IF(AND($S44<=TODAY(),_xlpm.core,_xlpm.reqOK),"Completed","Incomplete"),IF($Q44="","Planned",IF(TODAY()<$Q44,"Planned",IF($R44="","In Progress",IF(TODAY()<=$R44,"In Progress","Overdue")))))))} | U44: =IF($B44="","",IF(COUNTIFS($B$5:$B$64,$B44,$G$5:$G$64,$G44,$H$5:$H$64,$H44)>1,"DUPLICATE","OK")) | V44: {=IF($C44="","",IFERROR(_xlfn.LET(_xlpm.x,_xlfn.UNIQUE(_xlfn._xlws.FILTER('14. Recovery & Response'!$B$6:$B$105,('14. Recovery & Response'!$C$6:$C$105=$C44)*('14. Recovery & Response'!$B$6:$B$105<>""))),_xlfn.TEXTJOIN(",",TRUE,_xlpm.x)),"Not Created"))}
A45: 41 | C45: =IF($B45="","","SS-"&TEXT($A45,"000")) | D45: {=IF($B45="","",IFERROR(_xlfn.XLOOKUP($B45,INDEX(RiskAssessment[],0,2),INDEX(RiskAssessment[],0,5),""),""))} | E45: {=IF($B45="","",IFERROR(_xlfn.XLOOKUP($B45,INDEX(RiskAssessment[],0,2),INDEX(RiskAssessment[],0,7),""),""))} | F45: {=IF($B45="","",IFERROR(_xlfn.XLOOKUP($B45,INDEX(RiskAssessment[],0,2),INDEX(RiskAssessment[],0,8),""),""))} | G45: =IF($B45="","",_xlfn.XLOOKUP($B45,'10. Risk Assessment'!$B$5:$B$34,'10. Risk Assessment'!$F$5:$F$34,"")) | T45: {=IF($B45="","",_xlfn.LET(_xlpm.flag,$J45:$O45,_xlpm.total,COUNTIFS('12. Requirements Register'!$C$5:$C$304,$C45,'12. Requirements Register'!$E$5:$E$304,$J$4:$O$4),_xlpm.readyCount,COUNTIFS('12. Requirements Register'!$C$5:$C$304,$C45,'12. Requirements Register'!$E$5:$E$304,$J$4:$O$4,'12. Requirements Register'!$M$5:$M$304,"Ready"),_xlpm.reqOK,SUM(--(_xlpm.flag="Yes")*--(_xlpm.total>0)*--(_xlpm.readyCount=_xlpm.total))=COUNTIF(_xlpm.flag,"Yes"),_xlpm.core,AND($H45<>"",$I45<>"",$P45<>"",$Q45<>"",$R45<>"",$V45<>"",$V45<>"Not Created"),IF($S45<>"",IF(AND($S45<=TODAY(),_xlpm.core,_xlpm.reqOK),"Completed","Incomplete"),IF($Q45="","Planned",IF(TODAY()<$Q45,"Planned",IF($R45="","In Progress",IF(TODAY()<=$R45,"In Progress","Overdue")))))))} | U45: =IF($B45="","",IF(COUNTIFS($B$5:$B$64,$B45,$G$5:$G$64,$G45,$H$5:$H$64,$H45)>1,"DUPLICATE","OK")) | V45: {=IF($C45="","",IFERROR(_xlfn.LET(_xlpm.x,_xlfn.UNIQUE(_xlfn._xlws.FILTER('14. Recovery & Response'!$B$6:$B$105,('14. Recovery & Response'!$C$6:$C$105=$C45)*('14. Recovery & Response'!$B$6:$B$105<>""))),_xlfn.TEXTJOIN(",",TRUE,_xlpm.x)),"Not Created"))}
A46: 42 | C46: =IF($B46="","","SS-"&TEXT($A46,"000")) | D46: {=IF($B46="","",IFERROR(_xlfn.XLOOKUP($B46,INDEX(RiskAssessment[],0,2),INDEX(RiskAssessment[],0,5),""),""))} | E46: {=IF($B46="","",IFERROR(_xlfn.XLOOKUP($B46,INDEX(RiskAssessment[],0,2),INDEX(RiskAssessment[],0,7),""),""))} | F46: {=IF($B46="","",IFERROR(_xlfn.XLOOKUP($B46,INDEX(RiskAssessment[],0,2),INDEX(RiskAssessment[],0,8),""),""))} | G46: =IF($B46="","",_xlfn.XLOOKUP($B46,'10. Risk Assessment'!$B$5:$B$34,'10. Risk Assessment'!$F$5:$F$34,"")) | T46: {=IF($B46="","",_xlfn.LET(_xlpm.flag,$J46:$O46,_xlpm.total,COUNTIFS('12. Requirements Register'!$C$5:$C$304,$C46,'12. Requirements Register'!$E$5:$E$304,$J$4:$O$4),_xlpm.readyCount,COUNTIFS('12. Requirements Register'!$C$5:$C$304,$C46,'12. Requirements Register'!$E$5:$E$304,$J$4:$O$4,'12. Requirements Register'!$M$5:$M$304,"Ready"),_xlpm.reqOK,SUM(--(_xlpm.flag="Yes")*--(_xlpm.total>0)*--(_xlpm.readyCount=_xlpm.total))=COUNTIF(_xlpm.flag,"Yes"),_xlpm.core,AND($H46<>"",$I46<>"",$P46<>"",$Q46<>"",$R46<>"",$V46<>"",$V46<>"Not Created"),IF($S46<>"",IF(AND($S46<=TODAY(),_xlpm.core,_xlpm.reqOK),"Completed","Incomplete"),IF($Q46="","Planned",IF(TODAY()<$Q46,"Planned",IF($R46="","In Progress",IF(TODAY()<=$R46,"In Progress","Overdue")))))))} | U46: =IF($B46="","",IF(COUNTIFS($B$5:$B$64,$B46,$G$5:$G$64,$G46,$H$5:$H$64,$H46)>1,"DUPLICATE","OK")) | V46: {=IF($C46="","",IFERROR(_xlfn.LET(_xlpm.x,_xlfn.UNIQUE(_xlfn._xlws.FILTER('14. Recovery & Response'!$B$6:$B$105,('14. Recovery & Response'!$C$6:$C$105=$C46)*('14. Recovery & Response'!$B$6:$B$105<>""))),_xlfn.TEXTJOIN(",",TRUE,_xlpm.x)),"Not Created"))}
... A64: 60 | C64: =IF($B64="","","SS-"&TEXT($A64,"000")) | D64: {=IF($B64="","",IFERROR(_xlfn.XLOOKUP($B64,INDEX(RiskAssessment[],0,2),INDEX(RiskAssessment[],0,5),""),""))} | E64: {=IF($B64="","",IFERROR(_xlfn.XLOOKUP($B64,INDEX(RiskAssessment[],0,2),INDEX(RiskAssessment[],0,7),""),""))} | F64: {=IF($B64="","",IFERROR(_xlfn.XLOOKUP($B64,INDEX(RiskAssessment[],0,2),INDEX(RiskAssessment[],0,8),""),""))} | G64: =IF($B64="","",_xlfn.XLOOKUP($B64,'10. Risk Assessment'!$B$5:$B$34,'10. Risk Assessment'!$F$5:$F$34,"")) | T64: {=IF($B64="","",_xlfn.LET(_xlpm.flag,$J64:$O64,_xlpm.total,COUNTIFS('12. Requirements Register'!$C$5:$C$304,$C64,'12. Requirements Register'!$E$5:$E$304,$J$4:$O$4),_xlpm.readyCount,COUNTIFS('12. Requirements Register'!$C$5:$C$304,$C64,'12. Requirements Register'!$E$5:$E$304,$J$4:$O$4,'12. Requirements Register'!$M$5:$M$304,"Ready"),_xlpm.reqOK,SUM(--(_xlpm.flag="Yes")*--(_xlpm.total>0)*--(_xlpm.readyCount=_xlpm.total))=COUNTIF(_xlpm.flag,"Yes"),_xlpm.core,AND($H64<>"",$I64<>"",$P64<>"",$Q64<>"",$R64<>"",$V64<>"",$V64<>"Not Created"),IF($S64<>"",IF(AND($S64<=TODAY(),_xlpm.core,_xlpm.reqOK),"Completed","Incomplete"),IF($Q64="","Planned",IF(TODAY()<$Q64,"Planned",IF($R64="","In Progress",IF(TODAY()<=$R64,"In Progress","Overdue")))))))} | U64: =IF($B64="","",IF(COUNTIFS($B$5:$B$64,$B64,$G$5:$G$64,$G64,$H$5:$H$64,$H64)>1,"DUPLICATE","OK")) | V64: {=IF($C64="","",IFERROR(_xlfn.LET(_xlpm.x,_xlfn.UNIQUE(_xlfn._xlws.FILTER('14. Recovery & Response'!$B$6:$B$105,('14. Recovery & Response'!$C$6:$C$105=$C64)*('14. Recovery & Response'!$B$6:$B$105<>""))),_xlfn.TEXTJOIN(",",TRUE,_xlpm.x)),"Not Created"))}

Sheet 12. Requirements Register
A1: Step 4b - Requirements Register
A2: One row per continuity requirement | ISO 22301: 8.3 Business continuity strategies and solutions
A4: No. | B4: Req ID | C4: S&S ID | D4: Risk ID (auto) | E4: Category | F4: Item / Resource / Role | G4: Detail / Specification | H4: MBCO resource requirement | I4: Primary Location | J4: Alternate Location(s) | K4: Supporting Documents | L4: Owner | M4: Readiness (auto)
A5: 1 | B5: =IF($F5="","","REQ-"&TEXT($A5,"000")) | C5: SS-030 | D5: =IF($C5="","",_xlfn.XLOOKUP($C5,StrategiesSolutions[S&S ID],StrategiesSolutions[Risk ID],"")) -> RA-001 | E5: People | M5: Ready
A6: 2 | B6: =IF($F6="","","REQ-"&TEXT($A6,"000")) | D6: =IF($C6="","",_xlfn.XLOOKUP($C6,StrategiesSolutions[S&S ID],StrategiesSolutions[Risk ID],"")) | E6: ICT
A7: 3 | B7: =IF($F7="","","REQ-"&TEXT($A7,"000")) | D7: =IF($C7="","",_xlfn.XLOOKUP($C7,StrategiesSolutions[S&S ID],StrategiesSolutions[Risk ID],""))
A8: 4 | B8: =IF($F8="","","REQ-"&TEXT($A8,"000")) | D8: =IF($C8="","",_xlfn.XLOOKUP($C8,StrategiesSolutions[S&S ID],StrategiesSolutions[Risk ID],""))
A9: 5 | B9: =IF($F9="","","REQ-"&TEXT($A9,"000")) | D9: =IF($C9="","",_xlfn.XLOOKUP($C9,StrategiesSolutions[S&S ID],StrategiesSolutions[Risk ID],""))
A10: 6 | B10: =IF($F10="","","REQ-"&TEXT($A10,"000")) | D10: =IF($C10="","",_xlfn.XLOOKUP($C10,StrategiesSolutions[S&S ID],StrategiesSolutions[Risk ID],""))
A11: 7 | B11: =IF($F11="","","REQ-"&TEXT($A11,"000")) | D11: =IF($C11="","",_xlfn.XLOOKUP($C11,StrategiesSolutions[S&S ID],StrategiesSolutions[Risk ID],""))
A12: 8 | B12: =IF($F12="","","REQ-"&TEXT($A12,"000")) | D12: =IF($C12="","",_xlfn.XLOOKUP($C12,StrategiesSolutions[S&S ID],StrategiesSolutions[Risk ID],""))
A13: 9 | B13: =IF($F13="","","REQ-"&TEXT($A13,"000")) | D13: =IF($C13="","",_xlfn.XLOOKUP($C13,StrategiesSolutions[S&S ID],StrategiesSolutions[Risk ID],""))
A14: 10 | B14: =IF($F14="","","REQ-"&TEXT($A14,"000")) | D14: =IF($C14="","",_xlfn.XLOOKUP($C14,StrategiesSolutions[S&S ID],StrategiesSolutions[Risk ID],""))
A15: 11 | B15: =IF($F15="","","REQ-"&TEXT($A15,"000")) | D15: =IF($C15="","",_xlfn.XLOOKUP($C15,StrategiesSolutions[S&S ID],StrategiesSolutions[Risk ID],""))
A16: 12 | B16: =IF($F16="","","REQ-"&TEXT($A16,"000")) | D16: =IF($C16="","",_xlfn.XLOOKUP($C16,StrategiesSolutions[S&S ID],StrategiesSolutions[Risk ID],""))
A17: 13 | B17: =IF($F17="","","REQ-"&TEXT($A17,"000")) | D17: =IF($C17="","",_xlfn.XLOOKUP($C17,StrategiesSolutions[S&S ID],StrategiesSolutions[Risk ID],""))
A18: 14 | B18: =IF($F18="","","REQ-"&TEXT($A18,"000")) | D18: =IF($C18="","",_xlfn.XLOOKUP($C18,StrategiesSolutions[S&S ID],StrategiesSolutions[Risk ID],""))
... A304: 300 | B304: =IF($F304="","","REQ-"&TEXT($A304,"000")) | D304: =IF($C304="","",_xlfn.XLOOKUP($C304,StrategiesSolutions[S&S ID],StrategiesSolutions[Risk ID],""))

Sheet 13. IT DR Register
A2: One row per critical system - compare Required vs DR-capable RTO/RPO - test evidence drives the PDCA DR step | ISO 22301: 8.3.2 ICT readiness (ref. ISO/IEC 27031)
A4: No. | B4: DR ID | C4: Dependency category | D4: Dependency area | E4: Dependent System / Application | F4: Business P&S supported | G4: Required RTO | H4: Required RPO | I4: DR RTO (capable) | J4: DR RPO (capable) | K4: DR Strategy | L4: DR Site / Location | M4: Last DR Test | N4: Test Scenario | O4: Result | P4: Next Test Due | Q4: Status (auto) | R4: Gaps / Remarks | S4: RTO Compliance | T4: RPO Compliance
A5: =ROW()-4 -> 1 | B5: =IF(AND(ITDRRegister[[#This Row],[Dependency category]]="",ITDRRegister[[#This Row],[Dependency area]]=""),"","DR-"&TEXT($A5,"000")) | P5: =IF($M5="","",EDATE($M5,12)) | Q5: =IF($E5="","",IF($K5="None (gap)","GAP - no DR",IF(OR($S5="Not Assessed",$T5="Not Assessed"),"Recovery Targets Incomplete",IF($M5="","Not Tested",IF(AND($P5<>"",$P5<TODAY()),"Test Overdue",IF($O5="","Not Tested",IF($O5<>"Pass","Retest Required",IF(OR($S5<>"RTO Complied",$T5<>"RPO Complied"),"Recovery Not Compliant","Tested & Current")))))))) | S5: =IF($E5="","",IF(OR(NOT(ISNUMBER($G5)),NOT(ISNUMBER($I5))),"Not Assessed",IF($I5<=$G5,"RTO Complied","RTO Not Complied"))) | T5: =IF($E5="","",IF(OR(NOT(ISNUMBER($H5)),NOT(ISNUMBER($J5))),"Not Assessed",IF($J5<=$H5,"RPO Complied","RPO Not Complied")))
A6: =ROW()-4 -> 2 | B6: =IF(AND(ITDRRegister[[#This Row],[Dependency category]]="",ITDRRegister[[#This Row],[Dependency area]]=""),"","DR-"&TEXT($A6,"000")) | P6: =IF($M6="","",EDATE($M6,12)) | Q6: =IF($E6="","",IF($K6="None (gap)","GAP - no DR",IF(OR($S6="Not Assessed",$T6="Not Assessed"),"Recovery Targets Incomplete",IF($M6="","Not Tested",IF(AND($P6<>"",$P6<TODAY()),"Test Overdue",IF($O6="","Not Tested",IF($O6<>"Pass","Retest Required",IF(OR($S6<>"RTO Complied",$T6<>"RPO Complied"),"Recovery Not Compliant","Tested & Current")))))))) | S6: =IF($E6="","",IF(OR(NOT(ISNUMBER($G6)),NOT(ISNUMBER($I6))),"Not Assessed",IF($I6<=$G6,"RTO Complied","RTO Not Complied"))) | T6: =IF($E6="","",IF(OR(NOT(ISNUMBER($H6)),NOT(ISNUMBER($J6))),"Not Assessed",IF($J6<=$H6,"RPO Complied","RPO Not Complied")))
A7: =ROW()-4 -> 3 | B7: =IF(AND(ITDRRegister[[#This Row],[Dependency category]]="",ITDRRegister[[#This Row],[Dependency area]]=""),"","DR-"&TEXT($A7,"000")) | P7: =IF($M7="","",EDATE($M7,12)) | Q7: =IF($E7="","",IF($K7="None (gap)","GAP - no DR",IF(OR($S7="Not Assessed",$T7="Not Assessed"),"Recovery Targets Incomplete",IF($M7="","Not Tested",IF(AND($P7<>"",$P7<TODAY()),"Test Overdue",IF($O7="","Not Tested",IF($O7<>"Pass","Retest Required",IF(OR($S7<>"RTO Complied",$T7<>"RPO Complied"),"Recovery Not Compliant","Tested & Current")))))))) | S7: =IF($E7="","",IF(OR(NOT(ISNUMBER($G7)),NOT(ISNUMBER($I7))),"Not Assessed",IF($I7<=$G7,"RTO Complied","RTO Not Complied"))) | T7: =IF($E7="","",IF(OR(NOT(ISNUMBER($H7)),NOT(ISNUMBER($J7))),"Not Assessed",IF($J7<=$H7,"RPO Complied","RPO Not Complied")))
A8: =ROW()-4 -> 4 | B8: =IF(AND(ITDRRegister[[#This Row],[Dependency category]]="",ITDRRegister[[#This Row],[Dependency area]]=""),"","DR-"&TEXT($A8,"000")) | P8: =IF($M8="","",EDATE($M8,12)) | Q8: =IF($E8="","",IF($K8="None (gap)","GAP - no DR",IF(OR($S8="Not Assessed",$T8="Not Assessed"),"Recovery Targets Incomplete",IF($M8="","Not Tested",IF(AND($P8<>"",$P8<TODAY()),"Test Overdue",IF($O8="","Not Tested",IF($O8<>"Pass","Retest Required",IF(OR($S8<>"RTO Complied",$T8<>"RPO Complied"),"Recovery Not Compliant","Tested & Current")))))))) | S8: =IF($E8="","",IF(OR(NOT(ISNUMBER($G8)),NOT(ISNUMBER($I8))),"Not Assessed",IF($I8<=$G8,"RTO Complied","RTO Not Complied"))) | T8: =IF($E8="","",IF(OR(NOT(ISNUMBER($H8)),NOT(ISNUMBER($J8))),"Not Assessed",IF($J8<=$H8,"RPO Complied","RPO Not Complied")))
A9: =ROW()-4 -> 5 | B9: =IF(AND(ITDRRegister[[#This Row],[Dependency category]]="",ITDRRegister[[#This Row],[Dependency area]]=""),"","DR-"&TEXT($A9,"000")) | P9: =IF($M9="","",EDATE($M9,12)) | Q9: =IF($E9="","",IF($K9="None (gap)","GAP - no DR",IF(OR($S9="Not Assessed",$T9="Not Assessed"),"Recovery Targets Incomplete",IF($M9="","Not Tested",IF(AND($P9<>"",$P9<TODAY()),"Test Overdue",IF($O9="","Not Tested",IF($O9<>"Pass","Retest Required",IF(OR($S9<>"RTO Complied",$T9<>"RPO Complied"),"Recovery Not Compliant","Tested & Current")))))))) | S9: =IF($E9="","",IF(OR(NOT(ISNUMBER($G9)),NOT(ISNUMBER($I9))),"Not Assessed",IF($I9<=$G9,"RTO Complied","RTO Not Complied"))) | T9: =IF($E9="","",IF(OR(NOT(ISNUMBER($H9)),NOT(ISNUMBER($J9))),"Not Assessed",IF($J9<=$H9,"RPO Complied","RPO Not Complied")))
A10: =ROW()-4 -> 6 | B10: =IF(AND(ITDRRegister[[#This Row],[Dependency category]]="",ITDRRegister[[#This Row],[Dependency area]]=""),"","DR-"&TEXT($A10,"000")) | P10: =IF($M10="","",EDATE($M10,12)) | Q10: =IF($E10="","",IF($K10="None (gap)","GAP - no DR",IF(OR($S10="Not Assessed",$T10="Not Assessed"),"Recovery Targets Incomplete",IF($M10="","Not Tested",IF(AND($P10<>"",$P10<TODAY()),"Test Overdue",IF($O10="","Not Tested",IF($O10<>"Pass","Retest Required",IF(OR($S10<>"RTO Complied",$T10<>"RPO Complied"),"Recovery Not Compliant","Tested & Current")))))))) | S10: =IF($E10="","",IF(OR(NOT(ISNUMBER($G10)),NOT(ISNUMBER($I10))),"Not Assessed",IF($I10<=$G10,"RTO Complied","RTO Not Complied"))) | T10: =IF($E10="","",IF(OR(NOT(ISNUMBER($H10)),NOT(ISNUMBER($J10))),"Not Assessed",IF($J10<=$H10,"RPO Complied","RPO Not Complied")))
A11: =ROW()-4 -> 7 | B11: =IF(AND(ITDRRegister[[#This Row],[Dependency category]]="",ITDRRegister[[#This Row],[Dependency area]]=""),"","DR-"&TEXT($A11,"000")) | P11: =IF($M11="","",EDATE($M11,12)) | Q11: =IF($E11="","",IF($K11="None (gap)","GAP - no DR",IF(OR($S11="Not Assessed",$T11="Not Assessed"),"Recovery Targets Incomplete",IF($M11="","Not Tested",IF(AND($P11<>"",$P11<TODAY()),"Test Overdue",IF($O11="","Not Tested",IF($O11<>"Pass","Retest Required",IF(OR($S11<>"RTO Complied",$T11<>"RPO Complied"),"Recovery Not Compliant","Tested & Current")))))))) | S11: =IF($E11="","",IF(OR(NOT(ISNUMBER($G11)),NOT(ISNUMBER($I11))),"Not Assessed",IF($I11<=$G11,"RTO Complied","RTO Not Complied"))) | T11: =IF($E11="","",IF(OR(NOT(ISNUMBER($H11)),NOT(ISNUMBER($J11))),"Not Assessed",IF($J11<=$H11,"RPO Complied","RPO Not Complied")))
A12: =ROW()-4 -> 8 | B12: =IF(AND(ITDRRegister[[#This Row],[Dependency category]]="",ITDRRegister[[#This Row],[Dependency area]]=""),"","DR-"&TEXT($A12,"000")) | P12: =IF($M12="","",EDATE($M12,12)) | Q12: =IF($E12="","",IF($K12="None (gap)","GAP - no DR",IF(OR($S12="Not Assessed",$T12="Not Assessed"),"Recovery Targets Incomplete",IF($M12="","Not Tested",IF(AND($P12<>"",$P12<TODAY()),"Test Overdue",IF($O12="","Not Tested",IF($O12<>"Pass","Retest Required",IF(OR($S12<>"RTO Complied",$T12<>"RPO Complied"),"Recovery Not Compliant","Tested & Current")))))))) | S12: =IF($E12="","",IF(OR(NOT(ISNUMBER($G12)),NOT(ISNUMBER($I12))),"Not Assessed",IF($I12<=$G12,"RTO Complied","RTO Not Complied"))) | T12: =IF($E12="","",IF(OR(NOT(ISNUMBER($H12)),NOT(ISNUMBER($J12))),"Not Assessed",IF($J12<=$H12,"RPO Complied","RPO Not Complied")))
A13: =ROW()-4 -> 9 | B13: =IF(AND(ITDRRegister[[#This Row],[Dependency category]]="",ITDRRegister[[#This Row],[Dependency area]]=""),"","DR-"&TEXT($A13,"000")) | P13: =IF($M13="","",EDATE($M13,12)) | Q13: =IF($E13="","",IF($K13="None (gap)","GAP - no DR",IF(OR($S13="Not Assessed",$T13="Not Assessed"),"Recovery Targets Incomplete",IF($M13="","Not Tested",IF(AND($P13<>"",$P13<TODAY()),"Test Overdue",IF($O13="","Not Tested",IF($O13<>"Pass","Retest Required",IF(OR($S13<>"RTO Complied",$T13<>"RPO Complied"),"Recovery Not Compliant","Tested & Current")))))))) | S13: =IF($E13="","",IF(OR(NOT(ISNUMBER($G13)),NOT(ISNUMBER($I13))),"Not Assessed",IF($I13<=$G13,"RTO Complied","RTO Not Complied"))) | T13: =IF($E13="","",IF(OR(NOT(ISNUMBER($H13)),NOT(ISNUMBER($J13))),"Not Assessed",IF($J13<=$H13,"RPO Complied","RPO Not Complied")))
A14: =ROW()-4 -> 10 | B14: =IF(AND(ITDRRegister[[#This Row],[Dependency category]]="",ITDRRegister[[#This Row],[Dependency area]]=""),"","DR-"&TEXT($A14,"000")) | P14: =IF($M14="","",EDATE($M14,12)) | Q14: =IF($E14="","",IF($K14="None (gap)","GAP - no DR",IF(OR($S14="Not Assessed",$T14="Not Assessed"),"Recovery Targets Incomplete",IF($M14="","Not Tested",IF(AND($P14<>"",$P14<TODAY()),"Test Overdue",IF($O14="","Not Tested",IF($O14<>"Pass","Retest Required",IF(OR($S14<>"RTO Complied",$T14<>"RPO Complied"),"Recovery Not Compliant","Tested & Current")))))))) | S14: =IF($E14="","",IF(OR(NOT(ISNUMBER($G14)),NOT(ISNUMBER($I14))),"Not Assessed",IF($I14<=$G14,"RTO Complied","RTO Not Complied"))) | T14: =IF($E14="","",IF(OR(NOT(ISNUMBER($H14)),NOT(ISNUMBER($J14))),"Not Assessed",IF($J14<=$H14,"RPO Complied","RPO Not Complied")))
A15: =ROW()-4 -> 11 | B15: =IF(AND(ITDRRegister[[#This Row],[Dependency category]]="",ITDRRegister[[#This Row],[Dependency area]]=""),"","DR-"&TEXT($A15,"000")) | P15: =IF($M15="","",EDATE($M15,12)) | Q15: =IF($E15="","",IF($K15="None (gap)","GAP - no DR",IF(OR($S15="Not Assessed",$T15="Not Assessed"),"Recovery Targets Incomplete",IF($M15="","Not Tested",IF(AND($P15<>"",$P15<TODAY()),"Test Overdue",IF($O15="","Not Tested",IF($O15<>"Pass","Retest Required",IF(OR($S15<>"RTO Complied",$T15<>"RPO Complied"),"Recovery Not Compliant","Tested & Current")))))))) | S15: =IF($E15="","",IF(OR(NOT(ISNUMBER($G15)),NOT(ISNUMBER($I15))),"Not Assessed",IF($I15<=$G15,"RTO Complied","RTO Not Complied"))) | T15: =IF($E15="","",IF(OR(NOT(ISNUMBER($H15)),NOT(ISNUMBER($J15))),"Not Assessed",IF($J15<=$H15,"RPO Complied","RPO Not Complied")))
A16: =ROW()-4 -> 12 | B16: =IF(AND(ITDRRegister[[#This Row],[Dependency category]]="",ITDRRegister[[#This Row],[Dependency area]]=""),"","DR-"&TEXT($A16,"000")) | P16: =IF($M16="","",EDATE($M16,12)) | Q16: =IF($E16="","",IF($K16="None (gap)","GAP - no DR",IF(OR($S16="Not Assessed",$T16="Not Assessed"),"Recovery Targets Incomplete",IF($M16="","Not Tested",IF(AND($P16<>"",$P16<TODAY()),"Test Overdue",IF($O16="","Not Tested",IF($O16<>"Pass","Retest Required",IF(OR($S16<>"RTO Complied",$T16<>"RPO Complied"),"Recovery Not Compliant","Tested & Current")))))))) | S16: =IF($E16="","",IF(OR(NOT(ISNUMBER($G16)),NOT(ISNUMBER($I16))),"Not Assessed",IF($I16<=$G16,"RTO Complied","RTO Not Complied"))) | T16: =IF($E16="","",IF(OR(NOT(ISNUMBER($H16)),NOT(ISNUMBER($J16))),"Not Assessed",IF($J16<=$H16,"RPO Complied","RPO Not Complied")))
... A204: =ROW()-4 -> 200 | B204: =IF(AND(ITDRRegister[[#This Row],[Dependency category]]="",ITDRRegister[[#This Row],[Dependency area]]=""),"","DR-"&TEXT($A204,"000")) | P204: =IF($M204="","",EDATE($M204,12)) | Q204: =IF($E204="","",IF($K204="None (gap)","GAP - no DR",IF(OR($S204="Not Assessed",$T204="Not Assessed"),"Recovery Targets Incomplete",IF($M204="","Not Tested",IF(AND($P204<>"",$P204<TODAY()),"Test Overdue",IF($O204="","Not Tested",IF($O204<>"Pass","Retest Required",IF(OR($S204<>"RTO Complied",$T204<>"RPO Complied"),"Recovery Not Compliant","Tested & Current")))))))) | S204: =IF($E204="","",IF(OR(NOT(ISNUMBER($G204)),NOT(ISNUMBER($I204))),"Not Assessed",IF($I204<=$G204,"RTO Complied","RTO Not Complied"))) | T204: =IF($E204="","",IF(OR(NOT(ISNUMBER($H204)),NOT(ISNUMBER($J204))),"Not Assessed",IF($J204<=$H204,"RPO Complied","RPO Not Complied")))

Sheet 14. Recovery & Response
A1: Step 5 - Recovery & Response Plan
A2: ISO 22301: 8.4 Plans & procedures; 8.5 Exercise programme
A4: Keys (S&S -> BCP -> BIA) | E4: Immediate Response | G4: Risk Context (auto) | J4: Strategy & Resources (auto)
A5: No. | B5: R&R ID | C5: S&S ID | D5: Product / Service | E5: Response & Recovery Actions | F5: Supporting Plans / Procedures | G5: Dependency | H5: Risk Assumption | I5: Disruption Scenario | J5: Strategy | K5: Solution Details | L5: Planned Exercise Date | M5: Actual Exercise Date | N5: Exercise Result | O5: Next Exercise Due | P5: Exercise Status | Q5: Duplicate Check | R5: Remarks
A6: 1 | B6: =IF($C6="","","RR-"&TEXT($A6,"000")) -> RR-001 | C6: SS-030 | D6: =IF($C6="","",_xlfn.XLOOKUP($C6,StrategiesSolutions[S&S ID],StrategiesSolutions[Products / Services],"")) -> cb | G6: =IF($C6="","",_xlfn.XLOOKUP($C6,StrategiesSolutions[S&S ID],StrategiesSolutions[Dependency],"")) -> People | H6: =IF($C6="","",_xlfn.XLOOKUP($C6,StrategiesSolutions[S&S ID],StrategiesSolutions[Risk Assumption],"")) -> Workforce evacuation | I6: =IF($C6="","",_xlfn.XLOOKUP($C6,StrategiesSolutions[S&S ID],StrategiesSolutions[Disruption Scenario],"")) -> Inability to deliver the associated products/services due to [Workforce evacuation] | J6: =IF($C6="","",_xlfn.XLOOKUP($C6,StrategiesSolutions[S&S ID],StrategiesSolutions[Strategy],"")) -> Alternative Site / Relocation | K6: =IF($C6="","",_xlfn.LET(_xlpm.x,_xlfn.XLOOKUP($C6,StrategiesSolutions[S&S ID],StrategiesSolutions[Strategy Details / Do nothing Justification],""),IF(_xlpm.x=0,"",_xlpm.x))) | O6: =IF($M6="","",EDATE($M6,12)) | P6: =IF($C6="","",_xlfn.LET(_xlpm.ssStatus,_xlfn.XLOOKUP($C6,StrategiesSolutions[S&S ID],StrategiesSolutions[Status],""),IF($L6="","Not Scheduled",IF($M6="",IF($L6<TODAY(),"Overdue","Scheduled"),IF($N6="","Result Required",IF(OR($E6="",$F6="",$Q6=""),"Incomplete Exercise",IF($N6="Fail","Failed",IF(OR(OR($N6="Pass with Findings",$N6="Pass with finding"),_xlpm.ssStatus<>"Completed"),"Pass with Findings","Passed")))))))) -> Not Scheduled | Q6: =IF($C6="","",IF(COUNTIFS($C$6:$C$105,$C6,$D$6:$D$105,$D6,$E$6:$E$105,$E6)>1,"DUPLICATE","OK")) -> OK
A7: 2 | B7: =IF($C7="","","RR-"&TEXT($A7,"000")) | D7: =IF($C7="","",_xlfn.XLOOKUP($C7,StrategiesSolutions[S&S ID],StrategiesSolutions[Products / Services],"")) | G7: =IF($C7="","",_xlfn.XLOOKUP($C7,StrategiesSolutions[S&S ID],StrategiesSolutions[Dependency],"")) | H7: =IF($C7="","",_xlfn.XLOOKUP($C7,StrategiesSolutions[S&S ID],StrategiesSolutions[Risk Assumption],"")) | I7: =IF($C7="","",_xlfn.XLOOKUP($C7,StrategiesSolutions[S&S ID],StrategiesSolutions[Disruption Scenario],"")) | J7: =IF($C7="","",_xlfn.XLOOKUP($C7,StrategiesSolutions[S&S ID],StrategiesSolutions[Strategy],"")) | K7: =IF($C7="","",_xlfn.LET(_xlpm.x,_xlfn.XLOOKUP($C7,StrategiesSolutions[S&S ID],StrategiesSolutions[Strategy Details / Do nothing Justification],""),IF(_xlpm.x=0,"",_xlpm.x))) | O7: =IF($M7="","",EDATE($M7,12)) | P7: =IF($C7="","",_xlfn.LET(_xlpm.ssStatus,_xlfn.XLOOKUP($C7,StrategiesSolutions[S&S ID],StrategiesSolutions[Status],""),IF($L7="","Not Scheduled",IF($M7="",IF($L7<TODAY(),"Overdue","Scheduled"),IF($N7="","Result Required",IF(OR($E7="",$F7="",$Q7=""),"Incomplete Exercise",IF($N7="Fail","Failed",IF(OR(OR($N7="Pass with Findings",$N7="Pass with finding"),_xlpm.ssStatus<>"Completed"),"Pass with Findings","Passed")))))))) | Q7: =IF($C7="","",IF(COUNTIFS($C$6:$C$105,$C7,$D$6:$D$105,$D7,$E$6:$E$105,$E7)>1,"DUPLICATE","OK"))
A8: 3 | B8: =IF($C8="","","RR-"&TEXT($A8,"000")) | D8: =IF($C8="","",_xlfn.XLOOKUP($C8,StrategiesSolutions[S&S ID],StrategiesSolutions[Products / Services],"")) | G8: =IF($C8="","",_xlfn.XLOOKUP($C8,StrategiesSolutions[S&S ID],StrategiesSolutions[Dependency],"")) | H8: =IF($C8="","",_xlfn.XLOOKUP($C8,StrategiesSolutions[S&S ID],StrategiesSolutions[Risk Assumption],"")) | I8: =IF($C8="","",_xlfn.XLOOKUP($C8,StrategiesSolutions[S&S ID],StrategiesSolutions[Disruption Scenario],"")) | J8: =IF($C8="","",_xlfn.XLOOKUP($C8,StrategiesSolutions[S&S ID],StrategiesSolutions[Strategy],"")) | K8: =IF($C8="","",_xlfn.LET(_xlpm.x,_xlfn.XLOOKUP($C8,StrategiesSolutions[S&S ID],StrategiesSolutions[Strategy Details / Do nothing Justification],""),IF(_xlpm.x=0,"",_xlpm.x))) | O8: =IF($M8="","",EDATE($M8,12)) | P8: =IF($C8="","",_xlfn.LET(_xlpm.ssStatus,_xlfn.XLOOKUP($C8,StrategiesSolutions[S&S ID],StrategiesSolutions[Status],""),IF($L8="","Not Scheduled",IF($M8="",IF($L8<TODAY(),"Overdue","Scheduled"),IF($N8="","Result Required",IF(OR($E8="",$F8="",$Q8=""),"Incomplete Exercise",IF($N8="Fail","Failed",IF(OR(OR($N8="Pass with Findings",$N8="Pass with finding"),_xlpm.ssStatus<>"Completed"),"Pass with Findings","Passed")))))))) | Q8: =IF($C8="","",IF(COUNTIFS($C$6:$C$105,$C8,$D$6:$D$105,$D8,$E$6:$E$105,$E8)>1,"DUPLICATE","OK"))
A9: 4 | B9: =IF($C9="","","RR-"&TEXT($A9,"000")) | D9: =IF($C9="","",_xlfn.XLOOKUP($C9,StrategiesSolutions[S&S ID],StrategiesSolutions[Products / Services],"")) | G9: =IF($C9="","",_xlfn.XLOOKUP($C9,StrategiesSolutions[S&S ID],StrategiesSolutions[Dependency],"")) | H9: =IF($C9="","",_xlfn.XLOOKUP($C9,StrategiesSolutions[S&S ID],StrategiesSolutions[Risk Assumption],"")) | I9: =IF($C9="","",_xlfn.XLOOKUP($C9,StrategiesSolutions[S&S ID],StrategiesSolutions[Disruption Scenario],"")) | J9: =IF($C9="","",_xlfn.XLOOKUP($C9,StrategiesSolutions[S&S ID],StrategiesSolutions[Strategy],"")) | K9: =IF($C9="","",_xlfn.LET(_xlpm.x,_xlfn.XLOOKUP($C9,StrategiesSolutions[S&S ID],StrategiesSolutions[Strategy Details / Do nothing Justification],""),IF(_xlpm.x=0,"",_xlpm.x))) | O9: =IF($M9="","",EDATE($M9,12)) | P9: =IF($C9="","",_xlfn.LET(_xlpm.ssStatus,_xlfn.XLOOKUP($C9,StrategiesSolutions[S&S ID],StrategiesSolutions[Status],""),IF($L9="","Not Scheduled",IF($M9="",IF($L9<TODAY(),"Overdue","Scheduled"),IF($N9="","Result Required",IF(OR($E9="",$F9="",$Q9=""),"Incomplete Exercise",IF($N9="Fail","Failed",IF(OR(OR($N9="Pass with Findings",$N9="Pass with finding"),_xlpm.ssStatus<>"Completed"),"Pass with Findings","Passed")))))))) | Q9: =IF($C9="","",IF(COUNTIFS($C$6:$C$105,$C9,$D$6:$D$105,$D9,$E$6:$E$105,$E9)>1,"DUPLICATE","OK"))
A10: 5 | B10: =IF($C10="","","RR-"&TEXT($A10,"000")) | D10: =IF($C10="","",_xlfn.XLOOKUP($C10,StrategiesSolutions[S&S ID],StrategiesSolutions[Products / Services],"")) | G10: =IF($C10="","",_xlfn.XLOOKUP($C10,StrategiesSolutions[S&S ID],StrategiesSolutions[Dependency],"")) | H10: =IF($C10="","",_xlfn.XLOOKUP($C10,StrategiesSolutions[S&S ID],StrategiesSolutions[Risk Assumption],"")) | I10: =IF($C10="","",_xlfn.XLOOKUP($C10,StrategiesSolutions[S&S ID],StrategiesSolutions[Disruption Scenario],"")) | J10: =IF($C10="","",_xlfn.XLOOKUP($C10,StrategiesSolutions[S&S ID],StrategiesSolutions[Strategy],"")) | K10: =IF($C10="","",_xlfn.LET(_xlpm.x,_xlfn.XLOOKUP($C10,StrategiesSolutions[S&S ID],StrategiesSolutions[Strategy Details / Do nothing Justification],""),IF(_xlpm.x=0,"",_xlpm.x))) | O10: =IF($M10="","",EDATE($M10,12)) | P10: =IF($C10="","",_xlfn.LET(_xlpm.ssStatus,_xlfn.XLOOKUP($C10,StrategiesSolutions[S&S ID],StrategiesSolutions[Status],""),IF($L10="","Not Scheduled",IF($M10="",IF($L10<TODAY(),"Overdue","Scheduled"),IF($N10="","Result Required",IF(OR($E10="",$F10="",$Q10=""),"Incomplete Exercise",IF($N10="Fail","Failed",IF(OR(OR($N10="Pass with Findings",$N10="Pass with finding"),_xlpm.ssStatus<>"Completed"),"Pass with Findings","Passed")))))))) | Q10: =IF($C10="","",IF(COUNTIFS($C$6:$C$105,$C10,$D$6:$D$105,$D10,$E$6:$E$105,$E10)>1,"DUPLICATE","OK"))
A11: 6 | B11: =IF($C11="","","RR-"&TEXT($A11,"000")) | D11: =IF($C11="","",_xlfn.XLOOKUP($C11,StrategiesSolutions[S&S ID],StrategiesSolutions[Products / Services],"")) | G11: =IF($C11="","",_xlfn.XLOOKUP($C11,StrategiesSolutions[S&S ID],StrategiesSolutions[Dependency],"")) | H11: =IF($C11="","",_xlfn.XLOOKUP($C11,StrategiesSolutions[S&S ID],StrategiesSolutions[Risk Assumption],"")) | I11: =IF($C11="","",_xlfn.XLOOKUP($C11,StrategiesSolutions[S&S ID],StrategiesSolutions[Disruption Scenario],"")) | J11: =IF($C11="","",_xlfn.XLOOKUP($C11,StrategiesSolutions[S&S ID],StrategiesSolutions[Strategy],"")) | K11: =IF($C11="","",_xlfn.LET(_xlpm.x,_xlfn.XLOOKUP($C11,StrategiesSolutions[S&S ID],StrategiesSolutions[Strategy Details / Do nothing Justification],""),IF(_xlpm.x=0,"",_xlpm.x))) | O11: =IF($M11="","",EDATE($M11,12)) | P11: =IF($C11="","",_xlfn.LET(_xlpm.ssStatus,_xlfn.XLOOKUP($C11,StrategiesSolutions[S&S ID],StrategiesSolutions[Status],""),IF($L11="","Not Scheduled",IF($M11="",IF($L11<TODAY(),"Overdue","Scheduled"),IF($N11="","Result Required",IF(OR($E11="",$F11="",$Q11=""),"Incomplete Exercise",IF($N11="Fail","Failed",IF(OR(OR($N11="Pass with Findings",$N11="Pass with finding"),_xlpm.ssStatus<>"Completed"),"Pass with Findings","Passed")))))))) | Q11: =IF($C11="","",IF(COUNTIFS($C$6:$C$105,$C11,$D$6:$D$105,$D11,$E$6:$E$105,$E11)>1,"DUPLICATE","OK"))
A12: 7 | B12: =IF($C12="","","RR-"&TEXT($A12,"000")) | D12: =IF($C12="","",_xlfn.XLOOKUP($C12,StrategiesSolutions[S&S ID],StrategiesSolutions[Products / Services],"")) | G12: =IF($C12="","",_xlfn.XLOOKUP($C12,StrategiesSolutions[S&S ID],StrategiesSolutions[Dependency],"")) | H12: =IF($C12="","",_xlfn.XLOOKUP($C12,StrategiesSolutions[S&S ID],StrategiesSolutions[Risk Assumption],"")) | I12: =IF($C12="","",_xlfn.XLOOKUP($C12,StrategiesSolutions[S&S ID],StrategiesSolutions[Disruption Scenario],"")) | J12: =IF($C12="","",_xlfn.XLOOKUP($C12,StrategiesSolutions[S&S ID],StrategiesSolutions[Strategy],"")) | K12: =IF($C12="","",_xlfn.LET(_xlpm.x,_xlfn.XLOOKUP($C12,StrategiesSolutions[S&S ID],StrategiesSolutions[Strategy Details / Do nothing Justification],""),IF(_xlpm.x=0,"",_xlpm.x))) | O12: =IF($M12="","",EDATE($M12,12)) | P12: =IF($C12="","",_xlfn.LET(_xlpm.ssStatus,_xlfn.XLOOKUP($C12,StrategiesSolutions[S&S ID],StrategiesSolutions[Status],""),IF($L12="","Not Scheduled",IF($M12="",IF($L12<TODAY(),"Overdue","Scheduled"),IF($N12="","Result Required",IF(OR($E12="",$F12="",$Q12=""),"Incomplete Exercise",IF($N12="Fail","Failed",IF(OR(OR($N12="Pass with Findings",$N12="Pass with finding"),_xlpm.ssStatus<>"Completed"),"Pass with Findings","Passed")))))))) | Q12: =IF($C12="","",IF(COUNTIFS($C$6:$C$105,$C12,$D$6:$D$105,$D12,$E$6:$E$105,$E12)>1,"DUPLICATE","OK"))
A13: 8 | B13: =IF($C13="","","RR-"&TEXT($A13,"000")) | D13: =IF($C13="","",_xlfn.XLOOKUP($C13,StrategiesSolutions[S&S ID],StrategiesSolutions[Products / Services],"")) | G13: =IF($C13="","",_xlfn.XLOOKUP($C13,StrategiesSolutions[S&S ID],StrategiesSolutions[Dependency],"")) | H13: =IF($C13="","",_xlfn.XLOOKUP($C13,StrategiesSolutions[S&S ID],StrategiesSolutions[Risk Assumption],"")) | I13: =IF($C13="","",_xlfn.XLOOKUP($C13,StrategiesSolutions[S&S ID],StrategiesSolutions[Disruption Scenario],"")) | J13: =IF($C13="","",_xlfn.XLOOKUP($C13,StrategiesSolutions[S&S ID],StrategiesSolutions[Strategy],"")) | K13: =IF($C13="","",_xlfn.LET(_xlpm.x,_xlfn.XLOOKUP($C13,StrategiesSolutions[S&S ID],StrategiesSolutions[Strategy Details / Do nothing Justification],""),IF(_xlpm.x=0,"",_xlpm.x))) | O13: =IF($M13="","",EDATE($M13,12)) | P13: =IF($C13="","",_xlfn.LET(_xlpm.ssStatus,_xlfn.XLOOKUP($C13,StrategiesSolutions[S&S ID],StrategiesSolutions[Status],""),IF($L13="","Not Scheduled",IF($M13="",IF($L13<TODAY(),"Overdue","Scheduled"),IF($N13="","Result Required",IF(OR($E13="",$F13="",$Q13=""),"Incomplete Exercise",IF($N13="Fail","Failed",IF(OR(OR($N13="Pass with Findings",$N13="Pass with finding"),_xlpm.ssStatus<>"Completed"),"Pass with Findings","Passed")))))))) | Q13: =IF($C13="","",IF(COUNTIFS($C$6:$C$105,$C13,$D$6:$D$105,$D13,$E$6:$E$105,$E13)>1,"DUPLICATE","OK"))
